Workbook

Sheet Assumptions
A1: ALL VALUES ARE ASSUMPTIONS TO BE TESTED - NOT RESULTS. Yellow = edit me.
A2: Variable | B2: Conservative | C2: Base | D2: Optimistic | E2: Note / status
A3: Retainer base fee ($/client/mo) | B3: 750 | C3: 900 | D3: 1000 | E3: Estimate. Vendor list prices seen: $297-$599/mo software/agency-lite; AR VA $1,000-2,500/mo. Test in discovery calls.
A4: New estimates sent per client per month | B4: 25 | C4: 35 | D4: 45 | E4: Unverified. Collect from each prospect's own FSM data.
A5: Share of estimates that close AFTER our first touch | B5: 0.05 | C5: 0.08 | D5: 0.12 | E5: Unverified. Vendor claims only (e.g. 20-30% recovery of unsold HVAC estimates, unsourced). This is THE number the pilot must measure.
A6: Average closed job value ($) | B6: 5000 | C6: 7000 | D6: 9000 | E6: Unverified placeholder. Replace with prospect's real average approved-estimate value.
A7: Commission rate on attributed closed+collected jobs | B7: 0.05 | C7: 0.05 | D7: 0.05 | E7: Contract term, negotiable.
A8: Commission realization (disputes/uncollected/attribution fights) | B8: 0.7 | C8: 0.8 | D8: 0.9 | E8: Assumption.
A9: Delivery hours per client per month | B9: 24 | C9: 16 | D9: 12 | E9: Assumption: ~3-touch cadence per estimate + weekly report.
A10: Loaded hourly cost of delivery staff ($) | B10: 28 | C10: 22 | D10: 18 | E10: Assumption (contractor/VA). Owner time NOT costed.
A11: Variable tools cost per client ($/mo: SMS, VoIP minutes) | B11: 20 | C11: 20 | D11: 20 | E11: Assumption.
A12: Management/QA overhead (% of revenue) | B12: 0.08 | C12: 0.08 | D12: 0.08 | E12: Assumption.
A13: Payment processing + credits/refunds (% of revenue) | B13: 0.06 | C13: 0.06 | D13: 0.06 | E13: Assumption (~3% processing + ~3% credits).
A14: Fixed software & operating expenses ($/mo) | B14: 150 | C14: 150 | D14: 150 | E14: Assumption: CRM/spreadsheet, phone, email, bookkeeping, e-sign.
... A21: Pilot delivery hours | B21: 30 | C21: 20 | D21: 15 | E21: Assumption (backlog of unsold quotes + 30-day cadence).

Sheet Unit economics
A1: Per-client monthly economics (ESTIMATES) | B1: Conservative | C1: Base | D1: Optimistic
A2: Base fee revenue | B2: =Assumptions!B3 -> 750 | C2: =Assumptions!C3 -> 900 | D2: =Assumptions!D3 -> 1000
A3: Commission revenue (realized) | B3: =Assumptions!B4*Assumptions!B5*Assumptions!B6*Assumptions!B7*Assumptions!B8 -> 218.75 | C3: =Assumptions!C4*Assumptions!C5*Assumptions!C6*Assumptions!C7*Assumptions!C8 -> 784 | D3: =Assumptions!D4*Assumptions!D5*Assumptions!D6*Assumptions!D7*Assumptions!D8 -> 2187
A4: Total revenue per client | B4: =B2+B3 -> 968.75 | C4: =C2+C3 -> 1684 | D4: =D2+D3 -> 3187
A5: Direct labor | B5: =Assumptions!B9*Assumptions!B10 -> 672 | C5: =Assumptions!C9*Assumptions!C10 -> 352 | D5: =Assumptions!D9*Assumptions!D10 -> 216
A6: Variable tools | B6: =Assumptions!B11 -> 20 | C6: =Assumptions!C11 -> 20 | D6: =Assumptions!D11 -> 20
A7: Mgmt/QA overhead | B7: =B4*Assumptions!B12 -> 77.5 | C7: =C4*Assumptions!C12 -> 134.72 | D7: =D4*Assumptions!D12 -> 254.96
A8: Processing + credits | B8: =B4*Assumptions!B13 -> 58.125 | C8: =C4*Assumptions!C13 -> 101.04 | D8: =D4*Assumptions!D13 -> 191.22
A9: Contribution per client | B9: =B4-B5-B6-B7-B8 -> 141.125 | C9: =C4-C5-C6-C7-C8 -> 1076.24 | D9: =D4-D5-D6-D7-D8 -> 2504.82
A10: Gross margin % | B10: =IF(B4=0,0,B9/B4) -> 0.14567742 | C10: =IF(C4=0,0,C9/C4) -> 0.63909739 | D10: =IF(D4=0,0,D9/D4) -> 0.78594917
A11: Expected client lifetime (months) = 1/churn | B11: =1/Assumptions!B15 -> 12.5 | C11: =1/Assumptions!C15 -> 20 | D11: =1/Assumptions!D15 -> 33.333333
A12: Lifetime contribution (LTV, before CAC) | B12: =B9*B11 -> 1764.0625 | C12: =C9*C11 -> 21524.8 | D12: =D9*D11 -> 83494
A13: Cold contacts per retained client | B13: =Assumptions!B16/Assumptions!B17 -> 400 | C13: =Assumptions!C16/Assumptions!C17 -> 100 | D13: =Assumptions!D16/Assumptions!D17 -> 45.454545
A14: Owner sales hours per retained client (time cost) | B14: =B13*Assumptions!B18/60 -> 40 | C14: =C13*Assumptions!C18/60 -> 10 | D14: =D13*Assumptions!D18/60 -> 4.5454545
A15: Pilot cash margin (fee - delivery cost; commission excluded) | B15: =Assumptions!B20-Assumptions!B21*Assumptions!B10 -> -90 | C15: =Assumptions!C20-Assumptions!C21*Assumptions!C10 -> 310 | D15: =Assumptions!D20-Assumptions!D21*Assumptions!D10 -> 480

Sheet Targets
A1: Clients needed for monthly OPERATING profit (before taxes). ESTIMATES.
A2: Target operating profit/mo | B2: Conservative | C2: Base | D2: Optimistic
A3: 1000 | B3: =ROUNDUP(($A3+Assumptions!B14)/'Unit economics'!B9,0) -> 9 | C3: =ROUNDUP(($A3+Assumptions!C14)/'Unit economics'!C9,0) -> 2 | D3: =ROUNDUP(($A3+Assumptions!D14)/'Unit economics'!D9,0) -> 1
A4: 5000 | B4: =ROUNDUP(($A4+Assumptions!B14)/'Unit economics'!B9,0) -> 37 | C4: =ROUNDUP(($A4+Assumptions!C14)/'Unit economics'!C9,0) -> 5 | D4: =ROUNDUP(($A4+Assumptions!D14)/'Unit economics'!D9,0) -> 3
A5: 12000 | B5: =ROUNDUP(($A5+Assumptions!B14)/'Unit economics'!B9,0) -> 87 | C5: =ROUNDUP(($A5+Assumptions!C14)/'Unit economics'!C9,0) -> 12 | D5: =ROUNDUP(($A5+Assumptions!D14)/'Unit economics'!D9,0) -> 5
A7: Operating profit at N clients | B7: Conservative | C7: Base | D7: Optimistic
A8: 1 | B8: =$A8*'Unit economics'!B9-Assumptions!B14 -> -8.875 | C8: =$A8*'Unit economics'!C9-Assumptions!C14 -> 926.24 | D8: =$A8*'Unit economics'!D9-Assumptions!D14 -> 2354.82
A9: 3 | B9: =$A9*'Unit economics'!B9-Assumptions!B14 -> 273.375 | C9: =$A9*'Unit economics'!C9-Assumptions!C14 -> 3078.72 | D9: =$A9*'Unit economics'!D9-Assumptions!D14 -> 7364.46
A10: 5 | B10: =$A10*'Unit economics'!B9-Assumptions!B14 -> 555.625 | C10: =$A10*'Unit economics'!C9-Assumptions!C14 -> 5231.2 | D10: =$A10*'Unit economics'!D9-Assumptions!D14 -> 12374.1
A11: 10 | B11: =$A11*'Unit economics'!B9-Assumptions!B14 -> 1261.25 | C11: =$A11*'Unit economics'!C9-Assumptions!C14 -> 10612.4 | D11: =$A11*'Unit economics'!D9-Assumptions!D14 -> 24898.2
A12: 15 | B12: =$A12*'Unit economics'!B9-Assumptions!B14 -> 1966.875 | C12: =$A12*'Unit economics'!C9-Assumptions!C14 -> 15993.6 | D12: =$A12*'Unit economics'!D9-Assumptions!D14 -> 37422.3
A13: 20 | B13: =$A13*'Unit economics'!B9-Assumptions!B14 -> 2672.5 | C13: =$A13*'Unit economics'!C9-Assumptions!C14 -> 21374.8 | D13: =$A13*'Unit economics'!D9-Assumptions!D14 -> 49946.4
A14: 30 | B14: =$A14*'Unit economics'!B9-Assumptions!B14 -> 4083.75 | C14: =$A14*'Unit economics'!C9-Assumptions!C14 -> 32137.2 | D14: =$A14*'Unit economics'!D9-Assumptions!D14 -> 74994.6
A16: Owner take-home after placeholder tax at N clients | B16: Conservative | C16: Base | D16: Optimistic
A17: 1 | B17: =MAX(0,$A17*'Unit economics'!B9-Assumptions!B14)*(1-Assumptions!B19) -> 0 | C17: =MAX(0,$A17*'Unit economics'!C9-Assumptions!C14)*(1-Assumptions!C19) -> 648.368 | D17: =MAX(0,$A17*'Unit economics'!D9-Assumptions!D14)*(1-Assumptions!D19) -> 1648.374
A18: 3 | B18: =MAX(0,$A18*'Unit economics'!B9-Assumptions!B14)*(1-Assumptions!B19) -> 191.3625 | C18: =MAX(0,$A18*'Unit economics'!C9-Assumptions!C14)*(1-Assumptions!C19) -> 2155.104 | D18: =MAX(0,$A18*'Unit economics'!D9-Assumptions!D14)*(1-Assumptions!D19) -> 5155.122
A19: 5 | B19: =MAX(0,$A19*'Unit economics'!B9-Assumptions!B14)*(1-Assumptions!B19) -> 388.9375 | C19: =MAX(0,$A19*'Unit economics'!C9-Assumptions!C14)*(1-Assumptions!C19) -> 3661.84 | D19: =MAX(0,$A19*'Unit economics'!D9-Assumptions!D14)*(1-Assumptions!D19) -> 8661.87
A20: 10 | B20: =MAX(0,$A20*'Unit economics'!B9-Assumptions!B14)*(1-Assumptions!B19) -> 882.875 | C20: =MAX(0,$A20*'Unit economics'!C9-Assumptions!C14)*(1-Assumptions!C19) -> 7428.68 | D20: =MAX(0,$A20*'Unit economics'!D9-Assumptions!D14)*(1-Assumptions!D19) -> 17428.74
A21: 15 | B21: =MAX(0,$A21*'Unit economics'!B9-Assumptions!B14)*(1-Assumptions!B19) -> 1376.8125 | C21: =MAX(0,$A21*'Unit economics'!C9-Assumptions!C14)*(1-Assumptions!C19) -> 11195.52 | D21: =MAX(0,$A21*'Unit economics'!D9-Assumptions!D14)*(1-Assumptions!D19) -> 26195.61
A22: 20 | B22: =MAX(0,$A22*'Unit economics'!B9-Assumptions!B14)*(1-Assumptions!B19) -> 1870.75 | C22: =MAX(0,$A22*'Unit economics'!C9-Assumptions!C14)*(1-Assumptions!C19) -> 14962.36 | D22: =MAX(0,$A22*'Unit economics'!D9-Assumptions!D14)*(1-Assumptions!D19) -> 34962.48
A23: 30 | B23: =MAX(0,$A23*'Unit economics'!B9-Assumptions!B14)*(1-Assumptions!B19) -> 2858.625 | C23: =MAX(0,$A23*'Unit economics'!C9-Assumptions!C14)*(1-Assumptions!C19) -> 22496.04 | D23: =MAX(0,$A23*'Unit economics'!D9-Assumptions!D14)*(1-Assumptions!D19) -> 52496.22
A25: Delivery hours/mo at N clients (capacity check; 1 FTE ~ 140 productive hrs) | B25: Conservative | C25: Base | D25: Optimistic
A26: 5 | B26: =$A26*Assumptions!B9 -> 120 | C26: =$A26*Assumptions!C9 -> 80 | D26: =$A26*Assumptions!D9 -> 60
A27: 10 | B27: =$A27*Assumptions!B9 -> 240 | C27: =$A27*Assumptions!C9 -> 160 | D27: =$A27*Assumptions!D9 -> 120
A28: 20 | B28: =$A28*Assumptions!B9 -> 480 | C28: =$A28*Assumptions!C9 -> 320 | D28: =$A28*Assumptions!D9 -> 240
A29: 30 | B29: =$A29*Assumptions!B9 -> 720 | C29: =$A29*Assumptions!C9 -> 480 | D29: =$A29*Assumptions!D9 -> 360
