Workbook
Name BizName: 'SETTINGS'!$B$6
Name OwnerName: 'SETTINGS'!$B$7
Name BizPhone: 'SETTINGS'!$B$8
Name BizEmail: 'SETTINGS'!$B$9
Name BizWeb: 'SETTINGS'!$B$10
Name BizArea: 'SETTINGS'!$B$11
Name AsOfInput: 'SETTINGS'!$B$13
Name AsOf: 'SETTINGS'!$B$14
Name RMInput: 'SETTINGS'!$B$15
Name ReportMonth: 'SETTINGS'!$B$16
Name ReportYear: 'SETTINGS'!$B$17
Name PayRate: 'SETTINGS'!$B$19
Name Burden: 'SETTINGS'!$B$20
Name SupHr: 'SETTINGS'!$B$21
Name MileRate: 'SETTINGS'!$B$22
Name TravelMin: 'SETTINGS'!$B$23
Name FeePct: 'SETTINGS'!$B$24
Name TaxDefault: 'SETTINGS'!$B$25
Name OverheadHr: 'SETTINGS'!$B$26
Name TargetMargin: 'SETTINGS'!$B$28
Name MinJob: 'SETTINGS'!$B$29
Name SoonDays: 'SETTINGS'!$B$30
Name ReactDays: 'SETTINGS'!$B$31
Name QCPass: 'SETTINGS'!$B$32
Name ReviewWait: 'SETTINGS'!$B$33

Sheet START HERE
B1: CLEANING BUSINESS AI GROWTH OS
B2: Run your cleaning business from lead to payment in one connected system.
B3: DEMO FILE — every name, address and number is fictional sample data. Explore it, then use the CLEAN file for your business.
B5: SET UP IN 5 STEPS (about 30 minutes) | E5: COLOR LEGEND
B6: 1. SETTINGS | C6: Enter your business details. Replace the example labor, supply, vehicle and fee assumptions with your own. Leave the as-of date BLANK. | E6: Type here
B7: 2. STAFF & TASKS | C7: Add each worker's name and pay rate (the owner too, if you clean). | E7: Key setting / input
B8: 3. PRICING | C8: Adjust billing rates, time assumptions and add-ons until the rate card matches how you want to price. Test a few quotes. | E8: Automatic — don't type
B9: 4. CUSTOMERS & PROPERTIES | C9: Add current customers and their properties (square feet, bedrooms and bathrooms power automatic time estimates). | E9: Column header you fill
B10: 5. RECURRING & JOBS | C10: Add recurring plans, then your upcoming jobs. From then on: log payments in REVENUE and check the DASHBOARD daily. | E10: Automatic column header ⚙
E11: Needs attention
B12: DAILY FLOW: Lead → Quote → Book → Schedule → Clean → Inspect → Get paid → Review → Referral → Repeat | E12: Below target
E13: Good / done
B14: GET STARTED
B15: START HERE → | C15: This page: setup steps, map and color legend.
B16: DASHBOARD → | C16: Executive dashboard: money, pipeline, operations, reputation and today's action list. | E16: GOLDEN RULES
B17: SETTINGS → | C17: Business details, cost assumptions, targets, dates and all dropdown lists. | E17: • Never type in gray cells or ⚙ columns.
E18: • Keep customer names, property labels and staff names unique.
B19: WIN THE CUSTOMER | E19: • Use dropdowns — they keep the links working.
B20: LEADS → | C20: Lead CRM and sales pipeline: 8 stages, automatic follow-up status and outcome. | E20: • Filter freely; sort a sheet only by selecting the whole table.
B21: QUOTE BUILDER → | C21: Price one job: price, labor cost, direct costs, gross profit, margin and break-even. | E21: • Add rows by typing in the next empty row (1,500 job rows included).
B22: PRICING → | C22: Your pricing assumptions by cleaning type, condition, frequency and add-ons + rate card. | E22: • Back up weekly (File → Save a copy).
B23: CUSTOMERS → | C23: Customer list with lifetime revenue, balance due and a suggested next action. | E23: • Numbers are estimates from your assumptions — not tax, legal or accounting advice.
B24: PROPERTIES → | C24: Property details (size, rooms, access, pets) that feed automatic time estimates.
E25: INCLUDED WITH THIS SYSTEM
B26: DO THE WORK | E26: ✓ Quick Start Guide (PDF)
B27: JOBS → | C27: Every job: schedule, worker, hours, price, payment status and estimated profit. | E27: ✓ Full User Guide (PDF)
B28: RECURRING → | C28: Recurring plans: next visit due, booking status and recurring revenue. | E28: ✓ AI Workflow Library — 18 workflows (PDF)
B29: SCHEDULE → | C29: Weekly calendar built from JOBS + recurring visits that need booking. | E29: ✓ Client Forms — 14 editable templates
B30: STAFF & TASKS → | C30: Team roster with pay rates and monthly output, plus a task assignment list. | E30: ✓ Marketing Kit — print + social templates
B31: SUPPLIES → | C31: Supply inventory with reorder alerts.
B32: QUALITY CONTROL → | C32: Inspection log with pass/fail scores, rework tracking and an issue log.
B33: QC CHECKLISTS → | C33: Six printable checklists: standard, deep, move, Airbnb, commercial, final inspection.
B35: GET PAID & KNOW YOUR NUMBERS
B36: REVENUE → | C36: Payments received, linked to jobs, with processing-fee estimates.
B37: EXPENSES → | C37: Business expenses with overhead flag.
B38: MILEAGE → | C38: Trip log that feeds vehicle cost into each job.
B39: PROFITABILITY → | C39: Profit by service, worker and customer type, for any period.
B40: MONTHLY → | C40: Twelve-month performance: sales, operations, money and growth.
B42: GROW
B43: FOLLOW-UPS → | C43: Automatic list of leads to chase and unpaid jobs, plus your follow-up log.
B44: REVIEWS → | C44: Review requests, ratings and reply tracking.
B45: REFERRALS → | C45: Referrals, rewards owed and revenue from referrals.

Sheet DASHBOARD
B1: ="EXECUTIVE DASHBOARD · "&UPPER(BizName)
B2: ="Reporting month: "&TEXT(ReportMonth,"mmmm yyyy")&" · As of "&TEXT(AsOf,"mmm d, yyyy")&" · Change dates in SETTINGS"
B3: ← Start Here | D3: Settings →
B4: MONEY — REPORTING MONTH
B5: REVENUE | D5: JOB GROSS PROFIT | F5: GROSS MARGIN | H5: EST. OPERATING PROFIT | J5: PAYMENTS COLLECTED | L5: UNPAID BALANCES (ALL)
B6: =INDEX(MONTHLY!$B$19:$M$19,MONTH(ReportMonth)) | D6: =INDEX(MONTHLY!$B$24:$M$24,MONTH(ReportMonth)) | F6: =INDEX(MONTHLY!$B$25:$M$25,MONTH(ReportMonth)) | H6: =INDEX(MONTHLY!$B$27:$M$27,MONTH(ReportMonth)) | J6: =INDEX(MONTHLY!$B$31:$M$31,MONTH(ReportMonth)) | L6: =SUM('JOBS'!$U$5:$U$1504)
B7: =IFERROR(IF(OR(IF(MONTH(ReportMonth)=1,"",INDEX(MONTHLY!$B$19:$M$19,MONTH(ReportMonth)-1))="",N(IF(MONTH(ReportMonth)=1,"",INDEX(MONTHLY!$B$19:$M$19,MONTH(ReportMonth)-1)))=0),"No prior-month comparison",TEXT(INDEX(MONTHLY!$B$19:$M$19,MONTH(ReportMonth))/IF(MONTH(ReportMonth)=1,"",INDEX(MONTHLY!$B$19:$M$19,MONTH(ReportMonth)-1))-1,"+0%;-0%;0%")&" vs last month"),"No prior-month comparison") | D7: =IFERROR(IF(OR(IF(MONTH(ReportMonth)=1,"",INDEX(MONTHLY!$B$24:$M$24,MONTH(ReportMonth)-1))="",N(IF(MONTH(ReportMonth)=1,"",INDEX(MONTHLY!$B$24:$M$24,MONTH(ReportMonth)-1)))=0),"No prior-month comparison",TEXT(INDEX(MONTHLY!$B$24:$M$24,MONTH(ReportMonth))/IF(MONTH(ReportMonth)=1,"",INDEX(MONTHLY!$B$24:$M$24,MONTH(ReportMonth)-1))-1,"+0%;-0%;0%")&" vs last month"),"No prior-month comparison") | F7: ="Target: "&TEXT(TargetMargin,"0%") | H7: ="After overhead expenses" | J7: ="Incl. tax, by payment date" | L7: =COUNTIF('JOBS'!$V$5:$V$1504,"Unpaid")+COUNTIF('JOBS'!$V$5:$V$1504,"Partial")&" jobs with a balance"
B9: SALES PIPELINE
B10: NEW LEADS | D10: QUOTES GIVEN | F10: LEADS BOOKED | H10: CONVERSION RATE | J10: AVERAGE QUOTE | L10: FOLLOW-UPS DUE NOW
B11: =INDEX(MONTHLY!$B$6:$M$6,MONTH(ReportMonth)) | D11: =INDEX(MONTHLY!$B$7:$M$7,MONTH(ReportMonth)) | F11: =INDEX(MONTHLY!$B$8:$M$8,MONTH(ReportMonth)) | H11: =INDEX(MONTHLY!$B$9:$M$9,MONTH(ReportMonth)) | J11: =INDEX(MONTHLY!$B$10:$M$10,MONTH(ReportMonth)) | L11: =COUNTIF('LEADS'!$P$5:$P$504,"Overdue")+COUNTIF('LEADS'!$P$5:$P$504,"Due today")+COUNTIFS('FOLLOW-UPS'!$G$25:$G$324,"Open",'FOLLOW-UPS'!$A$25:$A$324,"<="&AsOf)
B12: =IFERROR(IF(OR(IF(MONTH(ReportMonth)=1,"",INDEX(MONTHLY!$B$6:$M$6,MONTH(ReportMonth)-1))="",N(IF(MONTH(ReportMonth)=1,"",INDEX(MONTHLY!$B$6:$M$6,MONTH(ReportMonth)-1)))=0),"No prior-month comparison",TEXT(INDEX(MONTHLY!$B$6:$M$6,MONTH(ReportMonth))/IF(MONTH(ReportMonth)=1,"",INDEX(MONTHLY!$B$6:$M$6,MONTH(ReportMonth)-1))-1,"+0%;-0%;0%")&" vs last month"),"No prior-month comparison") | D12: ="Leads added this month with a quote" | F12: ="From this month's leads" | H12: ="Booked ÷ new leads" | J12: ="This month's quotes" | L12: ="Overdue + due today"
B14: OPERATIONS
B15: JOBS COMPLETED | D15: AVERAGE JOB VALUE | F15: REVENUE / LABOR HOUR | H15: JOBS NEXT 7 DAYS | J15: ACTIVE RECURRING PLANS | L15: RECURRING MONTHLY VALUE
B16: =INDEX(MONTHLY!$B$12:$M$12,MONTH(ReportMonth)) | D16: =INDEX(MONTHLY!$B$29:$M$29,MONTH(ReportMonth)) | F16: =INDEX(MONTHLY!$B$30:$M$30,MONTH(ReportMonth)) | H16: =COUNTIFS('JOBS'!$B$5:$B$1504,">="&AsOf,'JOBS'!$B$5:$B$1504,"<="&AsOf+7,'JOBS'!$O$5:$O$1504,"Scheduled") | J16: =COUNTIF('RECURRING'!$J$5:$J$154,"Active") | L16: =SUM('RECURRING'!$R$5:$R$154)
B17: =IFERROR(IF(OR(IF(MONTH(ReportMonth)=1,"",INDEX(MONTHLY!$B$12:$M$12,MONTH(ReportMonth)-1))="",N(IF(MONTH(ReportMonth)=1,"",INDEX(MONTHLY!$B$12:$M$12,MONTH(ReportMonth)-1)))=0),"No prior-month comparison",TEXT(INDEX(MONTHLY!$B$12:$M$12,MONTH(ReportMonth))/IF(MONTH(ReportMonth)=1,"",INDEX(MONTHLY!$B$12:$M$12,MONTH(ReportMonth)-1))-1,"+0%;-0%;0%")&" vs last month"),"No prior-month comparison") | D17: ="Revenue ÷ jobs" | F17: ="All workers combined" | H17: ="Scheduled in JOBS" | J17: =SUMPRODUCT(('CUSTOMERS'!$P$5:$P$404="Yes")*1)&" recurring clients" | L17: ="Active plans, per month"
B19: REPUTATION & QUALITY
B20: REVIEWS RECEIVED | D20: AVERAGE RATING | F20: REFERRALS | H20: QC PASS RATE | J20: OPEN ISSUES | L20: CUSTOMERS TO REACTIVATE
B21: =INDEX(MONTHLY!$B$34:$M$34,MONTH(ReportMonth)) | D21: =IFERROR(AVERAGEIFS('REVIEWS'!$G$5:$G$504,'REVIEWS'!$E$5:$E$504,"Received"),"") | F21: =INDEX(MONTHLY!$B$36:$M$36,MONTH(ReportMonth)) | H21: =IFERROR(COUNTIFS('QUALITY CONTROL'!$P$5:$P$304,ReportMonth,'QUALITY CONTROL'!$N$5:$N$304,"Pass")/COUNTIFS('QUALITY CONTROL'!$P$5:$P$304,ReportMonth,'QUALITY CONTROL'!$N$5:$N$304,"?*"),"") | J21: =COUNTIF('QUALITY CONTROL'!$H$312:$H$461,"Open")+COUNTIF('QUALITY CONTROL'!$H$312:$H$461,"In progress") | L21: =COUNTIF('CUSTOMERS'!$R$5:$R$404,"Reactivate")
B22: ="This month" | D22: ="All-time, received reviews" | F22: =COUNTIF('REFERRALS'!$E$5:$E$204,"Booked")&" booked all-time" | H22: ="Inspections this month" | J22: ="From the issue log" | L22: ="No job in "&ReactDays&"+ days"
B24: ACTION CENTER — what needs attention today | I24: PIPELINE BY STAGE (all leads, current stage)
B25: Leads overdue or due for follow-up | F25: =COUNTIF('LEADS'!$P$5:$P$504,"Overdue")+COUNTIF('LEADS'!$P$5:$P$504,"Due today") | G25: Open Follow-Ups → | I25: Stage | K25: Leads | M25: Quote Value
B26: Other follow-ups overdue / due (your log) | F26: =COUNTIFS('FOLLOW-UPS'!$G$25:$G$324,"Open",'FOLLOW-UPS'!$A$25:$A$324,"<="&AsOf) | G26: Open Follow-Ups → | I26: New Lead | K26: =COUNTIF('LEADS'!$J$5:$J$504,I26) | M26: =SUMIF('LEADS'!$J$5:$J$504,I26,'LEADS'!$I$5:$I$504)
B27: Completed jobs not fully paid | F27: =COUNTIF('JOBS'!$V$5:$V$1504,"Unpaid")+COUNTIF('JOBS'!$V$5:$V$1504,"Partial") | G27: Open Follow-Ups → | I27: Contacted | K27: =COUNTIF('LEADS'!$J$5:$J$504,I27) | M27: =SUMIF('LEADS'!$J$5:$J$504,I27,'LEADS'!$I$5:$I$504)
B28: Recurring visits that need booking | F28: =SUM('RECURRING'!$T$5:$T$154) | G28: Open Schedule → | I28: Quote Requested | K28: =COUNTIF('LEADS'!$J$5:$J$504,I28) | M28: =SUMIF('LEADS'!$J$5:$J$504,I28,'LEADS'!$I$5:$I$504)
B29: Booked leads missing from CUSTOMERS | F29: =COUNTIF('LEADS'!$R$5:$R$504,"Add to CUSTOMERS") | G29: Open Leads → | I29: Quote Sent | K29: =COUNTIF('LEADS'!$J$5:$J$504,I29) | M29: =SUMIF('LEADS'!$J$5:$J$504,I29,'LEADS'!$I$5:$I$504)
B30: Review requests needing a reminder or reply | F30: =COUNTIF('REVIEWS'!$K$5:$K$504,"Send reminder")+COUNTIF('REVIEWS'!$K$5:$K$504,"Reply to review") | G30: Open Reviews → | I30: Follow-Up | K30: =COUNTIF('LEADS'!$J$5:$J$504,I30) | M30: =SUMIF('LEADS'!$J$5:$J$504,I30,'LEADS'!$I$5:$I$504)
B31: Referral rewards owed | F31: =COUNTIF('REFERRALS'!$G$5:$G$204,"Owed") | G31: Open Referrals → | I31: Booked | K31: =COUNTIF('LEADS'!$J$5:$J$504,I31) | M31: =SUMIF('LEADS'!$J$5:$J$504,I31,'LEADS'!$I$5:$I$504)
B32: Rework jobs still open | F32: =COUNTIF('QUALITY CONTROL'!$O$5:$O$304,"Rework open") | G32: Open Quality Control → | I32: Recurring Client | K32: =COUNTIF('LEADS'!$J$5:$J$504,I32) | M32: =SUMIF('LEADS'!$J$5:$J$504,I32,'LEADS'!$I$5:$I$504)
B33: Supplies at or below reorder level | F33: =COUNTIF('SUPPLIES'!$K$5:$K$104,"Reorder") | G33: Open Supplies → | I33: Lost/Declined | K33: =COUNTIF('LEADS'!$J$5:$J$504,I33) | M33: =SUMIF('LEADS'!$J$5:$J$504,I33,'LEADS'!$I$5:$I$504)
B34: Overdue staff tasks | F34: =COUNTIF('STAFF & TASKS'!$H$31:$H$230,"Overdue") | G34: Open Staff & Tasks →
B37: TRENDS
B54: All figures come from your logs and your assumptions. They are management estimates, not accounting, tax or legal advice.

Sheet LEADS
A1: LEAD CRM & SALES PIPELINE
A2: One row per lead. Move the Stage as the lead progresses. Follow-up status, outcome and 'add to customers' reminders are automatic.
A3: ← Start Here | B3: Dashboard →
A4: Lead ID | B4: Date Added | C4: Name | D4: Phone | E4: Email | F4: Lead Source | G4: Requested Service | H4: Area / Property Notes | I4: Quote Value ($) | J4: Stage | K4: Last Contact | L4: Next Follow-Up | M4: Lost Reason | N4: Notes | O4: Booking Outcome ⚙ | P4: Follow-Up Status ⚙ | Q4: Days Since Added ⚙ | R4: Customer Record ⚙ | S4: Open? (1/0) ⚙ | T4: Month ⚙ | U4: Follow-Up Order ⚙
A5: L-0001 | B5: 46024 | C5: Dana Collins | D5: 555-0109 | E5: dana.collins@example.com | F5: Google Business Profile | G5: Deep Clean | H5: Lakeview (fictional) | I5: 450 | J5: Recurring Client | K5: 46025 | O5: =IF(C5="","",IF(OR(J5="Booked",J5="Recurring Client"),"Booked",IF(J5="Lost/Declined","Lost","Open"))) | P5: =IF(C5="","",IF(S5=0,"—",IF(L5="","Set date",IF(L5<AsOf,"Overdue",IF(L5=AsOf,"Due today",IF(L5<=AsOf+SoonDays,"Due soon","Scheduled")))))) | Q5: =IF(C5="","",IF(B5="","",AsOf-B5)) | R5: =IF(C5="","",IF(O5<>"Booked","",IF(COUNTIF('CUSTOMERS'!$B$5:$B$404,C5)>0,"✓ In CUSTOMERS","Add to CUSTOMERS"))) | S5: =IF(C5="","",IF(OR(J5="Booked",J5="Recurring Client",J5="Lost/Declined"),0,1)) | T5: =IF(B5="","",DATE(YEAR(B5),MONTH(B5),1)) | U5: =IF(OR(S5<>1,L5=""),"",COUNTIFS('LEADS'!$S$5:$S$504,1,'LEADS'!$L$5:$L$504,"<"&L5)+COUNTIFS($S$5:S5,1,$L$5:L5,L5))
A6: L-0002 | B6: 46030 | C6: Lane Northcott | D6: 555-0113 | E6: lane.northcott@example.com | F6: Google Business Profile | G6: Deep Clean | H6: Lakeview (fictional) | I6: 345 | J6: Recurring Client | K6: 46031 | O6: =IF(C6="","",IF(OR(J6="Booked",J6="Recurring Client"),"Booked",IF(J6="Lost/Declined","Lost","Open"))) | P6: =IF(C6="","",IF(S6=0,"—",IF(L6="","Set date",IF(L6<AsOf,"Overdue",IF(L6=AsOf,"Due today",IF(L6<=AsOf+SoonDays,"Due soon","Scheduled")))))) | Q6: =IF(C6="","",IF(B6="","",AsOf-B6)) | R6: =IF(C6="","",IF(O6<>"Booked","",IF(COUNTIF('CUSTOMERS'!$B$5:$B$404,C6)>0,"✓ In CUSTOMERS","Add to CUSTOMERS"))) | S6: =IF(C6="","",IF(OR(J6="Booked",J6="Recurring Client",J6="Lost/Declined"),0,1)) | T6: =IF(B6="","",DATE(YEAR(B6),MONTH(B6),1)) | U6: =IF(OR(S6<>1,L6=""),"",COUNTIFS('LEADS'!$S$5:$S$504,1,'LEADS'!$L$5:$L$504,"<"&L6)+COUNTIFS($S$5:S6,1,$L$5:L6,L6))
A7: L-0003 | B7: 46032 | C7: Elliot Collins | D7: 555-0150 | E7: elliot.collins@example.com | F7: Facebook | G7: Move-In/Move-Out | H7: Riverbend (fictional) | I7: 340 | J7: Lost/Declined | K7: 46034 | M7: Price | O7: =IF(C7="","",IF(OR(J7="Booked",J7="Recurring Client"),"Booked",IF(J7="Lost/Declined","Lost","Open"))) | P7: =IF(C7="","",IF(S7=0,"—",IF(L7="","Set date",IF(L7<AsOf,"Overdue",IF(L7=AsOf,"Due today",IF(L7<=AsOf+SoonDays,"Due soon","Scheduled")))))) | Q7: =IF(C7="","",IF(B7="","",AsOf-B7)) | R7: =IF(C7="","",IF(O7<>"Booked","",IF(COUNTIF('CUSTOMERS'!$B$5:$B$404,C7)>0,"✓ In CUSTOMERS","Add to CUSTOMERS"))) | S7: =IF(C7="","",IF(OR(J7="Booked",J7="Recurring Client",J7="Lost/Declined"),0,1)) | T7: =IF(B7="","",DATE(YEAR(B7),MONTH(B7),1)) | U7: =IF(OR(S7<>1,L7=""),"",COUNTIFS('LEADS'!$S$5:$S$504,1,'LEADS'!$L$5:$L$504,"<"&L7)+COUNTIFS($S$5:S7,1,$L$5:L7,L7))
A8: L-0004 | B8: 46033 | C8: Micah Quigley | D8: 555-0141 | E8: micah.quigley@example.com | F8: Flyer / Door Hanger | G8: Standard Clean | H8: Sampletown | I8: 160 | J8: Lost/Declined | K8: 46040 | M8: Price | O8: =IF(C8="","",IF(OR(J8="Booked",J8="Recurring Client"),"Booked",IF(J8="Lost/Declined","Lost","Open"))) | P8: =IF(C8="","",IF(S8=0,"—",IF(L8="","Set date",IF(L8<AsOf,"Overdue",IF(L8=AsOf,"Due today",IF(L8<=AsOf+SoonDays,"Due soon","Scheduled")))))) | Q8: =IF(C8="","",IF(B8="","",AsOf-B8)) | R8: =IF(C8="","",IF(O8<>"Booked","",IF(COUNTIF('CUSTOMERS'!$B$5:$B$404,C8)>0,"✓ In CUSTOMERS","Add to CUSTOMERS"))) | S8: =IF(C8="","",IF(OR(J8="Booked",J8="Recurring Client",J8="Lost/Declined"),0,1)) | T8: =IF(B8="","",DATE(YEAR(B8),MONTH(B8),1)) | U8: =IF(OR(S8<>1,L8=""),"",COUNTIFS('LEADS'!$S$5:$S$504,1,'LEADS'!$L$5:$L$504,"<"&L8)+COUNTIFS($S$5:S8,1,$L$5:L8,L8))
A9: L-0005 | B9: 46035 | C9: Dana Oakes | D9: 555-0129 | E9: dana.oakes@example.com | F9: Facebook | G9: Airbnb Turnover | H9: North Sampletown | I9: 135 | J9: Booked | K9: 46036 | O9: =IF(C9="","",IF(OR(J9="Booked",J9="Recurring Client"),"Booked",IF(J9="Lost/Declined","Lost","Open"))) | P9: =IF(C9="","",IF(S9=0,"—",IF(L9="","Set date",IF(L9<AsOf,"Overdue",IF(L9=AsOf,"Due today",IF(L9<=AsOf+SoonDays,"Due soon","Scheduled")))))) | Q9: =IF(C9="","",IF(B9="","",AsOf-B9)) | R9: =IF(C9="","",IF(O9<>"Booked","",IF(COUNTIF('CUSTOMERS'!$B$5:$B$404,C9)>0,"✓ In CUSTOMERS","Add to CUSTOMERS"))) | S9: =IF(C9="","",IF(OR(J9="Booked",J9="Recurring Client",J9="Lost/Declined"),0,1)) | T9: =IF(B9="","",DATE(YEAR(B9),MONTH(B9),1)) | U9: =IF(OR(S9<>1,L9=""),"",COUNTIFS('LEADS'!$S$5:$S$504,1,'LEADS'!$L$5:$L$504,"<"&L9)+COUNTIFS($S$5:S9,1,$L$5:L9,L9))
A10: L-0006 | B10: 46036 | C10: Taylor Quigley | D10: 555-0112 | E10: taylor.quigley@example.com | F10: Flyer / Door Hanger | G10: Deep Clean | H10: Sampletown | I10: 330 | J10: Recurring Client | K10: 46037 | O10: =IF(C10="","",IF(OR(J10="Booked",J10="Recurring Client"),"Booked",IF(J10="Lost/Declined","Lost","Open"))) | P10: =IF(C10="","",IF(S10=0,"—",IF(L10="","Set date",IF(L10<AsOf,"Overdue",IF(L10=AsOf,"Due today",IF(L10<=AsOf+SoonDays,"Due soon","Scheduled")))))) | Q10: =IF(C10="","",IF(B10="","",AsOf-B10)) | R10: =IF(C10="","",IF(O10<>"Booked","",IF(COUNTIF('CUSTOMERS'!$B$5:$B$404,C10)>0,"✓ In CUSTOMERS","Add to CUSTOMERS"))) | S10: =IF(C10="","",IF(OR(J10="Booked",J10="Recurring Client",J10="Lost/Declined"),0,1)) | T10: =IF(B10="","",DATE(YEAR(B10),MONTH(B10),1)) | U10: =IF(OR(S10<>1,L10=""),"",COUNTIFS('LEADS'!$S$5:$S$504,1,'LEADS'!$L$5:$L$504,"<"&L10)+COUNTIFS($S$5:S10,1,$L$5:L10,L10))
A11: L-0007 | B11: 46036 | C11: Emerson Holloway | D11: 555-0131 | E11: emerson.holloway@example.com | F11: Google Business Profile | G11: Airbnb Turnover | H11: North Sampletown | I11: 150 | J11: Booked | K11: 46037 | O11: =IF(C11="","",IF(OR(J11="Booked",J11="Recurring Client"),"Booked",IF(J11="Lost/Declined","Lost","Open"))) | P11: =IF(C11="","",IF(S11=0,"—",IF(L11="","Set date",IF(L11<AsOf,"Overdue",IF(L11=AsOf,"Due today",IF(L11<=AsOf+SoonDays,"Due soon","Scheduled")))))) | Q11: =IF(C11="","",IF(B11="","",AsOf-B11)) | R11: =IF(C11="","",IF(O11<>"Booked","",IF(COUNTIF('CUSTOMERS'!$B$5:$B$404,C11)>0,"✓ In CUSTOMERS","Add to CUSTOMERS"))) | S11: =IF(C11="","",IF(OR(J11="Booked",J11="Recurring Client",J11="Lost/Declined"),0,1)) | T11: =IF(B11="","",DATE(YEAR(B11),MONTH(B11),1)) | U11: =IF(OR(S11<>1,L11=""),"",COUNTIFS('LEADS'!$S$5:$S$504,1,'LEADS'!$L$5:$L$504,"<"&L11)+COUNTIFS($S$5:S11,1,$L$5:L11,L11))
A12: L-0008 | B12: 46038 | C12: Blake Oakes | D12: 555-0130 | E12: blake.oakes@example.com | F12: Google Search | G12: Airbnb Turnover | H12: North Sampletown | I12: 135 | J12: Booked | K12: 46039 | O12: =IF(C12="","",IF(OR(J12="Booked",J12="Recurring Client"),"Booked",IF(J12="Lost/Declined","Lost","Open"))) | P12: =IF(C12="","",IF(S12=0,"—",IF(L12="","Set date",IF(L12<AsOf,"Overdue",IF(L12=AsOf,"Due today",IF(L12<=AsOf+SoonDays,"Due soon","Scheduled")))))) | Q12: =IF(C12="","",IF(B12="","",AsOf-B12)) | R12: =IF(C12="","",IF(O12<>"Booked","",IF(COUNTIF('CUSTOMERS'!$B$5:$B$404,C12)>0,"✓ In CUSTOMERS","Add to CUSTOMERS"))) | S12: =IF(C12="","",IF(OR(J12="Booked",J12="Recurring Client",J12="Lost/Declined"),0,1)) | T12: =IF(B12="","",DATE(YEAR(B12),MONTH(B12),1)) | U12: =IF(OR(S12<>1,L12=""),"",COUNTIFS('LEADS'!$S$5:$S$504,1,'LEADS'!$L$5:$L$504,"<"&L12)+COUNTIFS($S$5:S12,1,$L$5:L12,L12))
A13: L-0009 | B13: 46042 | C13: Lane Ivers | D13: 555-0104 | E13: lane.ivers@example.com | F13: Website Form | G13: Deep Clean | H13: Sampletown | I13: 450 | J13: Recurring Client | K13: 46043 | O13: =IF(C13="","",IF(OR(J13="Booked",J13="Recurring Client"),"Booked",IF(J13="Lost/Declined","Lost","Open"))) | P13: =IF(C13="","",IF(S13=0,"—",IF(L13="","Set date",IF(L13<AsOf,"Overdue",IF(L13=AsOf,"Due today",IF(L13<=AsOf+SoonDays,"Due soon","Scheduled")))))) | Q13: =IF(C13="","",IF(B13="","",AsOf-B13)) | R13: =IF(C13="","",IF(O13<>"Booked","",IF(COUNTIF('CUSTOMERS'!$B$5:$B$404,C13)>0,"✓ In CUSTOMERS","Add to CUSTOMERS"))) | S13: =IF(C13="","",IF(OR(J13="Booked",J13="Recurring Client",J13="Lost/Declined"),0,1)) | T13: =IF(B13="","",DATE(YEAR(B13),MONTH(B13),1)) | U13: =IF(OR(S13<>1,L13=""),"",COUNTIFS('LEADS'!$S$5:$S$504,1,'LEADS'!$L$5:$L$504,"<"&L13)+COUNTIFS($S$5:S13,1,$L$5:L13,L13))
A14: L-0010 | B14: 46045 | C14: Dana Hartwell | D14: 555-0158 | E14: dana.hartwell@example.com | F14: Google Search | G14: Move-In/Move-Out | H14: Lakeview (fictional) | I14: 395 | J14: Lost/Declined | K14: 46053 | M14: Timing / availability | O14: =IF(C14="","",IF(OR(J14="Booked",J14="Recurring Client"),"Booked",IF(J14="Lost/Declined","Lost","Open"))) | P14: =IF(C14="","",IF(S14=0,"—",IF(L14="","Set date",IF(L14<AsOf,"Overdue",IF(L14=AsOf,"Due today",IF(L14<=AsOf+SoonDays,"Due soon","Scheduled")))))) | Q14: =IF(C14="","",IF(B14="","",AsOf-B14)) | R14: =IF(C14="","",IF(O14<>"Booked","",IF(COUNTIF('CUSTOMERS'!$B$5:$B$404,C14)>0,"✓ In CUSTOMERS","Add to CUSTOMERS"))) | S14: =IF(C14="","",IF(OR(J14="Booked",J14="Recurring Client",J14="Lost/Declined"),0,1)) | T14: =IF(B14="","",DATE(YEAR(B14),MONTH(B14),1)) | U14: =IF(OR(S14<>1,L14=""),"",COUNTIFS('LEADS'!$S$5:$S$504,1,'LEADS'!$L$5:$L$504,"<"&L14)+COUNTIFS($S$5:S14,1,$L$5:L14,L14))
A15: L-0011 | B15: 46046 | C15: Parker Lockhart | D15: 555-0132 | E15: parker.lockhart@example.com | F15: Google Search | G15: Airbnb Turnover | H15: Sampletown | I15: 150 | J15: Booked | K15: 46047 | O15: =IF(C15="","",IF(OR(J15="Booked",J15="Recurring Client"),"Booked",IF(J15="Lost/Declined","Lost","Open"))) | P15: =IF(C15="","",IF(S15=0,"—",IF(L15="","Set date",IF(L15<AsOf,"Overdue",IF(L15=AsOf,"Due today",IF(L15<=AsOf+SoonDays,"Due soon","Scheduled")))))) | Q15: =IF(C15="","",IF(B15="","",AsOf-B15)) | R15: =IF(C15="","",IF(O15<>"Booked","",IF(COUNTIF('CUSTOMERS'!$B$5:$B$404,C15)>0,"✓ In CUSTOMERS","Add to CUSTOMERS"))) | S15: =IF(C15="","",IF(OR(J15="Booked",J15="Recurring Client",J15="Lost/Declined"),0,1)) | T15: =IF(B15="","",DATE(YEAR(B15),MONTH(B15),1)) | U15: =IF(OR(S15<>1,L15=""),"",COUNTIFS('LEADS'!$S$5:$S$504,1,'LEADS'!$L$5:$L$504,"<"&L15)+COUNTIFS($S$5:S15,1,$L$5:L15,L15))
A16: L-0012 | B16: 46049 | C16: Brightside Dental Studio (sample) | D16: 555-0126 | E16: brightside.dental.studio.(sample)@example.com | F16: Referral | G16: Commercial Clean | H16: North Sampletown | I16: 100 | J16: Recurring Client | K16: 46050 | O16: =IF(C16="","",IF(OR(J16="Booked",J16="Recurring Client"),"Booked",IF(J16="Lost/Declined","Lost","Open"))) | P16: =IF(C16="","",IF(S16=0,"—",IF(L16="","Set date",IF(L16<AsOf,"Overdue",IF(L16=AsOf,"Due today",IF(L16<=AsOf+SoonDays,"Due soon","Scheduled")))))) | Q16: =IF(C16="","",IF(B16="","",AsOf-B16)) | R16: =IF(C16="","",IF(O16<>"Booked","",IF(COUNTIF('CUSTOMERS'!$B$5:$B$404,C16)>0,"✓ In CUSTOMERS","Add to CUSTOMERS"))) | S16: =IF(C16="","",IF(OR(J16="Booked",J16="Recurring Client",J16="Lost/Declined"),0,1)) | T16: =IF(B16="","",DATE(YEAR(B16),MONTH(B16),1)) | U16: =IF(OR(S16<>1,L16=""),"",COUNTIFS('LEADS'!$S$5:$S$504,1,'LEADS'!$L$5:$L$504,"<"&L16)+COUNTIFS($S$5:S16,1,$L$5:L16,L16))
A17: L-0013 | B17: 46050 | C17: Wren Porter | D17: 555-0123 | E17: wren.porter@example.com | F17: Referral | G17: Deep Clean | H17: North Sampletown | I17: 685 | J17: Booked | K17: 46051 | O17: =IF(C17="","",IF(OR(J17="Booked",J17="Recurring Client"),"Booked",IF(J17="Lost/Declined","Lost","Open"))) | P17: =IF(C17="","",IF(S17=0,"—",IF(L17="","Set date",IF(L17<AsOf,"Overdue",IF(L17=AsOf,"Due today",IF(L17<=AsOf+SoonDays,"Due soon","Scheduled")))))) | Q17: =IF(C17="","",IF(B17="","",AsOf-B17)) | R17: =IF(C17="","",IF(O17<>"Booked","",IF(COUNTIF('CUSTOMERS'!$B$5:$B$404,C17)>0,"✓ In CUSTOMERS","Add to CUSTOMERS"))) | S17: =IF(C17="","",IF(OR(J17="Booked",J17="Recurring Client",J17="Lost/Declined"),0,1)) | T17: =IF(B17="","",DATE(YEAR(B17),MONTH(B17),1)) | U17: =IF(OR(S17<>1,L17=""),"",COUNTIFS('LEADS'!$S$5:$S$504,1,'LEADS'!$L$5:$L$504,"<"&L17)+COUNTIFS($S$5:S17,1,$L$5:L17,L17))
A18: L-0014 | B18: 46052 | C18: Dana Delgado | D18: 555-0163 | E18: dana.delgado@example.com | F18: Google Business Profile | G18: Airbnb Turnover | H18: Riverbend (fictional) | J18: Lost/Declined | K18: 46057 | M18: No response | O18: =IF(C18="","",IF(OR(J18="Booked",J18="Recurring Client"),"Booked",IF(J18="Lost/Declined","Lost","Open"))) | P18: =IF(C18="","",IF(S18=0,"—",IF(L18="","Set date",IF(L18<AsOf,"Overdue",IF(L18=AsOf,"Due today",IF(L18<=AsOf+SoonDays,"Due soon","Scheduled")))))) | Q18: =IF(C18="","",IF(B18="","",AsOf-B18)) | R18: =IF(C18="","",IF(O18<>"Booked","",IF(COUNTIF('CUSTOMERS'!$B$5:$B$404,C18)>0,"✓ In CUSTOMERS","Add to CUSTOMERS"))) | S18: =IF(C18="","",IF(OR(J18="Booked",J18="Recurring Client",J18="Lost/Declined"),0,1)) | T18: =IF(B18="","",DATE(YEAR(B18),MONTH(B18),1)) | U18: =IF(OR(S18<>1,L18=""),"",COUNTIFS('LEADS'!$S$5:$S$504,1,'LEADS'!$L$5:$L$504,"<"&L18)+COUNTIFS($S$5:S18,1,$L$5:L18,L18))
A19: L-0015 | B19: 46055 | C19: Peyton Thornbury | D19: 555-0157 | E19: peyton.thornbury@example.com | F19: Referral | G19: Standard Clean | H19: Lakeview (fictional) | I19: 285 | J19: Lost/Declined | K19: 46060 | M19: No response | O19: =IF(C19="","",IF(OR(J19="Booked",J19="Recurring Client"),"Booked",IF(J19="Lost/Declined","Lost","Open"))) | P19: =IF(C19="","",IF(S19=0,"—",IF(L19="","Set date",IF(L19<AsOf,"Overdue",IF(L19=AsOf,"Due today",IF(L19<=AsOf+SoonDays,"Due soon","Scheduled")))))) | Q19: =IF(C19="","",IF(B19="","",AsOf-B19)) | R19: =IF(C19="","",IF(O19<>"Booked","",IF(COUNTIF('CUSTOMERS'!$B$5:$B$404,C19)>0,"✓ In CUSTOMERS","Add to CUSTOMERS"))) | S19: =IF(C19="","",IF(OR(J19="Booked",J19="Recurring Client",J19="Lost/Declined"),0,1)) | T19: =IF(B19="","",DATE(YEAR(B19),MONTH(B19),1)) | U19: =IF(OR(S19<>1,L19=""),"",COUNTIFS('LEADS'!$S$5:$S$504,1,'LEADS'!$L$5:$L$504,"<"&L19)+COUNTIFS($S$5:S19,1,$L$5:L19,L19))
A20: L-0016 | B20: 46062 | C20: Drew Underhill | D20: 555-0145 | E20: drew.underhill@example.com | F20: Flyer / Door Hanger | G20: Move-In/Move-Out | H20: Riverbend (fictional) | I20: 395 | J20: Lost/Declined | K20: 46068 | M20: Outside service area | O20: =IF(C20="","",IF(OR(J20="Booked",J20="Recurring Client"),"Booked",IF(J20="Lost/Declined","Lost","Open"))) | P20: =IF(C20="","",IF(S20=0,"—",IF(L20="","Set date",IF(L20<AsOf,"Overdue",IF(L20=AsOf,"Due today",IF(L20<=AsOf+SoonDays,"Due soon","Scheduled")))))) | Q20: =IF(C20="","",IF(B20="","",AsOf-B20)) | R20: =IF(C20="","",IF(O20<>"Booked","",IF(COUNTIF('CUSTOMERS'!$B$5:$B$404,C20)>0,"✓ In CUSTOMERS","Add to CUSTOMERS"))) | S20: =IF(C20="","",IF(OR(J20="Booked",J20="Recurring Client",J20="Lost/Declined"),0,1)) | T20: =IF(B20="","",DATE(YEAR(B20),MONTH(B20),1)) | U20: =IF(OR(S20<>1,L20=""),"",COUNTIFS('LEADS'!$S$5:$S$504,1,'LEADS'!$L$5:$L$504,"<"&L20)+COUNTIFS($S$5:S20,1,$L$5:L20,L20))
A21: L-0017 | B21: 46067 | C21: Arden Northcott | D21: 555-0155 | E21: arden.northcott@example.com | F21: Referral | G21: Move-In/Move-Out | H21: Lakeview (fictional) | J21: Lost/Declined | K21: 46069 | M21: Price | O21: =IF(C21="","",IF(OR(J21="Booked",J21="Recurring Client"),"Booked",IF(J21="Lost/Declined","Lost","Open"))) | P21: =IF(C21="","",IF(S21=0,"—",IF(L21="","Set date",IF(L21<AsOf,"Overdue",IF(L21=AsOf,"Due today",IF(L21<=AsOf+SoonDays,"Due soon","Scheduled")))))) | Q21: =IF(C21="","",IF(B21="","",AsOf-B21)) | R21: =IF(C21="","",IF(O21<>"Booked","",IF(COUNTIF('CUSTOMERS'!$B$5:$B$404,C21)>0,"✓ In CUSTOMERS","Add to CUSTOMERS"))) | S21: =IF(C21="","",IF(OR(J21="Booked",J21="Recurring Client",J21="Lost/Declined"),0,1)) | T21: =IF(B21="","",DATE(YEAR(B21),MONTH(B21),1)) | U21: =IF(OR(S21<>1,L21=""),"",COUNTIFS('LEADS'!$S$5:$S$504,1,'LEADS'!$L$5:$L$504,"<"&L21)+COUNTIFS($S$5:S21,1,$L$5:L21,L21))
A22: L-0018 | B22: 46068 | C22: Skyler Winslow | D22: 555-0146 | E22: skyler.winslow@example.com | F22: Facebook | G22: Airbnb Turnover | H22: North Sampletown | I22: 395 | J22: Lost/Declined | K22: 46070 | M22: Timing / availability | O22: =IF(C22="","",IF(OR(J22="Booked",J22="Recurring Client"),"Booked",IF(J22="Lost/Declined","Lost","Open"))) | P22: =IF(C22="","",IF(S22=0,"—",IF(L22="","Set date",IF(L22<AsOf,"Overdue",IF(L22=AsOf,"Due today",IF(L22<=AsOf+SoonDays,"Due soon","Scheduled")))))) | Q22: =IF(C22="","",IF(B22="","",AsOf-B22)) | R22: =IF(C22="","",IF(O22<>"Booked","",IF(COUNTIF('CUSTOMERS'!$B$5:$B$404,C22)>0,"✓ In CUSTOMERS","Add to CUSTOMERS"))) | S22: =IF(C22="","",IF(OR(J22="Booked",J22="Recurring Client",J22="Lost/Declined"),0,1)) | T22: =IF(B22="","",DATE(YEAR(B22),MONTH(B22),1)) | U22: =IF(OR(S22<>1,L22=""),"",COUNTIFS('LEADS'!$S$5:$S$504,1,'LEADS'!$L$5:$L$504,"<"&L22)+COUNTIFS($S$5:S22,1,$L$5:L22,L22))
A23: L-0019 | B23: 46073 | C23: Crescent Property Group (sample) | D23: 555-0133 | E23: crescent.property.group.(sample)@example.com | F23: Google Business Profile | G23: Move-In/Move-Out | H23: North Sampletown | I23: 300 | J23: Booked | K23: 46074 | O23: =IF(C23="","",IF(OR(J23="Booked",J23="Recurring Client"),"Booked",IF(J23="Lost/Declined","Lost","Open"))) | P23: =IF(C23="","",IF(S23=0,"—",IF(L23="","Set date",IF(L23<AsOf,"Overdue",IF(L23=AsOf,"Due today",IF(L23<=AsOf+SoonDays,"Due soon","Scheduled")))))) | Q23: =IF(C23="","",IF(B23="","",AsOf-B23)) | R23: =IF(C23="","",IF(O23<>"Booked","",IF(COUNTIF('CUSTOMERS'!$B$5:$B$404,C23)>0,"✓ In CUSTOMERS","Add to CUSTOMERS"))) | S23: =IF(C23="","",IF(OR(J23="Booked",J23="Recurring Client",J23="Lost/Declined"),0,1)) | T23: =IF(B23="","",DATE(YEAR(B23),MONTH(B23),1)) | U23: =IF(OR(S23<>1,L23=""),"",COUNTIFS('LEADS'!$S$5:$S$504,1,'LEADS'!$L$5:$L$504,"<"&L23)+COUNTIFS($S$5:S23,1,$L$5:L23,L23))
A24: L-0020 | B24: 46075 | C24: Rory Vance | D24: 555-0140 | E24: rory.vance@example.com | F24: Google Business Profile | G24: Airbnb Turnover | H24: Old Mill District | I24: 395 | J24: Lost/Declined | K24: 46078 | M24: Timing / availability | O24: =IF(C24="","",IF(OR(J24="Booked",J24="Recurring Client"),"Booked",IF(J24="Lost/Declined","Lost","Open"))) | P24: =IF(C24="","",IF(S24=0,"—",IF(L24="","Set date",IF(L24<AsOf,"Overdue",IF(L24=AsOf,"Due today",IF(L24<=AsOf+SoonDays,"Due soon","Scheduled")))))) | Q24: =IF(C24="","",IF(B24="","",AsOf-B24)) | R24: =IF(C24="","",IF(O24<>"Booked","",IF(COUNTIF('CUSTOMERS'!$B$5:$B$404,C24)>0,"✓ In CUSTOMERS","Add to CUSTOMERS"))) | S24: =IF(C24="","",IF(OR(J24="Booked",J24="Recurring Client",J24="Lost/Declined"),0,1)) | T24: =IF(B24="","",DATE(YEAR(B24),MONTH(B24),1)) | U24: =IF(OR(S24<>1,L24=""),"",COUNTIFS('LEADS'!$S$5:$S$504,1,'LEADS'!$L$5:$L$504,"<"&L24)+COUNTIFS($S$5:S24,1,$L$5:L24,L24))
A25: L-0021 | B25: 46079 | C25: Peyton Underhill | D25: 555-0114 | E25: peyton.underhill@example.com | F25: Referral | G25: Deep Clean | H25: Sampletown | I25: 300 | J25: Booked | K25: 46080 | O25: =IF(C25="","",IF(OR(J25="Booked",J25="Recurring Client"),"Booked",IF(J25="Lost/Declined","Lost","Open"))) | P25: =IF(C25="","",IF(S25=0,"—",IF(L25="","Set date",IF(L25<AsOf,"Overdue",IF(L25=AsOf,"Due today",IF(L25<=AsOf+SoonDays,"Due soon","Scheduled")))))) | Q25: =IF(C25="","",IF(B25="","",AsOf-B25)) | R25: =IF(C25="","",IF(O25<>"Booked","",IF(COUNTIF('CUSTOMERS'!$B$5:$B$404,C25)>0,"✓ In CUSTOMERS","Add to CUSTOMERS"))) | S25: =IF(C25="","",IF(OR(J25="Booked",J25="Recurring Client",J25="Lost/Declined"),0,1)) | T25: =IF(B25="","",DATE(YEAR(B25),MONTH(B25),1)) | U25: =IF(OR(S25<>1,L25=""),"",COUNTIFS('LEADS'!$S$5:$S$504,1,'LEADS'!$L$5:$L$504,"<"&L25)+COUNTIFS($S$5:S25,1,$L$5:L25,L25))
A26: L-0022 | B26: 46080 | C26: Noel Hayes | D26: 555-0135 | E26: noel.hayes@example.com | F26: Referral | G26: Standard Clean | H26: Sampletown | I26: 160 | J26: Lost/Declined | K26: 46085 | M26: Timing / availability | O26: =IF(C26="","",IF(OR(J26="Booked",J26="Recurring Client"),"Booked",IF(J26="Lost/Declined","Lost","Open"))) | P26: =IF(C26="","",IF(S26=0,"—",IF(L26="","Set date",IF(L26<AsOf,"Overdue",IF(L26=AsOf,"Due today",IF(L26<=AsOf+SoonDays,"Due soon","Scheduled")))))) | Q26: =IF(C26="","",IF(B26="","",AsOf-B26)) | R26: =IF(C26="","",IF(O26<>"Booked","",IF(COUNTIF('CUSTOMERS'!$B$5:$B$404,C26)>0,"✓ In CUSTOMERS","Add to CUSTOMERS"))) | S26: =IF(C26="","",IF(OR(J26="Booked",J26="Recurring Client",J26="Lost/Declined"),0,1)) | T26: =IF(B26="","",DATE(YEAR(B26),MONTH(B26),1)) | U26: =IF(OR(S26<>1,L26=""),"",COUNTIFS('LEADS'!$S$5:$S$504,1,'LEADS'!$L$5:$L$504,"<"&L26)+COUNTIFS($S$5:S26,1,$L$5:L26,L26))
A27: L-0023 | B27: 46086 | C27: Harbor Yoga Loft (sample) | D27: 555-0128 | E27: harbor.yoga.loft.(sample)@example.com | F27: Nextdoor | G27: Commercial Clean | H27: Sampletown | I27: 160 | J27: Booked | K27: 46087 | O27: =IF(C27="","",IF(OR(J27="Booked",J27="Recurring Client"),"Booked",IF(J27="Lost/Declined","Lost","Open"))) | P27: =IF(C27="","",IF(S27=0,"—",IF(L27="","Set date",IF(L27<AsOf,"Overdue",IF(L27=AsOf,"Due today",IF(L27<=AsOf+SoonDays,"Due soon","Scheduled")))))) | Q27: =IF(C27="","",IF(B27="","",AsOf-B27)) | R27: =IF(C27="","",IF(O27<>"Booked","",IF(COUNTIF('CUSTOMERS'!$B$5:$B$404,C27)>0,"✓ In CUSTOMERS","Add to CUSTOMERS"))) | S27: =IF(C27="","",IF(OR(J27="Booked",J27="Recurring Client",J27="Lost/Declined"),0,1)) | T27: =IF(B27="","",DATE(YEAR(B27),MONTH(B27),1)) | U27: =IF(OR(S27<>1,L27=""),"",COUNTIFS('LEADS'!$S$5:$S$504,1,'LEADS'!$L$5:$L$504,"<"&L27)+COUNTIFS($S$5:S27,1,$L$5:L27,L27))
A28: L-0024 | B28: 46086 | C28: Avery Brightwater | D28: 555-0159 | E28: avery.brightwater@example.com | F28: Website Form | G28: Airbnb Turnover | H28: Riverbend (fictional) | I28: 340 | J28: Lost/Declined | K28: 46090 | M28: Outside service area | O28: =IF(C28="","",IF(OR(J28="Booked",J28="Recurring Client"),"Booked",IF(J28="Lost/Declined","Lost","Open"))) | P28: =IF(C28="","",IF(S28=0,"—",IF(L28="","Set date",IF(L28<AsOf,"Overdue",IF(L28=AsOf,"Due today",IF(L28<=AsOf+SoonDays,"Due soon","Scheduled")))))) | Q28: =IF(C28="","",IF(B28="","",AsOf-B28)) | R28: =IF(C28="","",IF(O28<>"Booked","",IF(COUNTIF('CUSTOMERS'!$B$5:$B$404,C28)>0,"✓ In CUSTOMERS","Add to CUSTOMERS"))) | S28: =IF(C28="","",IF(OR(J28="Booked",J28="Recurring Client",J28="Lost/Declined"),0,1)) | T28: =IF(B28="","",DATE(YEAR(B28),MONTH(B28),1)) | U28: =IF(OR(S28<>1,L28=""),"",COUNTIFS('LEADS'!$S$5:$S$504,1,'LEADS'!$L$5:$L$504,"<"&L28)+COUNTIFS($S$5:S28,1,$L$5:L28,L28))
A29: L-0025 | B29: 46089 | C29: Rowan Foxworth | D29: 555-0108 | E29: rowan.foxworth@example.com | F29: Google Search | G29: Deep Clean | H29: North Sampletown | I29: 530 | J29: Recurring Client | K29: 46090 | O29: =IF(C29="","",IF(OR(J29="Booked",J29="Recurring Client"),"Booked",IF(J29="Lost/Declined","Lost","Open"))) | P29: =IF(C29="","",IF(S29=0,"—",IF(L29="","Set date",IF(L29<AsOf,"Overdue",IF(L29=AsOf,"Due today",IF(L29<=AsOf+SoonDays,"Due soon","Scheduled")))))) | Q29: =IF(C29="","",IF(B29="","",AsOf-B29)) | R29: =IF(C29="","",IF(O29<>"Booked","",IF(COUNTIF('CUSTOMERS'!$B$5:$B$404,C29)>0,"✓ In CUSTOMERS","Add to CUSTOMERS"))) | S29: =IF(C29="","",IF(OR(J29="Booked",J29="Recurring Client",J29="Lost/Declined"),0,1)) | T29: =IF(B29="","",DATE(YEAR(B29),MONTH(B29),1)) | U29: =IF(OR(S29<>1,L29=""),"",COUNTIFS('LEADS'!$S$5:$S$504,1,'LEADS'!$L$5:$L$504,"<"&L29)+COUNTIFS($S$5:S29,1,$L$5:L29,L29))
A30: L-0026 | B30: 46091 | C30: Rowan Merriweather | D30: 555-0115 | E30: rowan.merriweather@example.com | F30: Nextdoor | G30: Deep Clean | H30: North Sampletown | I30: 650 | J30: Booked | K30: 46092 | O30: =IF(C30="","",IF(OR(J30="Booked",J30="Recurring Client"),"Booked",IF(J30="Lost/Declined","Lost","Open"))) | P30: =IF(C30="","",IF(S30=0,"—",IF(L30="","Set date",IF(L30<AsOf,"Overdue",IF(L30=AsOf,"Due today",IF(L30<=AsOf+SoonDays,"Due soon","Scheduled")))))) | Q30: =IF(C30="","",IF(B30="","",AsOf-B30)) | R30: =IF(C30="","",IF(O30<>"Booked","",IF(COUNTIF('CUSTOMERS'!$B$5:$B$404,C30)>0,"✓ In CUSTOMERS","Add to CUSTOMERS"))) | S30: =IF(C30="","",IF(OR(J30="Booked",J30="Recurring Client",J30="Lost/Declined"),0,1)) | T30: =IF(B30="","",DATE(YEAR(B30),MONTH(B30),1)) | U30: =IF(OR(S30<>1,L30=""),"",COUNTIFS('LEADS'!$S$5:$S$504,1,'LEADS'!$L$5:$L$504,"<"&L30)+COUNTIFS($S$5:S30,1,$L$5:L30,L30))
A31: L-0027 | B31: 46094 | C31: Logan Porter | D31: 555-0105 | E31: logan.porter@example.com | F31: Referral | G31: Deep Clean | H31: Lakeview (fictional) | I31: 530 | J31: Recurring Client | K31: 46095 | O31: =IF(C31="","",IF(OR(J31="Booked",J31="Recurring Client"),"Booked",IF(J31="Lost/Declined","Lost","Open"))) | P31: =IF(C31="","",IF(S31=0,"—",IF(L31="","Set date",IF(L31<AsOf,"Overdue",IF(L31=AsOf,"Due today",IF(L31<=AsOf+SoonDays,"Due soon","Scheduled")))))) | Q31: =IF(C31="","",IF(B31="","",AsOf-B31)) | R31: =IF(C31="","",IF(O31<>"Booked","",IF(COUNTIF('CUSTOMERS'!$B$5:$B$404,C31)>0,"✓ In CUSTOMERS","Add to CUSTOMERS"))) | S31: =IF(C31="","",IF(OR(J31="Booked",J31="Recurring Client",J31="Lost/Declined"),0,1)) | T31: =IF(B31="","",DATE(YEAR(B31),MONTH(B31),1)) | U31: =IF(OR(S31<>1,L31=""),"",COUNTIFS('LEADS'!$S$5:$S$504,1,'LEADS'!$L$5:$L$504,"<"&L31)+COUNTIFS($S$5:S31,1,$L$5:L31,L31))
A32: L-0028 | B32: 46098 | C32: Noel Collins | D32: 555-0107 | E32: noel.collins@example.com | F32: Facebook | G32: Deep Clean | H32: Lakeview (fictional) | I32: 595 | J32: Booked | K32: 46099 | O32: =IF(C32="","",IF(OR(J32="Booked",J32="Recurring Client"),"Booked",IF(J32="Lost/Declined","Lost","Open"))) | P32: =IF(C32="","",IF(S32=0,"—",IF(L32="","Set date",IF(L32<AsOf,"Overdue",IF(L32=AsOf,"Due today",IF(L32<=AsOf+SoonDays,"Due soon","Scheduled")))))) | Q32: =IF(C32="","",IF(B32="","",AsOf-B32)) | R32: =IF(C32="","",IF(O32<>"Booked","",IF(COUNTIF('CUSTOMERS'!$B$5:$B$404,C32)>0,"✓ In CUSTOMERS","Add to CUSTOMERS"))) | S32: =IF(C32="","",IF(OR(J32="Booked",J32="Recurring Client",J32="Lost/Declined"),0,1)) | T32: =IF(B32="","",DATE(YEAR(B32),MONTH(B32),1)) | U32: =IF(OR(S32<>1,L32=""),"",COUNTIFS('LEADS'!$S$5:$S$504,1,'LEADS'!$L$5:$L$504,"<"&L32)+COUNTIFS($S$5:S32,1,$L$5:L32,L32))
A33: L-0029 | B33: 46100 | C33: Devon Hartwell | D33: 555-0160 | E33: devon.hartwell@example.com | F33: Google Search | G33: Deep Clean | H33: Lakeview (fictional) | I33: 395 | J33: Lost/Declined | K33: 46103 | M33: No response | O33: =IF(C33="","",IF(OR(J33="Booked",J33="Recurring Client"),"Booked",IF(J33="Lost/Declined","Lost","Open"))) | P33: =IF(C33="","",IF(S33=0,"—",IF(L33="","Set date",IF(L33<AsOf,"Overdue",IF(L33=AsOf,"Due today",IF(L33<=AsOf+SoonDays,"Due soon","Scheduled")))))) | Q33: =IF(C33="","",IF(B33="","",AsOf-B33)) | R33: =IF(C33="","",IF(O33<>"Booked","",IF(COUNTIF('CUSTOMERS'!$B$5:$B$404,C33)>0,"✓ In CUSTOMERS","Add to CUSTOMERS"))) | S33: =IF(C33="","",IF(OR(J33="Booked",J33="Recurring Client",J33="Lost/Declined"),0,1)) | T33: =IF(B33="","",DATE(YEAR(B33),MONTH(B33),1)) | U33: =IF(OR(S33<>1,L33=""),"",COUNTIFS('LEADS'!$S$5:$S$504,1,'LEADS'!$L$5:$L$504,"<"&L33)+COUNTIFS($S$5:S33,1,$L$5:L33,L33))
A34: L-0030 | B34: 46105 | C34: Finley Quigley | D34: 555-0110 | E34: finley.quigley@example.com | F34: Google Search | G34: Deep Clean | H34: North Sampletown | I34: 250 | J34: Recurring Client | K34: 46106 | O34: =IF(C34="","",IF(OR(J34="Booked",J34="Recurring Client"),"Booked",IF(J34="Lost/Declined","Lost","Open"))) | P34: =IF(C34="","",IF(S34=0,"—",IF(L34="","Set date",IF(L34<AsOf,"Overdue",IF(L34=AsOf,"Due today",IF(L34<=AsOf+SoonDays,"Due soon","Scheduled")))))) | Q34: =IF(C34="","",IF(B34="","",AsOf-B34)) | R34: =IF(C34="","",IF(O34<>"Booked","",IF(COUNTIF('CUSTOMERS'!$B$5:$B$404,C34)>0,"✓ In CUSTOMERS","Add to CUSTOMERS"))) | S34: =IF(C34="","",IF(OR(J34="Booked",J34="Recurring Client",J34="Lost/Declined"),0,1)) | T34: =IF(B34="","",DATE(YEAR(B34),MONTH(B34),1)) | U34: =IF(OR(S34<>1,L34=""),"",COUNTIFS('LEADS'!$S$5:$S$504,1,'LEADS'!$L$5:$L$504,"<"&L34)+COUNTIFS($S$5:S34,1,$L$5:L34,L34))
A35: L-0031 | B35: 46105 | C35: Parker Holloway | D35: 555-0139 | E35: parker.holloway@example.com | F35: Google Business Profile | G35: Airbnb Turnover | H35: North Sampletown | J35: Lost/Declined | K35: 46109 | M35: Price | O35: =IF(C35="","",IF(OR(J35="Booked",J35="Recurring Client"),"Booked",IF(J35="Lost/Declined","Lost","Open"))) | P35: =IF(C35="","",IF(S35=0,"—",IF(L35="","Set date",IF(L35<AsOf,"Overdue",IF(L35=AsOf,"Due today",IF(L35<=AsOf+SoonDays,"Due soon","Scheduled")))))) | Q35: =IF(C35="","",IF(B35="","",AsOf-B35)) | R35: =IF(C35="","",IF(O35<>"Booked","",IF(COUNTIF('CUSTOMERS'!$B$5:$B$404,C35)>0,"✓ In CUSTOMERS","Add to CUSTOMERS"))) | S35: =IF(C35="","",IF(OR(J35="Booked",J35="Recurring Client",J35="Lost/Declined"),0,1)) | T35: =IF(B35="","",DATE(YEAR(B35),MONTH(B35),1)) | U35: =IF(OR(S35<>1,L35=""),"",COUNTIFS('LEADS'!$S$5:$S$504,1,'LEADS'!$L$5:$L$504,"<"&L35)+COUNTIFS($S$5:S35,1,$L$5:L35,L35))
A36: L-0032 | B36: 46111 | C36: Oakview Office Suites (sample) | D36: 555-0127 | E36: oakview.office.suites.(sample)@example.com | F36: Referral | G36: Commercial Clean | H36: North Sampletown | I36: 140 | J36: Recurring Client | K36: 46112 | O36: =IF(C36="","",IF(OR(J36="Booked",J36="Recurring Client"),"Booked",IF(J36="Lost/Declined","Lost","Open"))) | P36: =IF(C36="","",IF(S36=0,"—",IF(L36="","Set date",IF(L36<AsOf,"Overdue",IF(L36=AsOf,"Due today",IF(L36<=AsOf+SoonDays,"Due soon","Scheduled")))))) | Q36: =IF(C36="","",IF(B36="","",AsOf-B36)) | R36: =IF(C36="","",IF(O36<>"Booked","",IF(COUNTIF('CUSTOMERS'!$B$5:$B$404,C36)>0,"✓ In CUSTOMERS","Add to CUSTOMERS"))) | S36: =IF(C36="","",IF(OR(J36="Booked",J36="Recurring Client",J36="Lost/Declined"),0,1)) | T36: =IF(B36="","",DATE(YEAR(B36),MONTH(B36),1)) | U36: =IF(OR(S36<>1,L36=""),"",COUNTIFS('LEADS'!$S$5:$S$504,1,'LEADS'!$L$5:$L$504,"<"&L36)+COUNTIFS($S$5:S36,1,$L$5:L36,L36))
A37: L-0033 | B37: 46113 | C37: Kai Winslow | D37: 555-0152 | E37: kai.winslow@example.com | F37: Google Search | G37: Deep Clean | H37: Riverbend (fictional) | I37: 340 | J37: Lost/Declined | K37: 46117 | M37: No response | O37: =IF(C37="","",IF(OR(J37="Booked",J37="Recurring Client"),"Booked",IF(J37="Lost/Declined","Lost","Open"))) | P37: =IF(C37="","",IF(S37=0,"—",IF(L37="","Set date",IF(L37<AsOf,"Overdue",IF(L37=AsOf,"Due today",IF(L37<=AsOf+SoonDays,"Due soon","Scheduled")))))) | Q37: =IF(C37="","",IF(B37="","",AsOf-B37)) | R37: =IF(C37="","",IF(O37<>"Booked","",IF(COUNTIF('CUSTOMERS'!$B$5:$B$404,C37)>0,"✓ In CUSTOMERS","Add to CUSTOMERS"))) | S37: =IF(C37="","",IF(OR(J37="Booked",J37="Recurring Client",J37="Lost/Declined"),0,1)) | T37: =IF(B37="","",DATE(YEAR(B37),MONTH(B37),1)) | U37: =IF(OR(S37<>1,L37=""),"",COUNTIFS('LEADS'!$S$5:$S$504,1,'LEADS'!$L$5:$L$504,"<"&L37)+COUNTIFS($S$5:S37,1,$L$5:L37,L37))
A38: L-0034 | B38: 46117 | C38: Skyler Yardley | D38: 555-0122 | E38: skyler.yardley@example.com | F38: Nextdoor | G38: Deep Clean | H38: Sampletown | I38: 685 | J38: Booked | K38: 46118 | O38: =IF(C38="","",IF(OR(J38="Booked",J38="Recurring Client"),"Booked",IF(J38="Lost/Declined","Lost","Open"))) | P38: =IF(C38="","",IF(S38=0,"—",IF(L38="","Set date",IF(L38<AsOf,"Overdue",IF(L38=AsOf,"Due today",IF(L38<=AsOf+SoonDays,"Due soon","Scheduled")))))) | Q38: =IF(C38="","",IF(B38="","",AsOf-B38)) | R38: =IF(C38="","",IF(O38<>"Booked","",IF(COUNTIF('CUSTOMERS'!$B$5:$B$404,C38)>0,"✓ In CUSTOMERS","Add to CUSTOMERS"))) | S38: =IF(C38="","",IF(OR(J38="Booked",J38="Recurring Client",J38="Lost/Declined"),0,1)) | T38: =IF(B38="","",DATE(YEAR(B38),MONTH(B38),1)) | U38: =IF(OR(S38<>1,L38=""),"",COUNTIFS('LEADS'!$S$5:$S$504,1,'LEADS'!$L$5:$L$504,"<"&L38)+COUNTIFS($S$5:S38,1,$L$5:L38,L38))
A39: L-0035 | B39: 46129 | C39: Frankie Hayes | D39: 555-0138 | E39: frankie.hayes@example.com | F39: Website Form | G39: Deep Clean | H39: Old Mill District | J39: Lost/Declined | K39: 46132 | M39: Chose another company | O39: =IF(C39="","",IF(OR(J39="Booked",J39="Recurring Client"),"Booked",IF(J39="Lost/Declined","Lost","Open"))) | P39: =IF(C39="","",IF(S39=0,"—",IF(L39="","Set date",IF(L39<AsOf,"Overdue",IF(L39=AsOf,"Due today",IF(L39<=AsOf+SoonDays,"Due soon","Scheduled")))))) | Q39: =IF(C39="","",IF(B39="","",AsOf-B39)) | R39: =IF(C39="","",IF(O39<>"Booked","",IF(COUNTIF('CUSTOMERS'!$B$5:$B$404,C39)>0,"✓ In CUSTOMERS","Add to CUSTOMERS"))) | S39: =IF(C39="","",IF(OR(J39="Booked",J39="Recurring Client",J39="Lost/Declined"),0,1)) | T39: =IF(B39="","",DATE(YEAR(B39),MONTH(B39),1)) | U39: =IF(OR(S39<>1,L39=""),"",COUNTIFS('LEADS'!$S$5:$S$504,1,'LEADS'!$L$5:$L$504,"<"&L39)+COUNTIFS($S$5:S39,1,$L$5:L39,L39))
A40: L-0036 | B40: 46134 | C40: Parker Pembrook | D40: 555-0118 | E40: parker.pembrook@example.com | F40: Google Search | G40: Deep Clean | H40: Lakeview (fictional) | I40: 320 | J40: Booked | K40: 46135 | O40: =IF(C40="","",IF(OR(J40="Booked",J40="Recurring Client"),"Booked",IF(J40="Lost/Declined","Lost","Open"))) | P40: =IF(C40="","",IF(S40=0,"—",IF(L40="","Set date",IF(L40<AsOf,"Overdue",IF(L40=AsOf,"Due today",IF(L40<=AsOf+SoonDays,"Due soon","Scheduled")))))) | Q40: =IF(C40="","",IF(B40="","",AsOf-B40)) | R40: =IF(C40="","",IF(O40<>"Booked","",IF(COUNTIF('CUSTOMERS'!$B$5:$B$404,C40)>0,"✓ In CUSTOMERS","Add to CUSTOMERS"))) | S40: =IF(C40="","",IF(OR(J40="Booked",J40="Recurring Client",J40="Lost/Declined"),0,1)) | T40: =IF(B40="","",DATE(YEAR(B40),MONTH(B40),1)) | U40: =IF(OR(S40<>1,L40=""),"",COUNTIFS('LEADS'!$S$5:$S$504,1,'LEADS'!$L$5:$L$504,"<"&L40)+COUNTIFS($S$5:S40,1,$L$5:L40,L40))
A41: L-0037 | B41: 46140 | C41: Oakley Winslow | D41: 555-0142 | E41: oakley.winslow@example.com | F41: Referral | G41: Move-In/Move-Out | H41: North Sampletown | I41: 160 | J41: Lost/Declined | K41: 46148 | M41: No response | O41: =IF(C41="","",IF(OR(J41="Booked",J41="Recurring Client"),"Booked",IF(J41="Lost/Declined","Lost","Open"))) | P41: =IF(C41="","",IF(S41=0,"—",IF(L41="","Set date",IF(L41<AsOf,"Overdue",IF(L41=AsOf,"Due today",IF(L41<=AsOf+SoonDays,"Due soon","Scheduled")))))) | Q41: =IF(C41="","",IF(B41="","",AsOf-B41)) | R41: =IF(C41="","",IF(O41<>"Booked","",IF(COUNTIF('CUSTOMERS'!$B$5:$B$404,C41)>0,"✓ In CUSTOMERS","Add to CUSTOMERS"))) | S41: =IF(C41="","",IF(OR(J41="Booked",J41="Recurring Client",J41="Lost/Declined"),0,1)) | T41: =IF(B41="","",DATE(YEAR(B41),MONTH(B41),1)) | U41: =IF(OR(S41<>1,L41=""),"",COUNTIFS('LEADS'!$S$5:$S$504,1,'LEADS'!$L$5:$L$504,"<"&L41)+COUNTIFS($S$5:S41,1,$L$5:L41,L41))
A42: L-0038 | B42: 46142 | C42: Frankie Lockhart | D42: 555-0151 | E42: frankie.lockhart@example.com | F42: Google Business Profile | G42: Airbnb Turnover | H42: Riverbend (fictional) | I42: 285 | J42: Lost/Declined | K42: 46150 | M42: No response | O42: =IF(C42="","",IF(OR(J42="Booked",J42="Recurring Client"),"Booked",IF(J42="Lost/Declined","Lost","Open"))) | P42: =IF(C42="","",IF(S42=0,"—",IF(L42="","Set date",IF(L42<AsOf,"Overdue",IF(L42=AsOf,"Due today",IF(L42<=AsOf+SoonDays,"Due soon","Scheduled")))))) | Q42: =IF(C42="","",IF(B42="","",AsOf-B42)) | R42: =IF(C42="","",IF(O42<>"Booked","",IF(COUNTIF('CUSTOMERS'!$B$5:$B$404,C42)>0,"✓ In CUSTOMERS","Add to CUSTOMERS"))) | S42: =IF(C42="","",IF(OR(J42="Booked",J42="Recurring Client",J42="Lost/Declined"),0,1)) | T42: =IF(B42="","",DATE(YEAR(B42),MONTH(B42),1)) | U42: =IF(OR(S42<>1,L42=""),"",COUNTIFS('LEADS'!$S$5:$S$504,1,'LEADS'!$L$5:$L$504,"<"&L42)+COUNTIFS($S$5:S42,1,$L$5:L42,L42))
A43: L-0039 | B43: 46146 | C43: Carmen Bennett | D43: 555-0148 | E43: carmen.bennett@example.com | F43: Google Business Profile | G43: Move-In/Move-Out | H43: Old Mill District | I43: 395 | J43: Lost/Declined | K43: 46151 | M43: Outside service area | O43: =IF(C43="","",IF(OR(J43="Booked",J43="Recurring Client"),"Booked",IF(J43="Lost/Declined","Lost","Open"))) | P43: =IF(C43="","",IF(S43=0,"—",IF(L43="","Set date",IF(L43<AsOf,"Overdue",IF(L43=AsOf,"Due today",IF(L43<=AsOf+SoonDays,"Due soon","Scheduled")))))) | Q43: =IF(C43="","",IF(B43="","",AsOf-B43)) | R43: =IF(C43="","",IF(O43<>"Booked","",IF(COUNTIF('CUSTOMERS'!$B$5:$B$404,C43)>0,"✓ In CUSTOMERS","Add to CUSTOMERS"))) | S43: =IF(C43="","",IF(OR(J43="Booked",J43="Recurring Client",J43="Lost/Declined"),0,1)) | T43: =IF(B43="","",DATE(YEAR(B43),MONTH(B43),1)) | U43: =IF(OR(S43<>1,L43=""),"",COUNTIFS('LEADS'!$S$5:$S$504,1,'LEADS'!$L$5:$L$504,"<"&L43)+COUNTIFS($S$5:S43,1,$L$5:L43,L43))
A44: L-0040 | B44: 46147 | C44: Dana Ivers | D44: 555-0111 | E44: dana.ivers@example.com | F44: Google Business Profile | G44: Deep Clean | H44: North Sampletown | I44: 650 | J44: Booked | K44: 46148 | O44: =IF(C44="","",IF(OR(J44="Booked",J44="Recurring Client"),"Booked",IF(J44="Lost/Declined","Lost","Open"))) | P44: =IF(C44="","",IF(S44=0,"—",IF(L44="","Set date",IF(L44<AsOf,"Overdue",IF(L44=AsOf,"Due today",IF(L44<=AsOf+SoonDays,"Due soon","Scheduled")))))) | Q44: =IF(C44="","",IF(B44="","",AsOf-B44)) | R44: =IF(C44="","",IF(O44<>"Booked","",IF(COUNTIF('CUSTOMERS'!$B$5:$B$404,C44)>0,"✓ In CUSTOMERS","Add to CUSTOMERS"))) | S44: =IF(C44="","",IF(OR(J44="Booked",J44="Recurring Client",J44="Lost/Declined"),0,1)) | T44: =IF(B44="","",DATE(YEAR(B44),MONTH(B44),1)) | U44: =IF(OR(S44<>1,L44=""),"",COUNTIFS('LEADS'!$S$5:$S$504,1,'LEADS'!$L$5:$L$504,"<"&L44)+COUNTIFS($S$5:S44,1,$L$5:L44,L44))
A45: L-0041 | B45: 46151 | C45: Rowan Ashworth | D45: 555-0136 | E45: rowan.ashworth@example.com | F45: Nextdoor | G45: Airbnb Turnover | H45: Lakeview (fictional) | I45: 395 | J45: Lost/Declined | K45: 46153 | M45: No response | O45: =IF(C45="","",IF(OR(J45="Booked",J45="Recurring Client"),"Booked",IF(J45="Lost/Declined","Lost","Open"))) | P45: =IF(C45="","",IF(S45=0,"—",IF(L45="","Set date",IF(L45<AsOf,"Overdue",IF(L45=AsOf,"Due today",IF(L45<=AsOf+SoonDays,"Due soon","Scheduled")))))) | Q45: =IF(C45="","",IF(B45="","",AsOf-B45)) | R45: =IF(C45="","",IF(O45<>"Booked","",IF(COUNTIF('CUSTOMERS'!$B$5:$B$404,C45)>0,"✓ In CUSTOMERS","Add to CUSTOMERS"))) | S45: =IF(C45="","",IF(OR(J45="Booked",J45="Recurring Client",J45="Lost/Declined"),0,1)) | T45: =IF(B45="","",DATE(YEAR(B45),MONTH(B45),1)) | U45: =IF(OR(S45<>1,L45=""),"",COUNTIFS('LEADS'!$S$5:$S$504,1,'LEADS'!$L$5:$L$504,"<"&L45)+COUNTIFS($S$5:S45,1,$L$5:L45,L45))
A46: L-0042 | B46: 46155 | C46: Remy Dunmore | D46: 555-0162 | E46: remy.dunmore@example.com | F46: Google Business Profile | G46: Move-In/Move-Out | H46: Sampletown | J46: Lost/Declined | K46: 46163 | M46: Outside service area | O46: =IF(C46="","",IF(OR(J46="Booked",J46="Recurring Client"),"Booked",IF(J46="Lost/Declined","Lost","Open"))) | P46: =IF(C46="","",IF(S46=0,"—",IF(L46="","Set date",IF(L46<AsOf,"Overdue",IF(L46=AsOf,"Due today",IF(L46<=AsOf+SoonDays,"Due soon","Scheduled")))))) | Q46: =IF(C46="","",IF(B46="","",AsOf-B46)) | R46: =IF(C46="","",IF(O46<>"Booked","",IF(COUNTIF('CUSTOMERS'!$B$5:$B$404,C46)>0,"✓ In CUSTOMERS","Add to CUSTOMERS"))) | S46: =IF(C46="","",IF(OR(J46="Booked",J46="Recurring Client",J46="Lost/Declined"),0,1)) | T46: =IF(B46="","",DATE(YEAR(B46),MONTH(B46),1)) | U46: =IF(OR(S46<>1,L46=""),"",COUNTIFS('LEADS'!$S$5:$S$504,1,'LEADS'!$L$5:$L$504,"<"&L46)+COUNTIFS($S$5:S46,1,$L$5:L46,L46))
A47: L-0043 | B47: 46159 | C47: Blake Dunmore | D47: 555-0119 | E47: blake.dunmore@example.com | F47: Instagram | G47: Deep Clean | H47: Lakeview (fictional) | I47: 260 | J47: Booked | K47: 46160 | O47: =IF(C47="","",IF(OR(J47="Booked",J47="Recurring Client"),"Booked",IF(J47="Lost/Declined","Lost","Open"))) | P47: =IF(C47="","",IF(S47=0,"—",IF(L47="","Set date",IF(L47<AsOf,"Overdue",IF(L47=AsOf,"Due today",IF(L47<=AsOf+SoonDays,"Due soon","Scheduled")))))) | Q47: =IF(C47="","",IF(B47="","",AsOf-B47)) | R47: =IF(C47="","",IF(O47<>"Booked","",IF(COUNTIF('CUSTOMERS'!$B$5:$B$404,C47)>0,"✓ In CUSTOMERS","Add to CUSTOMERS"))) | S47: =IF(C47="","",IF(OR(J47="Booked",J47="Recurring Client",J47="Lost/Declined"),0,1)) | T47: =IF(B47="","",DATE(YEAR(B47),MONTH(B47),1)) | U47: =IF(OR(S47<>1,L47=""),"",COUNTIFS('LEADS'!$S$5:$S$504,1,'LEADS'!$L$5:$L$504,"<"&L47)+COUNTIFS($S$5:S47,1,$L$5:L47,L47))
A48: L-0044 | B48: 46161 | C48: Devon Hayes | D48: 555-0106 | E48: devon.hayes@example.com | F48: Google Business Profile | G48: Deep Clean | H48: Lakeview (fictional) | I48: 530 | J48: Recurring Client | K48: 46162 | O48: =IF(C48="","",IF(OR(J48="Booked",J48="Recurring Client"),"Booked",IF(J48="Lost/Declined","Lost","Open"))) | P48: =IF(C48="","",IF(S48=0,"—",IF(L48="","Set date",IF(L48<AsOf,"Overdue",IF(L48=AsOf,"Due today",IF(L48<=AsOf+SoonDays,"Due soon","Scheduled")))))) | Q48: =IF(C48="","",IF(B48="","",AsOf-B48)) | R48: =IF(C48="","",IF(O48<>"Booked","",IF(COUNTIF('CUSTOMERS'!$B$5:$B$404,C48)>0,"✓ In CUSTOMERS","Add to CUSTOMERS"))) | S48: =IF(C48="","",IF(OR(J48="Booked",J48="Recurring Client",J48="Lost/Declined"),0,1)) | T48: =IF(B48="","",DATE(YEAR(B48),MONTH(B48),1)) | U48: =IF(OR(S48<>1,L48=""),"",COUNTIFS('LEADS'!$S$5:$S$504,1,'LEADS'!$L$5:$L$504,"<"&L48)+COUNTIFS($S$5:S48,1,$L$5:L48,L48))
A49: L-0045 | B49: 46181 | C49: Wren Delgado | D49: 555-0124 | E49: wren.delgado@example.com | F49: Nextdoor | G49: Deep Clean | H49: North Sampletown | I49: 490 | J49: Booked | K49: 46182 | O49: =IF(C49="","",IF(OR(J49="Booked",J49="Recurring Client"),"Booked",IF(J49="Lost/Declined","Lost","Open"))) | P49: =IF(C49="","",IF(S49=0,"—",IF(L49="","Set date",IF(L49<AsOf,"Overdue",IF(L49=AsOf,"Due today",IF(L49<=AsOf+SoonDays,"Due soon","Scheduled")))))) | Q49: =IF(C49="","",IF(B49="","",AsOf-B49)) | R49: =IF(C49="","",IF(O49<>"Booked","",IF(COUNTIF('CUSTOMERS'!$B$5:$B$404,C49)>0,"✓ In CUSTOMERS","Add to CUSTOMERS"))) | S49: =IF(C49="","",IF(OR(J49="Booked",J49="Recurring Client",J49="Lost/Declined"),0,1)) | T49: =IF(B49="","",DATE(YEAR(B49),MONTH(B49),1)) | U49: =IF(OR(S49<>1,L49=""),"",COUNTIFS('LEADS'!$S$5:$S$504,1,'LEADS'!$L$5:$L$504,"<"&L49)+COUNTIFS($S$5:S49,1,$L$5:L49,L49))
A50: L-0046 | B50: 46192 | C50: Oakley Oakes | D50: 555-0147 | E50: oakley.oakes@example.com | F50: Google Search | G50: Deep Clean | H50: Old Mill District | I50: 285 | J50: Lost/Declined | K50: 46197 | M50: No response | O50: =IF(C50="","",IF(OR(J50="Booked",J50="Recurring Client"),"Booked",IF(J50="Lost/Declined","Lost","Open"))) | P50: =IF(C50="","",IF(S50=0,"—",IF(L50="","Set date",IF(L50<AsOf,"Overdue",IF(L50=AsOf,"Due today",IF(L50<=AsOf+SoonDays,"Due soon","Scheduled")))))) | Q50: =IF(C50="","",IF(B50="","",AsOf-B50)) | R50: =IF(C50="","",IF(O50<>"Booked","",IF(COUNTIF('CUSTOMERS'!$B$5:$B$404,C50)>0,"✓ In CUSTOMERS","Add to CUSTOMERS"))) | S50: =IF(C50="","",IF(OR(J50="Booked",J50="Recurring Client",J50="Lost/Declined"),0,1)) | T50: =IF(B50="","",DATE(YEAR(B50),MONTH(B50),1)) | U50: =IF(OR(S50<>1,L50=""),"",COUNTIFS('LEADS'!$S$5:$S$504,1,'LEADS'!$L$5:$L$504,"<"&L50)+COUNTIFS($S$5:S50,1,$L$5:L50,L50))
A51: L-0047 | B51: 46196 | C51: Peyton Garrison | D51: 555-0134 | E51: peyton.garrison@example.com | F51: Referral | G51: Deep Clean | H51: Riverbend (fictional) | I51: 395 | J51: Lost/Declined | K51: 46201 | M51: Timing / availability | O51: =IF(C51="","",IF(OR(J51="Booked",J51="Recurring Client"),"Booked",IF(J51="Lost/Declined","Lost","Open"))) | P51: =IF(C51="","",IF(S51=0,"—",IF(L51="","Set date",IF(L51<AsOf,"Overdue",IF(L51=AsOf,"Due today",IF(L51<=AsOf+SoonDays,"Due soon","Scheduled")))))) | Q51: =IF(C51="","",IF(B51="","",AsOf-B51)) | R51: =IF(C51="","",IF(O51<>"Booked","",IF(COUNTIF('CUSTOMERS'!$B$5:$B$404,C51)>0,"✓ In CUSTOMERS","Add to CUSTOMERS"))) | S51: =IF(C51="","",IF(OR(J51="Booked",J51="Recurring Client",J51="Lost/Declined"),0,1)) | T51: =IF(B51="","",DATE(YEAR(B51),MONTH(B51),1)) | U51: =IF(OR(S51<>1,L51=""),"",COUNTIFS('LEADS'!$S$5:$S$504,1,'LEADS'!$L$5:$L$504,"<"&L51)+COUNTIFS($S$5:S51,1,$L$5:L51,L51))
A52: L-0048 | B52: 46197 | C52: Rowan Ellison | D52: 555-0156 | E52: rowan.ellison@example.com | F52: Facebook | G52: Standard Clean | H52: Sampletown | I52: 160 | J52: Lost/Declined | K52: 46204 | M52: Chose another company | O52: =IF(C52="","",IF(OR(J52="Booked",J52="Recurring Client"),"Booked",IF(J52="Lost/Declined","Lost","Open"))) | P52: =IF(C52="","",IF(S52=0,"—",IF(L52="","Set date",IF(L52<AsOf,"Overdue",IF(L52=AsOf,"Due today",IF(L52<=AsOf+SoonDays,"Due soon","Scheduled")))))) | Q52: =IF(C52="","",IF(B52="","",AsOf-B52)) | R52: =IF(C52="","",IF(O52<>"Booked","",IF(COUNTIF('CUSTOMERS'!$B$5:$B$404,C52)>0,"✓ In CUSTOMERS","Add to CUSTOMERS"))) | S52: =IF(C52="","",IF(OR(J52="Booked",J52="Recurring Client",J52="Lost/Declined"),0,1)) | T52: =IF(B52="","",DATE(YEAR(B52),MONTH(B52),1)) | U52: =IF(OR(S52<>1,L52=""),"",COUNTIFS('LEADS'!$S$5:$S$504,1,'LEADS'!$L$5:$L$504,"<"&L52)+COUNTIFS($S$5:S52,1,$L$5:L52,L52))
A53: L-0049 | B53: 46199 | C53: Quinn Calloway | D53: 555-0153 | E53: quinn.calloway@example.com | F53: Nextdoor | G53: Deep Clean | H53: Riverbend (fictional) | I53: 285 | J53: Lost/Declined | K53: 46203 | M53: Outside service area | O53: =IF(C53="","",IF(OR(J53="Booked",J53="Recurring Client"),"Booked",IF(J53="Lost/Declined","Lost","Open"))) | P53: =IF(C53="","",IF(S53=0,"—",IF(L53="","Set date",IF(L53<AsOf,"Overdue",IF(L53=AsOf,"Due today",IF(L53<=AsOf+SoonDays,"Due soon","Scheduled")))))) | Q53: =IF(C53="","",IF(B53="","",AsOf-B53)) | R53: =IF(C53="","",IF(O53<>"Booked","",IF(COUNTIF('CUSTOMERS'!$B$5:$B$404,C53)>0,"✓ In CUSTOMERS","Add to CUSTOMERS"))) | S53: =IF(C53="","",IF(OR(J53="Booked",J53="Recurring Client",J53="Lost/Declined"),0,1)) | T53: =IF(B53="","",DATE(YEAR(B53),MONTH(B53),1)) | U53: =IF(OR(S53<>1,L53=""),"",COUNTIFS('LEADS'!$S$5:$S$504,1,'LEADS'!$L$5:$L$504,"<"&L53)+COUNTIFS($S$5:S53,1,$L$5:L53,L53))
A54: L-0050 | B54: 46211 | C54: Drew Bennett | D54: 555-0121 | E54: drew.bennett@example.com | F54: Website Form | G54: Deep Clean | H54: Sampletown | I54: 530 | J54: Booked | K54: 46212 | O54: =IF(C54="","",IF(OR(J54="Booked",J54="Recurring Client"),"Booked",IF(J54="Lost/Declined","Lost","Open"))) | P54: =IF(C54="","",IF(S54=0,"—",IF(L54="","Set date",IF(L54<AsOf,"Overdue",IF(L54=AsOf,"Due today",IF(L54<=AsOf+SoonDays,"Due soon","Scheduled")))))) | Q54: =IF(C54="","",IF(B54="","",AsOf-B54)) | R54: =IF(C54="","",IF(O54<>"Booked","",IF(COUNTIF('CUSTOMERS'!$B$5:$B$404,C54)>0,"✓ In CUSTOMERS","Add to CUSTOMERS"))) | S54: =IF(C54="","",IF(OR(J54="Booked",J54="Recurring Client",J54="Lost/Declined"),0,1)) | T54: =IF(B54="","",DATE(YEAR(B54),MONTH(B54),1)) | U54: =IF(OR(S54<>1,L54=""),"",COUNTIFS('LEADS'!$S$5:$S$504,1,'LEADS'!$L$5:$L$504,"<"&L54)+COUNTIFS($S$5:S54,1,$L$5:L54,L54))
A55: L-0051 | B55: 46213 | C55: Robin Ellison | D55: 555-0143 | E55: robin.ellison@example.com | F55: Google Search | G55: Standard Clean | H55: Lakeview (fictional) | I55: 210 | J55: Lost/Declined | K55: 46218 | M55: No response | O55: =IF(C55="","",IF(OR(J55="Booked",J55="Recurring Client"),"Booked",IF(J55="Lost/Declined","Lost","Open"))) | P55: =IF(C55="","",IF(S55=0,"—",IF(L55="","Set date",IF(L55<AsOf,"Overdue",IF(L55=AsOf,"Due today",IF(L55<=AsOf+SoonDays,"Due soon","Scheduled")))))) | Q55: =IF(C55="","",IF(B55="","",AsOf-B55)) | R55: =IF(C55="","",IF(O55<>"Booked","",IF(COUNTIF('CUSTOMERS'!$B$5:$B$404,C55)>0,"✓ In CUSTOMERS","Add to CUSTOMERS"))) | S55: =IF(C55="","",IF(OR(J55="Booked",J55="Recurring Client",J55="Lost/Declined"),0,1)) | T55: =IF(B55="","",DATE(YEAR(B55),MONTH(B55),1)) | U55: =IF(OR(S55<>1,L55=""),"",COUNTIFS('LEADS'!$S$5:$S$504,1,'LEADS'!$L$5:$L$504,"<"&L55)+COUNTIFS($S$5:S55,1,$L$5:L55,L55))
A56: L-0052 | B56: 46218 | C56: Toni Sutton | D56: 555-0161 | E56: toni.sutton@example.com | F56: Facebook | G56: Airbnb Turnover | H56: Riverbend (fictional) | I56: 210 | J56: Lost/Declined | K56: 46226 | M56: Price | O56: =IF(C56="","",IF(OR(J56="Booked",J56="Recurring Client"),"Booked",IF(J56="Lost/Declined","Lost","Open"))) | P56: =IF(C56="","",IF(S56=0,"—",IF(L56="","Set date",IF(L56<AsOf,"Overdue",IF(L56=AsOf,"Due today",IF(L56<=AsOf+SoonDays,"Due soon","Scheduled")))))) | Q56: =IF(C56="","",IF(B56="","",AsOf-B56)) | R56: =IF(C56="","",IF(O56<>"Booked","",IF(COUNTIF('CUSTOMERS'!$B$5:$B$404,C56)>0,"✓ In CUSTOMERS","Add to CUSTOMERS"))) | S56: =IF(C56="","",IF(OR(J56="Booked",J56="Recurring Client",J56="Lost/Declined"),0,1)) | T56: =IF(B56="","",DATE(YEAR(B56),MONTH(B56),1)) | U56: =IF(OR(S56<>1,L56=""),"",COUNTIFS('LEADS'!$S$5:$S$504,1,'LEADS'!$L$5:$L$504,"<"&L56)+COUNTIFS($S$5:S56,1,$L$5:L56,L56))
A57: L-0053 | B57: 46219 | C57: Quinn Jessup | D57: 555-0154 | E57: quinn.jessup@example.com | F57: Flyer / Door Hanger | G57: Move-In/Move-Out | H57: Sampletown | I57: 210 | J57: Lost/Declined | K57: 46222 | M57: Price | O57: =IF(C57="","",IF(OR(J57="Booked",J57="Recurring Client"),"Booked",IF(J57="Lost/Declined","Lost","Open"))) | P57: =IF(C57="","",IF(S57=0,"—",IF(L57="","Set date",IF(L57<AsOf,"Overdue",IF(L57=AsOf,"Due today",IF(L57<=AsOf+SoonDays,"Due soon","Scheduled")))))) | Q57: =IF(C57="","",IF(B57="","",AsOf-B57)) | R57: =IF(C57="","",IF(O57<>"Booked","",IF(COUNTIF('CUSTOMERS'!$B$5:$B$404,C57)>0,"✓ In CUSTOMERS","Add to CUSTOMERS"))) | S57: =IF(C57="","",IF(OR(J57="Booked",J57="Recurring Client",J57="Lost/Declined"),0,1)) | T57: =IF(B57="","",DATE(YEAR(B57),MONTH(B57),1)) | U57: =IF(OR(S57<>1,L57=""),"",COUNTIFS('LEADS'!$S$5:$S$504,1,'LEADS'!$L$5:$L$504,"<"&L57)+COUNTIFS($S$5:S57,1,$L$5:L57,L57))
A58: L-0054 | B58: 46221 | C58: Quinn Ashworth | D58: 555-0125 | E58: quinn.ashworth@example.com | F58: Website Form | G58: Deep Clean | H58: Sampletown | I58: 400 | J58: Booked | K58: 46222 | O58: =IF(C58="","",IF(OR(J58="Booked",J58="Recurring Client"),"Booked",IF(J58="Lost/Declined","Lost","Open"))) | P58: =IF(C58="","",IF(S58=0,"—",IF(L58="","Set date",IF(L58<AsOf,"Overdue",IF(L58=AsOf,"Due today",IF(L58<=AsOf+SoonDays,"Due soon","Scheduled")))))) | Q58: =IF(C58="","",IF(B58="","",AsOf-B58)) | R58: =IF(C58="","",IF(O58<>"Booked","",IF(COUNTIF('CUSTOMERS'!$B$5:$B$404,C58)>0,"✓ In CUSTOMERS","Add to CUSTOMERS"))) | S58: =IF(C58="","",IF(OR(J58="Booked",J58="Recurring Client",J58="Lost/Declined"),0,1)) | T58: =IF(B58="","",DATE(YEAR(B58),MONTH(B58),1)) | U58: =IF(OR(S58<>1,L58=""),"",COUNTIFS('LEADS'!$S$5:$S$504,1,'LEADS'!$L$5:$L$504,"<"&L58)+COUNTIFS($S$5:S58,1,$L$5:L58,L58))
A59: L-0055 | B59: 46228 | C59: Kendall Sutton | D59: 555-0120 | E59: kendall.sutton@example.com | F59: Google Business Profile | G59: Deep Clean | H59: Lakeview (fictional) | I59: 685 | J59: Booked | K59: 46229 | O59: =IF(C59="","",IF(OR(J59="Booked",J59="Recurring Client"),"Booked",IF(J59="Lost/Declined","Lost","Open"))) | P59: =IF(C59="","",IF(S59=0,"—",IF(L59="","Set date",IF(L59<AsOf,"Overdue",IF(L59=AsOf,"Due today",IF(L59<=AsOf+SoonDays,"Due soon","Scheduled")))))) | Q59: =IF(C59="","",IF(B59="","",AsOf-B59)) | R59: =IF(C59="","",IF(O59<>"Booked","",IF(COUNTIF('CUSTOMERS'!$B$5:$B$404,C59)>0,"✓ In CUSTOMERS","Add to CUSTOMERS"))) | S59: =IF(C59="","",IF(OR(J59="Booked",J59="Recurring Client",J59="Lost/Declined"),0,1)) | T59: =IF(B59="","",DATE(YEAR(B59),MONTH(B59),1)) | U59: =IF(OR(S59<>1,L59=""),"",COUNTIFS('LEADS'!$S$5:$S$504,1,'LEADS'!$L$5:$L$504,"<"&L59)+COUNTIFS($S$5:S59,1,$L$5:L59,L59))
A60: L-0056 | B60: 46232 | C60: Harper Garrison | D60: 555-0144 | E60: harper.garrison@example.com | F60: Website Form | G60: Airbnb Turnover | H60: Lakeview (fictional) | I60: 210 | J60: Lost/Declined | K60: 46235 | M60: Outside service area | O60: =IF(C60="","",IF(OR(J60="Booked",J60="Recurring Client"),"Booked",IF(J60="Lost/Declined","Lost","Open"))) | P60: =IF(C60="","",IF(S60=0,"—",IF(L60="","Set date",IF(L60<AsOf,"Overdue",IF(L60=AsOf,"Due today",IF(L60<=AsOf+SoonDays,"Due soon","Scheduled")))))) | Q60: =IF(C60="","",IF(B60="","",AsOf-B60)) | R60: =IF(C60="","",IF(O60<>"Booked","",IF(COUNTIF('CUSTOMERS'!$B$5:$B$404,C60)>0,"✓ In CUSTOMERS","Add to CUSTOMERS"))) | S60: =IF(C60="","",IF(OR(J60="Booked",J60="Recurring Client",J60="Lost/Declined"),0,1)) | T60: =IF(B60="","",DATE(YEAR(B60),MONTH(B60),1)) | U60: =IF(OR(S60<>1,L60=""),"",COUNTIFS('LEADS'!$S$5:$S$504,1,'LEADS'!$L$5:$L$504,"<"&L60)+COUNTIFS($S$5:S60,1,$L$5:L60,L60))
A61: L-0057 | B61: 46243 | C61: Emerson Delgado | D61: 555-0137 | E61: emerson.delgado@example.com | F61: Google Business Profile | G61: Move-In/Move-Out | H61: Sampletown | J61: Lost/Declined | K61: 46248 | M61: Price | O61: =IF(C61="","",IF(OR(J61="Booked",J61="Recurring Client"),"Booked",IF(J61="Lost/Declined","Lost","Open"))) | P61: =IF(C61="","",IF(S61=0,"—",IF(L61="","Set date",IF(L61<AsOf,"Overdue",IF(L61=AsOf,"Due today",IF(L61<=AsOf+SoonDays,"Due soon","Scheduled")))))) | Q61: =IF(C61="","",IF(B61="","",AsOf-B61)) | R61: =IF(C61="","",IF(O61<>"Booked","",IF(COUNTIF('CUSTOMERS'!$B$5:$B$404,C61)>0,"✓ In CUSTOMERS","Add to CUSTOMERS"))) | S61: =IF(C61="","",IF(OR(J61="Booked",J61="Recurring Client",J61="Lost/Declined"),0,1)) | T61: =IF(B61="","",DATE(YEAR(B61),MONTH(B61),1)) | U61: =IF(OR(S61<>1,L61=""),"",COUNTIFS('LEADS'!$S$5:$S$504,1,'LEADS'!$L$5:$L$504,"<"&L61)+COUNTIFS($S$5:S61,1,$L$5:L61,L61))
A62: L-0058 | B62: 46244 | C62: Emerson Calloway | D62: 555-0117 | E62: emerson.calloway@example.com | F62: Google Search | G62: Deep Clean | H62: North Sampletown | I62: 380 | J62: Booked | K62: 46245 | O62: =IF(C62="","",IF(OR(J62="Booked",J62="Recurring Client"),"Booked",IF(J62="Lost/Declined","Lost","Open"))) | P62: =IF(C62="","",IF(S62=0,"—",IF(L62="","Set date",IF(L62<AsOf,"Overdue",IF(L62=AsOf,"Due today",IF(L62<=AsOf+SoonDays,"Due soon","Scheduled")))))) | Q62: =IF(C62="","",IF(B62="","",AsOf-B62)) | R62: =IF(C62="","",IF(O62<>"Booked","",IF(COUNTIF('CUSTOMERS'!$B$5:$B$404,C62)>0,"✓ In CUSTOMERS","Add to CUSTOMERS"))) | S62: =IF(C62="","",IF(OR(J62="Booked",J62="Recurring Client",J62="Lost/Declined"),0,1)) | T62: =IF(B62="","",DATE(YEAR(B62),MONTH(B62),1)) | U62: =IF(OR(S62<>1,L62=""),"",COUNTIFS('LEADS'!$S$5:$S$504,1,'LEADS'!$L$5:$L$504,"<"&L62)+COUNTIFS($S$5:S62,1,$L$5:L62,L62))
A63: L-0059 | B63: 46249 | C63: Skyler Holloway | D63: 555-0149 | E63: skyler.holloway@example.com | F63: Facebook | G63: Airbnb Turnover | H63: Lakeview (fictional) | I63: 395 | J63: Lost/Declined | K63: 46251 | M63: Price | O63: =IF(C63="","",IF(OR(J63="Booked",J63="Recurring Client"),"Booked",IF(J63="Lost/Declined","Lost","Open"))) | P63: =IF(C63="","",IF(S63=0,"—",IF(L63="","Set date",IF(L63<AsOf,"Overdue",IF(L63=AsOf,"Due today",IF(L63<=AsOf+SoonDays,"Due soon","Scheduled")))))) | Q63: =IF(C63="","",IF(B63="","",AsOf-B63)) | R63: =IF(C63="","",IF(O63<>"Booked","",IF(COUNTIF('CUSTOMERS'!$B$5:$B$404,C63)>0,"✓ In CUSTOMERS","Add to CUSTOMERS"))) | S63: =IF(C63="","",IF(OR(J63="Booked",J63="Recurring Client",J63="Lost/Declined"),0,1)) | T63: =IF(B63="","",DATE(YEAR(B63),MONTH(B63),1)) | U63: =IF(OR(S63<>1,L63=""),"",COUNTIFS('LEADS'!$S$5:$S$504,1,'LEADS'!$L$5:$L$504,"<"&L63)+COUNTIFS($S$5:S63,1,$L$5:L63,L63))
A64: L-0060 | B64: 46254 | C64: Peyton Merriweather | D64: 555-0178 | E64: peyton.merriweather@example.com | F64: Nextdoor | G64: Deep Clean | H64: Old Mill District | I64: 165 | J64: Follow-Up | K64: 46255 | L64: 46300 | O64: =IF(C64="","",IF(OR(J64="Booked",J64="Recurring Client"),"Booked",IF(J64="Lost/Declined","Lost","Open"))) | P64: =IF(C64="","",IF(S64=0,"—",IF(L64="","Set date",IF(L64<AsOf,"Overdue",IF(L64=AsOf,"Due today",IF(L64<=AsOf+SoonDays,"Due soon","Scheduled")))))) | Q64: =IF(C64="","",IF(B64="","",AsOf-B64)) | R64: =IF(C64="","",IF(O64<>"Booked","",IF(COUNTIF('CUSTOMERS'!$B$5:$B$404,C64)>0,"✓ In CUSTOMERS","Add to CUSTOMERS"))) | S64: =IF(C64="","",IF(OR(J64="Booked",J64="Recurring Client",J64="Lost/Declined"),0,1)) | T64: =IF(B64="","",DATE(YEAR(B64),MONTH(B64),1)) | U64: =IF(OR(S64<>1,L64=""),"",COUNTIFS('LEADS'!$S$5:$S$504,1,'LEADS'!$L$5:$L$504,"<"&L64)+COUNTIFS($S$5:S64,1,$L$5:L64,L64))
A65: L-0061 | B65: 46257 | C65: Noel Everly | D65: 555-0177 | E65: noel.everly@example.com | F65: Google Search | G65: Move-In/Move-Out | H65: North Sampletown | I65: 190 | J65: Follow-Up | K65: 46258 | L65: 46298 | O65: =IF(C65="","",IF(OR(J65="Booked",J65="Recurring Client"),"Booked",IF(J65="Lost/Declined","Lost","Open"))) | P65: =IF(C65="","",IF(S65=0,"—",IF(L65="","Set date",IF(L65<AsOf,"Overdue",IF(L65=AsOf,"Due today",IF(L65<=AsOf+SoonDays,"Due soon","Scheduled")))))) | Q65: =IF(C65="","",IF(B65="","",AsOf-B65)) | R65: =IF(C65="","",IF(O65<>"Booked","",IF(COUNTIF('CUSTOMERS'!$B$5:$B$404,C65)>0,"✓ In CUSTOMERS","Add to CUSTOMERS"))) | S65: =IF(C65="","",IF(OR(J65="Booked",J65="Recurring Client",J65="Lost/Declined"),0,1)) | T65: =IF(B65="","",DATE(YEAR(B65),MONTH(B65),1)) | U65: =IF(OR(S65<>1,L65=""),"",COUNTIFS('LEADS'!$S$5:$S$504,1,'LEADS'!$L$5:$L$504,"<"&L65)+COUNTIFS($S$5:S65,1,$L$5:L65,L65))
A66: L-0062 | B66: 46264 | C66: Harper Hayes | D66: 555-0116 | E66: harper.hayes@example.com | F66: Referral | G66: Deep Clean | H66: North Sampletown | I66: 365 | J66: Booked | K66: 46265 | O66: =IF(C66="","",IF(OR(J66="Booked",J66="Recurring Client"),"Booked",IF(J66="Lost/Declined","Lost","Open"))) | P66: =IF(C66="","",IF(S66=0,"—",IF(L66="","Set date",IF(L66<AsOf,"Overdue",IF(L66=AsOf,"Due today",IF(L66<=AsOf+SoonDays,"Due soon","Scheduled")))))) | Q66: =IF(C66="","",IF(B66="","",AsOf-B66)) | R66: =IF(C66="","",IF(O66<>"Booked","",IF(COUNTIF('CUSTOMERS'!$B$5:$B$404,C66)>0,"✓ In CUSTOMERS","Add to CUSTOMERS"))) | S66: =IF(C66="","",IF(OR(J66="Booked",J66="Recurring Client",J66="Lost/Declined"),0,1)) | T66: =IF(B66="","",DATE(YEAR(B66),MONTH(B66),1)) | U66: =IF(OR(S66<>1,L66=""),"",COUNTIFS('LEADS'!$S$5:$S$504,1,'LEADS'!$L$5:$L$504,"<"&L66)+COUNTIFS($S$5:S66,1,$L$5:L66,L66))
A67: L-0063 | B67: 46264 | C67: Emerson Whitaker | D67: 555-0176 | E67: emerson.whitaker@example.com | F67: Google Search | G67: Commercial Clean | H67: North Sampletown | I67: 165 | J67: Follow-Up | K67: 46265 | L67: 46294 | O67: =IF(C67="","",IF(OR(J67="Booked",J67="Recurring Client"),"Booked",IF(J67="Lost/Declined","Lost","Open"))) | P67: =IF(C67="","",IF(S67=0,"—",IF(L67="","Set date",IF(L67<AsOf,"Overdue",IF(L67=AsOf,"Due today",IF(L67<=AsOf+SoonDays,"Due soon","Scheduled")))))) | Q67: =IF(C67="","",IF(B67="","",AsOf-B67)) | R67: =IF(C67="","",IF(O67<>"Booked","",IF(COUNTIF('CUSTOMERS'!$B$5:$B$404,C67)>0,"✓ In CUSTOMERS","Add to CUSTOMERS"))) | S67: =IF(C67="","",IF(OR(J67="Booked",J67="Recurring Client",J67="Lost/Declined"),0,1)) | T67: =IF(B67="","",DATE(YEAR(B67),MONTH(B67),1)) | U67: =IF(OR(S67<>1,L67=""),"",COUNTIFS('LEADS'!$S$5:$S$504,1,'LEADS'!$L$5:$L$504,"<"&L67)+COUNTIFS($S$5:S67,1,$L$5:L67,L67))
A68: L-0064 | B68: 46273 | C68: Sage Sterling | D68: 555-0175 | E68: sage.sterling@example.com | F68: Nextdoor | G68: Airbnb Turnover | H68: North Sampletown | I68: 520 | J68: Quote Sent | K68: 46274 | L68: 46291 | O68: =IF(C68="","",IF(OR(J68="Booked",J68="Recurring Client"),"Booked",IF(J68="Lost/Declined","Lost","Open"))) | P68: =IF(C68="","",IF(S68=0,"—",IF(L68="","Set date",IF(L68<AsOf,"Overdue",IF(L68=AsOf,"Due today",IF(L68<=AsOf+SoonDays,"Due soon","Scheduled")))))) | Q68: =IF(C68="","",IF(B68="","",AsOf-B68)) | R68: =IF(C68="","",IF(O68<>"Booked","",IF(COUNTIF('CUSTOMERS'!$B$5:$B$404,C68)>0,"✓ In CUSTOMERS","Add to CUSTOMERS"))) | S68: =IF(C68="","",IF(OR(J68="Booked",J68="Recurring Client",J68="Lost/Declined"),0,1)) | T68: =IF(B68="","",DATE(YEAR(B68),MONTH(B68),1)) | U68: =IF(OR(S68<>1,L68=""),"",COUNTIFS('LEADS'!$S$5:$S$504,1,'LEADS'!$L$5:$L$504,"<"&L68)+COUNTIFS($S$5:S68,1,$L$5:L68,L68))
A69: L-0065 | B69: 46280 | C69: Morgan Ivers | D69: 555-0174 | E69: morgan.ivers@example.com | F69: Website Form | G69: Commercial Clean | H69: Old Mill District | I69: 240 | J69: Quote Sent | K69: 46281 | L69: 46297 | O69: =IF(C69="","",IF(OR(J69="Booked",J69="Recurring Client"),"Booked",IF(J69="Lost/Declined","Lost","Open"))) | P69: =IF(C69="","",IF(S69=0,"—",IF(L69="","Set date",IF(L69<AsOf,"Overdue",IF(L69=AsOf,"Due today",IF(L69<=AsOf+SoonDays,"Due soon","Scheduled")))))) | Q69: =IF(C69="","",IF(B69="","",AsOf-B69)) | R69: =IF(C69="","",IF(O69<>"Booked","",IF(COUNTIF('CUSTOMERS'!$B$5:$B$404,C69)>0,"✓ In CUSTOMERS","Add to CUSTOMERS"))) | S69: =IF(C69="","",IF(OR(J69="Booked",J69="Recurring Client",J69="Lost/Declined"),0,1)) | T69: =IF(B69="","",DATE(YEAR(B69),MONTH(B69),1)) | U69: =IF(OR(S69<>1,L69=""),"",COUNTIFS('LEADS'!$S$5:$S$504,1,'LEADS'!$L$5:$L$504,"<"&L69)+COUNTIFS($S$5:S69,1,$L$5:L69,L69))
A70: L-0066 | B70: 46283 | C70: Sage Calloway | D70: 555-0173 | E70: sage.calloway@example.com | F70: Flyer / Door Hanger | G70: Commercial Clean | H70: Lakeview (fictional) | I70: 365 | J70: Quote Sent | K70: 46284 | L70: 46292 | O70: =IF(C70="","",IF(OR(J70="Booked",J70="Recurring Client"),"Booked",IF(J70="Lost/Declined","Lost","Open"))) | P70: =IF(C70="","",IF(S70=0,"—",IF(L70="","Set date",IF(L70<AsOf,"Overdue",IF(L70=AsOf,"Due today",IF(L70<=AsOf+SoonDays,"Due soon","Scheduled")))))) | Q70: =IF(C70="","",IF(B70="","",AsOf-B70)) | R70: =IF(C70="","",IF(O70<>"Booked","",IF(COUNTIF('CUSTOMERS'!$B$5:$B$404,C70)>0,"✓ In CUSTOMERS","Add to CUSTOMERS"))) | S70: =IF(C70="","",IF(OR(J70="Booked",J70="Recurring Client",J70="Lost/Declined"),0,1)) | T70: =IF(B70="","",DATE(YEAR(B70),MONTH(B70),1)) | U70: =IF(OR(S70<>1,L70=""),"",COUNTIFS('LEADS'!$S$5:$S$504,1,'LEADS'!$L$5:$L$504,"<"&L70)+COUNTIFS($S$5:S70,1,$L$5:L70,L70))
A71: L-0067 | B71: 46286 | C71: Parker Ransford | D71: 555-0172 | E71: parker.ransford@example.com | F71: Referral | G71: Standard Clean | H71: Sampletown | I71: 420 | J71: Quote Sent | K71: 46287 | L71: 46296 | O71: =IF(C71="","",IF(OR(J71="Booked",J71="Recurring Client"),"Booked",IF(J71="Lost/Declined","Lost","Open"))) | P71: =IF(C71="","",IF(S71=0,"—",IF(L71="","Set date",IF(L71<AsOf,"Overdue",IF(L71=AsOf,"Due today",IF(L71<=AsOf+SoonDays,"Due soon","Scheduled")))))) | Q71: =IF(C71="","",IF(B71="","",AsOf-B71)) | R71: =IF(C71="","",IF(O71<>"Booked","",IF(COUNTIF('CUSTOMERS'!$B$5:$B$404,C71)>0,"✓ In CUSTOMERS","Add to CUSTOMERS"))) | S71: =IF(C71="","",IF(OR(J71="Booked",J71="Recurring Client",J71="Lost/Declined"),0,1)) | T71: =IF(B71="","",DATE(YEAR(B71),MONTH(B71),1)) | U71: =IF(OR(S71<>1,L71=""),"",COUNTIFS('LEADS'!$S$5:$S$504,1,'LEADS'!$L$5:$L$504,"<"&L71)+COUNTIFS($S$5:S71,1,$L$5:L71,L71))
A72: L-0068 | B72: 46287 | C72: Casey Sterling | D72: 555-0169 | E72: casey.sterling@example.com | F72: Referral | G72: Airbnb Turnover | H72: North Sampletown | J72: Contacted | K72: 46288 | L72: 46297 | O72: =IF(C72="","",IF(OR(J72="Booked",J72="Recurring Client"),"Booked",IF(J72="Lost/Declined","Lost","Open"))) | P72: =IF(C72="","",IF(S72=0,"—",IF(L72="","Set date",IF(L72<AsOf,"Overdue",IF(L72=AsOf,"Due today",IF(L72<=AsOf+SoonDays,"Due soon","Scheduled")))))) | Q72: =IF(C72="","",IF(B72="","",AsOf-B72)) | R72: =IF(C72="","",IF(O72<>"Booked","",IF(COUNTIF('CUSTOMERS'!$B$5:$B$404,C72)>0,"✓ In CUSTOMERS","Add to CUSTOMERS"))) | S72: =IF(C72="","",IF(OR(J72="Booked",J72="Recurring Client",J72="Lost/Declined"),0,1)) | T72: =IF(B72="","",DATE(YEAR(B72),MONTH(B72),1)) | U72: =IF(OR(S72<>1,L72=""),"",COUNTIFS('LEADS'!$S$5:$S$504,1,'LEADS'!$L$5:$L$504,"<"&L72)+COUNTIFS($S$5:S72,1,$L$5:L72,L72))
A73: L-0069 | B73: 46288 | C73: Blair Sutton | D73: 555-0171 | E73: blair.sutton@example.com | F73: Instagram | G73: Airbnb Turnover | H73: Riverbend (fictional) | J73: Quote Requested | K73: 46289 | L73: 46294 | O73: =IF(C73="","",IF(OR(J73="Booked",J73="Recurring Client"),"Booked",IF(J73="Lost/Declined","Lost","Open"))) | P73: =IF(C73="","",IF(S73=0,"—",IF(L73="","Set date",IF(L73<AsOf,"Overdue",IF(L73=AsOf,"Due today",IF(L73<=AsOf+SoonDays,"Due soon","Scheduled")))))) | Q73: =IF(C73="","",IF(B73="","",AsOf-B73)) | R73: =IF(C73="","",IF(O73<>"Booked","",IF(COUNTIF('CUSTOMERS'!$B$5:$B$404,C73)>0,"✓ In CUSTOMERS","Add to CUSTOMERS"))) | S73: =IF(C73="","",IF(OR(J73="Booked",J73="Recurring Client",J73="Lost/Declined"),0,1)) | T73: =IF(B73="","",DATE(YEAR(B73),MONTH(B73),1)) | U73: =IF(OR(S73<>1,L73=""),"",COUNTIFS('LEADS'!$S$5:$S$504,1,'LEADS'!$L$5:$L$504,"<"&L73)+COUNTIFS($S$5:S73,1,$L$5:L73,L73))
A74: L-0070 | B74: 46290 | C74: Lane Garrison | D74: 555-0167 | E74: lane.garrison@example.com | F74: Flyer / Door Hanger | G74: Commercial Clean | H74: Lakeview (fictional) | J74: Contacted | K74: 46291 | L74: 46295 | O74: =IF(C74="","",IF(OR(J74="Booked",J74="Recurring Client"),"Booked",IF(J74="Lost/Declined","Lost","Open"))) | P74: =IF(C74="","",IF(S74=0,"—",IF(L74="","Set date",IF(L74<AsOf,"Overdue",IF(L74=AsOf,"Due today",IF(L74<=AsOf+SoonDays,"Due soon","Scheduled")))))) | Q74: =IF(C74="","",IF(B74="","",AsOf-B74)) | R74: =IF(C74="","",IF(O74<>"Booked","",IF(COUNTIF('CUSTOMERS'!$B$5:$B$404,C74)>0,"✓ In CUSTOMERS","Add to CUSTOMERS"))) | S74: =IF(C74="","",IF(OR(J74="Booked",J74="Recurring Client",J74="Lost/Declined"),0,1)) | T74: =IF(B74="","",DATE(YEAR(B74),MONTH(B74),1)) | U74: =IF(OR(S74<>1,L74=""),"",COUNTIFS('LEADS'!$S$5:$S$504,1,'LEADS'!$L$5:$L$504,"<"&L74)+COUNTIFS($S$5:S74,1,$L$5:L74,L74))
A75: L-0071 | B75: 46290 | C75: Marlow Delgado | D75: 555-0168 | E75: marlow.delgado@example.com | F75: Website Form | G75: Airbnb Turnover | H75: Sampletown | J75: Contacted | K75: 46291 | L75: 46293 | O75: =IF(C75="","",IF(OR(J75="Booked",J75="Recurring Client"),"Booked",IF(J75="Lost/Declined","Lost","Open"))) | P75: =IF(C75="","",IF(S75=0,"—",IF(L75="","Set date",IF(L75<AsOf,"Overdue",IF(L75=AsOf,"Due today",IF(L75<=AsOf+SoonDays,"Due soon","Scheduled")))))) | Q75: =IF(C75="","",IF(B75="","",AsOf-B75)) | R75: =IF(C75="","",IF(O75<>"Booked","",IF(COUNTIF('CUSTOMERS'!$B$5:$B$404,C75)>0,"✓ In CUSTOMERS","Add to CUSTOMERS"))) | S75: =IF(C75="","",IF(OR(J75="Booked",J75="Recurring Client",J75="Lost/Declined"),0,1)) | T75: =IF(B75="","",DATE(YEAR(B75),MONTH(B75),1)) | U75: =IF(OR(S75<>1,L75=""),"",COUNTIFS('LEADS'!$S$5:$S$504,1,'LEADS'!$L$5:$L$504,"<"&L75)+COUNTIFS($S$5:S75,1,$L$5:L75,L75))
A76: L-0072 | B76: 46292 | C76: Jamie Sutton | D76: 555-0166 | E76: jamie.sutton@example.com | F76: Nextdoor | G76: Commercial Clean | H76: North Sampletown | J76: New Lead | K76: 46293 | L76: 46294 | O76: =IF(C76="","",IF(OR(J76="Booked",J76="Recurring Client"),"Booked",IF(J76="Lost/Declined","Lost","Open"))) | P76: =IF(C76="","",IF(S76=0,"—",IF(L76="","Set date",IF(L76<AsOf,"Overdue",IF(L76=AsOf,"Due today",IF(L76<=AsOf+SoonDays,"Due soon","Scheduled")))))) | Q76: =IF(C76="","",IF(B76="","",AsOf-B76)) | R76: =IF(C76="","",IF(O76<>"Booked","",IF(COUNTIF('CUSTOMERS'!$B$5:$B$404,C76)>0,"✓ In CUSTOMERS","Add to CUSTOMERS"))) | S76: =IF(C76="","",IF(OR(J76="Booked",J76="Recurring Client",J76="Lost/Declined"),0,1)) | T76: =IF(B76="","",DATE(YEAR(B76),MONTH(B76),1)) | U76: =IF(OR(S76<>1,L76=""),"",COUNTIFS('LEADS'!$S$5:$S$504,1,'LEADS'!$L$5:$L$504,"<"&L76)+COUNTIFS($S$5:S76,1,$L$5:L76,L76))
A77: L-0073 | B77: 46292 | C77: Tatum Ashworth | D77: 555-0179 | E77: tatum.ashworth@example.com | F77: Referral | G77: Deep Clean | H77: Sampletown | I77: 345 | J77: Booked | K77: 46294 | N77: Booked for Oct 8 — add to CUSTOMERS | O77: =IF(C77="","",IF(OR(J77="Booked",J77="Recurring Client"),"Booked",IF(J77="Lost/Declined","Lost","Open"))) | P77: =IF(C77="","",IF(S77=0,"—",IF(L77="","Set date",IF(L77<AsOf,"Overdue",IF(L77=AsOf,"Due today",IF(L77<=AsOf+SoonDays,"Due soon","Scheduled")))))) | Q77: =IF(C77="","",IF(B77="","",AsOf-B77)) | R77: =IF(C77="","",IF(O77<>"Booked","",IF(COUNTIF('CUSTOMERS'!$B$5:$B$404,C77)>0,"✓ In CUSTOMERS","Add to CUSTOMERS"))) | S77: =IF(C77="","",IF(OR(J77="Booked",J77="Recurring Client",J77="Lost/Declined"),0,1)) | T77: =IF(B77="","",DATE(YEAR(B77),MONTH(B77),1)) | U77: =IF(OR(S77<>1,L77=""),"",COUNTIFS('LEADS'!$S$5:$S$504,1,'LEADS'!$L$5:$L$504,"<"&L77)+COUNTIFS($S$5:S77,1,$L$5:L77,L77))
A78: L-0074 | B78: 46293 | C78: Micah Everly | D78: 555-0170 | E78: micah.everly@example.com | F78: Google Search | G78: Move-In/Move-Out | H78: Riverbend (fictional) | J78: Quote Requested | K78: 46294 | L78: 46296 | O78: =IF(C78="","",IF(OR(J78="Booked",J78="Recurring Client"),"Booked",IF(J78="Lost/Declined","Lost","Open"))) | P78: =IF(C78="","",IF(S78=0,"—",IF(L78="","Set date",IF(L78<AsOf,"Overdue",IF(L78=AsOf,"Due today",IF(L78<=AsOf+SoonDays,"Due soon","Scheduled")))))) | Q78: =IF(C78="","",IF(B78="","",AsOf-B78)) | R78: =IF(C78="","",IF(O78<>"Booked","",IF(COUNTIF('CUSTOMERS'!$B$5:$B$404,C78)>0,"✓ In CUSTOMERS","Add to CUSTOMERS"))) | S78: =IF(C78="","",IF(OR(J78="Booked",J78="Recurring Client",J78="Lost/Declined"),0,1)) | T78: =IF(B78="","",DATE(YEAR(B78),MONTH(B78),1)) | U78: =IF(OR(S78<>1,L78=""),"",COUNTIFS('LEADS'!$S$5:$S$504,1,'LEADS'!$L$5:$L$504,"<"&L78)+COUNTIFS($S$5:S78,1,$L$5:L78,L78))
A79: L-0075 | B79: 46294 | C79: Lane Pembrook | D79: 555-0164 | E79: lane.pembrook@example.com | F79: Google Search | G79: Move-In/Move-Out | H79: North Sampletown | J79: New Lead | O79: =IF(C79="","",IF(OR(J79="Booked",J79="Recurring Client"),"Booked",IF(J79="Lost/Declined","Lost","Open"))) | P79: =IF(C79="","",IF(S79=0,"—",IF(L79="","Set date",IF(L79<AsOf,"Overdue",IF(L79=AsOf,"Due today",IF(L79<=AsOf+SoonDays,"Due soon","Scheduled")))))) | Q79: =IF(C79="","",IF(B79="","",AsOf-B79)) | R79: =IF(C79="","",IF(O79<>"Booked","",IF(COUNTIF('CUSTOMERS'!$B$5:$B$404,C79)>0,"✓ In CUSTOMERS","Add to CUSTOMERS"))) | S79: =IF(C79="","",IF(OR(J79="Booked",J79="Recurring Client",J79="Lost/Declined"),0,1)) | T79: =IF(B79="","",DATE(YEAR(B79),MONTH(B79),1)) | U79: =IF(OR(S79<>1,L79=""),"",COUNTIFS('LEADS'!$S$5:$S$504,1,'LEADS'!$L$5:$L$504,"<"&L79)+COUNTIFS($S$5:S79,1,$L$5:L79,L79))
A80: L-0076 | B80: 46294 | C80: Avery Fairbanks | D80: 555-0165 | E80: avery.fairbanks@example.com | F80: Google Business Profile | G80: Airbnb Turnover | H80: North Sampletown | J80: New Lead | K80: 46295 | L80: 46295 | O80: =IF(C80="","",IF(OR(J80="Booked",J80="Recurring Client"),"Booked",IF(J80="Lost/Declined","Lost","Open"))) | P80: =IF(C80="","",IF(S80=0,"—",IF(L80="","Set date",IF(L80<AsOf,"Overdue",IF(L80=AsOf,"Due today",IF(L80<=AsOf+SoonDays,"Due soon","Scheduled")))))) | Q80: =IF(C80="","",IF(B80="","",AsOf-B80)) | R80: =IF(C80="","",IF(O80<>"Booked","",IF(COUNTIF('CUSTOMERS'!$B$5:$B$404,C80)>0,"✓ In CUSTOMERS","Add to CUSTOMERS"))) | S80: =IF(C80="","",IF(OR(J80="Booked",J80="Recurring Client",J80="Lost/Declined"),0,1)) | T80: =IF(B80="","",DATE(YEAR(B80),MONTH(B80),1)) | U80: =IF(OR(S80<>1,L80=""),"",COUNTIFS('LEADS'!$S$5:$S$504,1,'LEADS'!$L$5:$L$504,"<"&L80)+COUNTIFS($S$5:S80,1,$L$5:L80,L80))
A81: L-0077 | O81: =IF(C81="","",IF(OR(J81="Booked",J81="Recurring Client"),"Booked",IF(J81="Lost/Declined","Lost","Open"))) | P81: =IF(C81="","",IF(S81=0,"—",IF(L81="","Set date",IF(L81<AsOf,"Overdue",IF(L81=AsOf,"Due today",IF(L81<=AsOf+SoonDays,"Due soon","Scheduled")))))) | Q81: =IF(C81="","",IF(B81="","",AsOf-B81)) | R81: =IF(C81="","",IF(O81<>"Booked","",IF(COUNTIF('CUSTOMERS'!$B$5:$B$404,C81)>0,"✓ In CUSTOMERS","Add to CUSTOMERS"))) | S81: =IF(C81="","",IF(OR(J81="Booked",J81="Recurring Client",J81="Lost/Declined"),0,1)) | T81: =IF(B81="","",DATE(YEAR(B81),MONTH(B81),1)) | U81: =IF(OR(S81<>1,L81=""),"",COUNTIFS('LEADS'!$S$5:$S$504,1,'LEADS'!$L$5:$L$504,"<"&L81)+COUNTIFS($S$5:S81,1,$L$5:L81,L81))
A82: L-0078 | O82: =IF(C82="","",IF(OR(J82="Booked",J82="Recurring Client"),"Booked",IF(J82="Lost/Declined","Lost","Open"))) | P82: =IF(C82="","",IF(S82=0,"—",IF(L82="","Set date",IF(L82<AsOf,"Overdue",IF(L82=AsOf,"Due today",IF(L82<=AsOf+SoonDays,"Due soon","Scheduled")))))) | Q82: =IF(C82="","",IF(B82="","",AsOf-B82)) | R82: =IF(C82="","",IF(O82<>"Booked","",IF(COUNTIF('CUSTOMERS'!$B$5:$B$404,C82)>0,"✓ In CUSTOMERS","Add to CUSTOMERS"))) | S82: =IF(C82="","",IF(OR(J82="Booked",J82="Recurring Client",J82="Lost/Declined"),0,1)) | T82: =IF(B82="","",DATE(YEAR(B82),MONTH(B82),1)) | U82: =IF(OR(S82<>1,L82=""),"",COUNTIFS('LEADS'!$S$5:$S$504,1,'LEADS'!$L$5:$L$504,"<"&L82)+COUNTIFS($S$5:S82,1,$L$5:L82,L82))
A83: L-0079 | O83: =IF(C83="","",IF(OR(J83="Booked",J83="Recurring Client"),"Booked",IF(J83="Lost/Declined","Lost","Open"))) | P83: =IF(C83="","",IF(S83=0,"—",IF(L83="","Set date",IF(L83<AsOf,"Overdue",IF(L83=AsOf,"Due today",IF(L83<=AsOf+SoonDays,"Due soon","Scheduled")))))) | Q83: =IF(C83="","",IF(B83="","",AsOf-B83)) | R83: =IF(C83="","",IF(O83<>"Booked","",IF(COUNTIF('CUSTOMERS'!$B$5:$B$404,C83)>0,"✓ In CUSTOMERS","Add to CUSTOMERS"))) | S83: =IF(C83="","",IF(OR(J83="Booked",J83="Recurring Client",J83="Lost/Declined"),0,1)) | T83: =IF(B83="","",DATE(YEAR(B83),MONTH(B83),1)) | U83: =IF(OR(S83<>1,L83=""),"",COUNTIFS('LEADS'!$S$5:$S$504,1,'LEADS'!$L$5:$L$504,"<"&L83)+COUNTIFS($S$5:S83,1,$L$5:L83,L83))
A84: L-0080 | O84: =IF(C84="","",IF(OR(J84="Booked",J84="Recurring Client"),"Booked",IF(J84="Lost/Declined","Lost","Open"))) | P84: =IF(C84="","",IF(S84=0,"—",IF(L84="","Set date",IF(L84<AsOf,"Overdue",IF(L84=AsOf,"Due today",IF(L84<=AsOf+SoonDays,"Due soon","Scheduled")))))) | Q84: =IF(C84="","",IF(B84="","",AsOf-B84)) | R84: =IF(C84="","",IF(O84<>"Booked","",IF(COUNTIF('CUSTOMERS'!$B$5:$B$404,C84)>0,"✓ In CUSTOMERS","Add to CUSTOMERS"))) | S84: =IF(C84="","",IF(OR(J84="Booked",J84="Recurring Client",J84="Lost/Declined"),0,1)) | T84: =IF(B84="","",DATE(YEAR(B84),MONTH(B84),1)) | U84: =IF(OR(S84<>1,L84=""),"",COUNTIFS('LEADS'!$S$5:$S$504,1,'LEADS'!$L$5:$L$504,"<"&L84)+COUNTIFS($S$5:S84,1,$L$5:L84,L84))
A85: L-0081 | O85: =IF(C85="","",IF(OR(J85="Booked",J85="Recurring Client"),"Booked",IF(J85="Lost/Declined","Lost","Open"))) | P85: =IF(C85="","",IF(S85=0,"—",IF(L85="","Set date",IF(L85<AsOf,"Overdue",IF(L85=AsOf,"Due today",IF(L85<=AsOf+SoonDays,"Due soon","Scheduled")))))) | Q85: =IF(C85="","",IF(B85="","",AsOf-B85)) | R85: =IF(C85="","",IF(O85<>"Booked","",IF(COUNTIF('CUSTOMERS'!$B$5:$B$404,C85)>0,"✓ In CUSTOMERS","Add to CUSTOMERS"))) | S85: =IF(C85="","",IF(OR(J85="Booked",J85="Recurring Client",J85="Lost/Declined"),0,1)) | T85: =IF(B85="","",DATE(YEAR(B85),MONTH(B85),1)) | U85: =IF(OR(S85<>1,L85=""),"",COUNTIFS('LEADS'!$S$5:$S$504,1,'LEADS'!$L$5:$L$504,"<"&L85)+COUNTIFS($S$5:S85,1,$L$5:L85,L85))
A86: L-0082 | O86: =IF(C86="","",IF(OR(J86="Booked",J86="Recurring Client"),"Booked",IF(J86="Lost/Declined","Lost","Open"))) | P86: =IF(C86="","",IF(S86=0,"—",IF(L86="","Set date",IF(L86<AsOf,"Overdue",IF(L86=AsOf,"Due today",IF(L86<=AsOf+SoonDays,"Due soon","Scheduled")))))) | Q86: =IF(C86="","",IF(B86="","",AsOf-B86)) | R86: =IF(C86="","",IF(O86<>"Booked","",IF(COUNTIF('CUSTOMERS'!$B$5:$B$404,C86)>0,"✓ In CUSTOMERS","Add to CUSTOMERS"))) | S86: =IF(C86="","",IF(OR(J86="Booked",J86="Recurring Client",J86="Lost/Declined"),0,1)) | T86: =IF(B86="","",DATE(YEAR(B86),MONTH(B86),1)) | U86: =IF(OR(S86<>1,L86=""),"",COUNTIFS('LEADS'!$S$5:$S$504,1,'LEADS'!$L$5:$L$504,"<"&L86)+COUNTIFS($S$5:S86,1,$L$5:L86,L86))
A87: L-0083 | O87: =IF(C87="","",IF(OR(J87="Booked",J87="Recurring Client"),"Booked",IF(J87="Lost/Declined","Lost","Open"))) | P87: =IF(C87="","",IF(S87=0,"—",IF(L87="","Set date",IF(L87<AsOf,"Overdue",IF(L87=AsOf,"Due today",IF(L87<=AsOf+SoonDays,"Due soon","Scheduled")))))) | Q87: =IF(C87="","",IF(B87="","",AsOf-B87)) | R87: =IF(C87="","",IF(O87<>"Booked","",IF(COUNTIF('CUSTOMERS'!$B$5:$B$404,C87)>0,"✓ In CUSTOMERS","Add to CUSTOMERS"))) | S87: =IF(C87="","",IF(OR(J87="Booked",J87="Recurring Client",J87="Lost/Declined"),0,1)) | T87: =IF(B87="","",DATE(YEAR(B87),MONTH(B87),1)) | U87: =IF(OR(S87<>1,L87=""),"",COUNTIFS('LEADS'!$S$5:$S$504,1,'LEADS'!$L$5:$L$504,"<"&L87)+COUNTIFS($S$5:S87,1,$L$5:L87,L87))
A88: L-0084 | O88: =IF(C88="","",IF(OR(J88="Booked",J88="Recurring Client"),"Booked",IF(J88="Lost/Declined","Lost","Open"))) | P88: =IF(C88="","",IF(S88=0,"—",IF(L88="","Set date",IF(L88<AsOf,"Overdue",IF(L88=AsOf,"Due today",IF(L88<=AsOf+SoonDays,"Due soon","Scheduled")))))) | Q88: =IF(C88="","",IF(B88="","",AsOf-B88)) | R88: =IF(C88="","",IF(O88<>"Booked","",IF(COUNTIF('CUSTOMERS'!$B$5:$B$404,C88)>0,"✓ In CUSTOMERS","Add to CUSTOMERS"))) | S88: =IF(C88="","",IF(OR(J88="Booked",J88="Recurring Client",J88="Lost/Declined"),0,1)) | T88: =IF(B88="","",DATE(YEAR(B88),MONTH(B88),1)) | U88: =IF(OR(S88<>1,L88=""),"",COUNTIFS('LEADS'!$S$5:$S$504,1,'LEADS'!$L$5:$L$504,"<"&L88)+COUNTIFS($S$5:S88,1,$L$5:L88,L88))
A89: L-0085 | O89: =IF(C89="","",IF(OR(J89="Booked",J89="Recurring Client"),"Booked",IF(J89="Lost/Declined","Lost","Open"))) | P89: =IF(C89="","",IF(S89=0,"—",IF(L89="","Set date",IF(L89<AsOf,"Overdue",IF(L89=AsOf,"Due today",IF(L89<=AsOf+SoonDays,"Due soon","Scheduled")))))) | Q89: =IF(C89="","",IF(B89="","",AsOf-B89)) | R89: =IF(C89="","",IF(O89<>"Booked","",IF(COUNTIF('CUSTOMERS'!$B$5:$B$404,C89)>0,"✓ In CUSTOMERS","Add to CUSTOMERS"))) | S89: =IF(C89="","",IF(OR(J89="Booked",J89="Recurring Client",J89="Lost/Declined"),0,1)) | T89: =IF(B89="","",DATE(YEAR(B89),MONTH(B89),1)) | U89: =IF(OR(S89<>1,L89=""),"",COUNTIFS('LEADS'!$S$5:$S$504,1,'LEADS'!$L$5:$L$504,"<"&L89)+COUNTIFS($S$5:S89,1,$L$5:L89,L89))
A90: L-0086 | O90: =IF(C90="","",IF(OR(J90="Booked",J90="Recurring Client"),"Booked",IF(J90="Lost/Declined","Lost","Open"))) | P90: =IF(C90="","",IF(S90=0,"—",IF(L90="","Set date",IF(L90<AsOf,"Overdue",IF(L90=AsOf,"Due today",IF(L90<=AsOf+SoonDays,"Due soon","Scheduled")))))) | Q90: =IF(C90="","",IF(B90="","",AsOf-B90)) | R90: =IF(C90="","",IF(O90<>"Booked","",IF(COUNTIF('CUSTOMERS'!$B$5:$B$404,C90)>0,"✓ In CUSTOMERS","Add to CUSTOMERS"))) | S90: =IF(C90="","",IF(OR(J90="Booked",J90="Recurring Client",J90="Lost/Declined"),0,1)) | T90: =IF(B90="","",DATE(YEAR(B90),MONTH(B90),1)) | U90: =IF(OR(S90<>1,L90=""),"",COUNTIFS('LEADS'!$S$5:$S$504,1,'LEADS'!$L$5:$L$504,"<"&L90)+COUNTIFS($S$5:S90,1,$L$5:L90,L90))
A91: L-0087 | O91: =IF(C91="","",IF(OR(J91="Booked",J91="Recurring Client"),"Booked",IF(J91="Lost/Declined","Lost","Open"))) | P91: =IF(C91="","",IF(S91=0,"—",IF(L91="","Set date",IF(L91<AsOf,"Overdue",IF(L91=AsOf,"Due today",IF(L91<=AsOf+SoonDays,"Due soon","Scheduled")))))) | Q91: =IF(C91="","",IF(B91="","",AsOf-B91)) | R91: =IF(C91="","",IF(O91<>"Booked","",IF(COUNTIF('CUSTOMERS'!$B$5:$B$404,C91)>0,"✓ In CUSTOMERS","Add to CUSTOMERS"))) | S91: =IF(C91="","",IF(OR(J91="Booked",J91="Recurring Client",J91="Lost/Declined"),0,1)) | T91: =IF(B91="","",DATE(YEAR(B91),MONTH(B91),1)) | U91: =IF(OR(S91<>1,L91=""),"",COUNTIFS('LEADS'!$S$5:$S$504,1,'LEADS'!$L$5:$L$504,"<"&L91)+COUNTIFS($S$5:S91,1,$L$5:L91,L91))
A92: L-0088 | O92: =IF(C92="","",IF(OR(J92="Booked",J92="Recurring Client"),"Booked",IF(J92="Lost/Declined","Lost","Open"))) | P92: =IF(C92="","",IF(S92=0,"—",IF(L92="","Set date",IF(L92<AsOf,"Overdue",IF(L92=AsOf,"Due today",IF(L92<=AsOf+SoonDays,"Due soon","Scheduled")))))) | Q92: =IF(C92="","",IF(B92="","",AsOf-B92)) | R92: =IF(C92="","",IF(O92<>"Booked","",IF(COUNTIF('CUSTOMERS'!$B$5:$B$404,C92)>0,"✓ In CUSTOMERS","Add to CUSTOMERS"))) | S92: =IF(C92="","",IF(OR(J92="Booked",J92="Recurring Client",J92="Lost/Declined"),0,1)) | T92: =IF(B92="","",DATE(YEAR(B92),MONTH(B92),1)) | U92: =IF(OR(S92<>1,L92=""),"",COUNTIFS('LEADS'!$S$5:$S$504,1,'LEADS'!$L$5:$L$504,"<"&L92)+COUNTIFS($S$5:S92,1,$L$5:L92,L92))
... A504: L-0500 | O504: =IF(C504="","",IF(OR(J504="Booked",J504="Recurring Client"),"Booked",IF(J504="Lost/Declined","Lost","Open"))) | P504: =IF(C504="","",IF(S504=0,"—",IF(L504="","Set date",IF(L504<AsOf,"Overdue",IF(L504=AsOf,"Due today",IF(L504<=AsOf+SoonDays,"Due soon","Scheduled")))))) | Q504: =IF(C504="","",IF(B504="","",AsOf-B504)) | R504: =IF(C504="","",IF(O504<>"Booked","",IF(COUNTIF('CUSTOMERS'!$B$5:$B$404,C504)>0,"✓ In CUSTOMERS","Add to CUSTOMERS"))) | S504: =IF(C504="","",IF(OR(J504="Booked",J504="Recurring Client",J504="Lost/Declined"),0,1)) | T504: =IF(B504="","",DATE(YEAR(B504),MONTH(B504),1)) | U504: =IF(OR(S504<>1,L504=""),"",COUNTIFS('LEADS'!$S$5:$S$504,1,'LEADS'!$L$5:$L$504,"<"&L504)+COUNTIFS($S$5:S504,1,$L$5:L504,L504))

Sheet CUSTOMERS
A1: CUSTOMERS
A2: Your customer list. History, lifetime revenue, balance due and the suggested next action fill in automatically from JOBS, RECURRING, REVIEWS and REFERRALS.
A3: ← Start Here | B3: Dashboard →
A4: Customer ID | B4: Customer Name (unique) | C4: Phone | D4: Email | E4: Customer Type | F4: Lead Source | G4: Preferred Contact | H4: Status | I4: Date Added | J4: Notes | K4: First Job ⚙ | L4: Last Job ⚙ | M4: Completed Jobs ⚙ | N4: Lifetime Revenue ⚙ | O4: Balance Due ⚙ | P4: Recurring Plan? ⚙ | Q4: Days Since Last Job ⚙ | R4: Suggested Next Action ⚙ | S4: Referrals Given ⚙
A5: C-001 | B5: Lane Ivers | C5: 555-0104 | D5: lane.ivers@example.com | E5: Residential | F5: Website Form | G5: Call | H5: Active | I5: 46042 | K5: =IF(B5="","",IF(_xlfn.MINIFS('JOBS'!$B$5:$B$1504,'JOBS'!$D$5:$D$1504,B5,'JOBS'!$O$5:$O$1504,"Completed")=0,"",_xlfn.MINIFS('JOBS'!$B$5:$B$1504,'JOBS'!$D$5:$D$1504,B5,'JOBS'!$O$5:$O$1504,"Completed"))) | L5: =IF(B5="","",IF(_xlfn.MAXIFS('JOBS'!$B$5:$B$1504,'JOBS'!$D$5:$D$1504,B5,'JOBS'!$O$5:$O$1504,"Completed")=0,"",_xlfn.MAXIFS('JOBS'!$B$5:$B$1504,'JOBS'!$D$5:$D$1504,B5,'JOBS'!$O$5:$O$1504,"Completed"))) | M5: =IF(B5="","",COUNTIFS('JOBS'!$D$5:$D$1504,B5,'JOBS'!$O$5:$O$1504,"Completed")) | N5: =IF(B5="","",SUMIFS('JOBS'!$L$5:$L$1504,'JOBS'!$D$5:$D$1504,B5,'JOBS'!$O$5:$O$1504,"Completed")) | O5: =IF(B5="","",SUMIFS('JOBS'!$U$5:$U$1504,'JOBS'!$D$5:$D$1504,B5)) | P5: =IF(B5="","",IF(COUNTIFS('RECURRING'!$B$5:$B$154,B5,'RECURRING'!$J$5:$J$154,"Active")>0,"Yes","No")) | Q5: =IF(L5="","",AsOf-L5) | R5: =IF(B5="","",IF(H5="Do not service","—",IF(O5>0.005,"Collect balance",IF(M5=0,"Book first job",IF(AND(P5="No",Q5>=ReactDays),"Reactivate",IF(COUNTIF('REVIEWS'!$A$5:$A$504,B5)=0,"Ask for review",IF(AND(P5="No",M5>=1),"Offer recurring plan","—"))))))) | S5: =IF(B5="","",COUNTIF('REFERRALS'!$B$5:$B$204,B5))
A6: C-002 | B6: Logan Porter | C6: 555-0105 | D6: logan.porter@example.com | E6: Residential | F6: Referral | G6: Text | H6: Active | I6: 46094 | K6: =IF(B6="","",IF(_xlfn.MINIFS('JOBS'!$B$5:$B$1504,'JOBS'!$D$5:$D$1504,B6,'JOBS'!$O$5:$O$1504,"Completed")=0,"",_xlfn.MINIFS('JOBS'!$B$5:$B$1504,'JOBS'!$D$5:$D$1504,B6,'JOBS'!$O$5:$O$1504,"Completed"))) | L6: =IF(B6="","",IF(_xlfn.MAXIFS('JOBS'!$B$5:$B$1504,'JOBS'!$D$5:$D$1504,B6,'JOBS'!$O$5:$O$1504,"Completed")=0,"",_xlfn.MAXIFS('JOBS'!$B$5:$B$1504,'JOBS'!$D$5:$D$1504,B6,'JOBS'!$O$5:$O$1504,"Completed"))) | M6: =IF(B6="","",COUNTIFS('JOBS'!$D$5:$D$1504,B6,'JOBS'!$O$5:$O$1504,"Completed")) | N6: =IF(B6="","",SUMIFS('JOBS'!$L$5:$L$1504,'JOBS'!$D$5:$D$1504,B6,'JOBS'!$O$5:$O$1504,"Completed")) | O6: =IF(B6="","",SUMIFS('JOBS'!$U$5:$U$1504,'JOBS'!$D$5:$D$1504,B6)) | P6: =IF(B6="","",IF(COUNTIFS('RECURRING'!$B$5:$B$154,B6,'RECURRING'!$J$5:$J$154,"Active")>0,"Yes","No")) | Q6: =IF(L6="","",AsOf-L6) | R6: =IF(B6="","",IF(H6="Do not service","—",IF(O6>0.005,"Collect balance",IF(M6=0,"Book first job",IF(AND(P6="No",Q6>=ReactDays),"Reactivate",IF(COUNTIF('REVIEWS'!$A$5:$A$504,B6)=0,"Ask for review",IF(AND(P6="No",M6>=1),"Offer recurring plan","—"))))))) | S6: =IF(B6="","",COUNTIF('REFERRALS'!$B$5:$B$204,B6))
A7: C-003 | B7: Devon Hayes | C7: 555-0106 | D7: devon.hayes@example.com | E7: Residential | F7: Google Business Profile | G7: Text | H7: Active | I7: 46161 | K7: =IF(B7="","",IF(_xlfn.MINIFS('JOBS'!$B$5:$B$1504,'JOBS'!$D$5:$D$1504,B7,'JOBS'!$O$5:$O$1504,"Completed")=0,"",_xlfn.MINIFS('JOBS'!$B$5:$B$1504,'JOBS'!$D$5:$D$1504,B7,'JOBS'!$O$5:$O$1504,"Completed"))) | L7: =IF(B7="","",IF(_xlfn.MAXIFS('JOBS'!$B$5:$B$1504,'JOBS'!$D$5:$D$1504,B7,'JOBS'!$O$5:$O$1504,"Completed")=0,"",_xlfn.MAXIFS('JOBS'!$B$5:$B$1504,'JOBS'!$D$5:$D$1504,B7,'JOBS'!$O$5:$O$1504,"Completed"))) | M7: =IF(B7="","",COUNTIFS('JOBS'!$D$5:$D$1504,B7,'JOBS'!$O$5:$O$1504,"Completed")) | N7: =IF(B7="","",SUMIFS('JOBS'!$L$5:$L$1504,'JOBS'!$D$5:$D$1504,B7,'JOBS'!$O$5:$O$1504,"Completed")) | O7: =IF(B7="","",SUMIFS('JOBS'!$U$5:$U$1504,'JOBS'!$D$5:$D$1504,B7)) | P7: =IF(B7="","",IF(COUNTIFS('RECURRING'!$B$5:$B$154,B7,'RECURRING'!$J$5:$J$154,"Active")>0,"Yes","No")) | Q7: =IF(L7="","",AsOf-L7) | R7: =IF(B7="","",IF(H7="Do not service","—",IF(O7>0.005,"Collect balance",IF(M7=0,"Book first job",IF(AND(P7="No",Q7>=ReactDays),"Reactivate",IF(COUNTIF('REVIEWS'!$A$5:$A$504,B7)=0,"Ask for review",IF(AND(P7="No",M7>=1),"Offer recurring plan","—"))))))) | S7: =IF(B7="","",COUNTIF('REFERRALS'!$B$5:$B$204,B7))
A8: C-004 | B8: Noel Collins | C8: 555-0107 | D8: noel.collins@example.com | E8: Residential | F8: Facebook | G8: Call | H8: Active | I8: 46098 | K8: =IF(B8="","",IF(_xlfn.MINIFS('JOBS'!$B$5:$B$1504,'JOBS'!$D$5:$D$1504,B8,'JOBS'!$O$5:$O$1504,"Completed")=0,"",_xlfn.MINIFS('JOBS'!$B$5:$B$1504,'JOBS'!$D$5:$D$1504,B8,'JOBS'!$O$5:$O$1504,"Completed"))) | L8: =IF(B8="","",IF(_xlfn.MAXIFS('JOBS'!$B$5:$B$1504,'JOBS'!$D$5:$D$1504,B8,'JOBS'!$O$5:$O$1504,"Completed")=0,"",_xlfn.MAXIFS('JOBS'!$B$5:$B$1504,'JOBS'!$D$5:$D$1504,B8,'JOBS'!$O$5:$O$1504,"Completed"))) | M8: =IF(B8="","",COUNTIFS('JOBS'!$D$5:$D$1504,B8,'JOBS'!$O$5:$O$1504,"Completed")) | N8: =IF(B8="","",SUMIFS('JOBS'!$L$5:$L$1504,'JOBS'!$D$5:$D$1504,B8,'JOBS'!$O$5:$O$1504,"Completed")) | O8: =IF(B8="","",SUMIFS('JOBS'!$U$5:$U$1504,'JOBS'!$D$5:$D$1504,B8)) | P8: =IF(B8="","",IF(COUNTIFS('RECURRING'!$B$5:$B$154,B8,'RECURRING'!$J$5:$J$154,"Active")>0,"Yes","No")) | Q8: =IF(L8="","",AsOf-L8) | R8: =IF(B8="","",IF(H8="Do not service","—",IF(O8>0.005,"Collect balance",IF(M8=0,"Book first job",IF(AND(P8="No",Q8>=ReactDays),"Reactivate",IF(COUNTIF('REVIEWS'!$A$5:$A$504,B8)=0,"Ask for review",IF(AND(P8="No",M8>=1),"Offer recurring plan","—"))))))) | S8: =IF(B8="","",COUNTIF('REFERRALS'!$B$5:$B$204,B8))
A9: C-005 | B9: Rowan Foxworth | C9: 555-0108 | D9: rowan.foxworth@example.com | E9: Residential | F9: Google Search | G9: Text | H9: Active | I9: 46089 | K9: =IF(B9="","",IF(_xlfn.MINIFS('JOBS'!$B$5:$B$1504,'JOBS'!$D$5:$D$1504,B9,'JOBS'!$O$5:$O$1504,"Completed")=0,"",_xlfn.MINIFS('JOBS'!$B$5:$B$1504,'JOBS'!$D$5:$D$1504,B9,'JOBS'!$O$5:$O$1504,"Completed"))) | L9: =IF(B9="","",IF(_xlfn.MAXIFS('JOBS'!$B$5:$B$1504,'JOBS'!$D$5:$D$1504,B9,'JOBS'!$O$5:$O$1504,"Completed")=0,"",_xlfn.MAXIFS('JOBS'!$B$5:$B$1504,'JOBS'!$D$5:$D$1504,B9,'JOBS'!$O$5:$O$1504,"Completed"))) | M9: =IF(B9="","",COUNTIFS('JOBS'!$D$5:$D$1504,B9,'JOBS'!$O$5:$O$1504,"Completed")) | N9: =IF(B9="","",SUMIFS('JOBS'!$L$5:$L$1504,'JOBS'!$D$5:$D$1504,B9,'JOBS'!$O$5:$O$1504,"Completed")) | O9: =IF(B9="","",SUMIFS('JOBS'!$U$5:$U$1504,'JOBS'!$D$5:$D$1504,B9)) | P9: =IF(B9="","",IF(COUNTIFS('RECURRING'!$B$5:$B$154,B9,'RECURRING'!$J$5:$J$154,"Active")>0,"Yes","No")) | Q9: =IF(L9="","",AsOf-L9) | R9: =IF(B9="","",IF(H9="Do not service","—",IF(O9>0.005,"Collect balance",IF(M9=0,"Book first job",IF(AND(P9="No",Q9>=ReactDays),"Reactivate",IF(COUNTIF('REVIEWS'!$A$5:$A$504,B9)=0,"Ask for review",IF(AND(P9="No",M9>=1),"Offer recurring plan","—"))))))) | S9: =IF(B9="","",COUNTIF('REFERRALS'!$B$5:$B$204,B9))
A10: C-006 | B10: Dana Collins | C10: 555-0109 | D10: dana.collins@example.com | E10: Residential | F10: Google Business Profile | G10: Text | H10: Active | I10: 46024 | K10: =IF(B10="","",IF(_xlfn.MINIFS('JOBS'!$B$5:$B$1504,'JOBS'!$D$5:$D$1504,B10,'JOBS'!$O$5:$O$1504,"Completed")=0,"",_xlfn.MINIFS('JOBS'!$B$5:$B$1504,'JOBS'!$D$5:$D$1504,B10,'JOBS'!$O$5:$O$1504,"Completed"))) | L10: =IF(B10="","",IF(_xlfn.MAXIFS('JOBS'!$B$5:$B$1504,'JOBS'!$D$5:$D$1504,B10,'JOBS'!$O$5:$O$1504,"Completed")=0,"",_xlfn.MAXIFS('JOBS'!$B$5:$B$1504,'JOBS'!$D$5:$D$1504,B10,'JOBS'!$O$5:$O$1504,"Completed"))) | M10: =IF(B10="","",COUNTIFS('JOBS'!$D$5:$D$1504,B10,'JOBS'!$O$5:$O$1504,"Completed")) | N10: =IF(B10="","",SUMIFS('JOBS'!$L$5:$L$1504,'JOBS'!$D$5:$D$1504,B10,'JOBS'!$O$5:$O$1504,"Completed")) | O10: =IF(B10="","",SUMIFS('JOBS'!$U$5:$U$1504,'JOBS'!$D$5:$D$1504,B10)) | P10: =IF(B10="","",IF(COUNTIFS('RECURRING'!$B$5:$B$154,B10,'RECURRING'!$J$5:$J$154,"Active")>0,"Yes","No")) | Q10: =IF(L10="","",AsOf-L10) | R10: =IF(B10="","",IF(H10="Do not service","—",IF(O10>0.005,"Collect balance",IF(M10=0,"Book first job",IF(AND(P10="No",Q10>=ReactDays),"Reactivate",IF(COUNTIF('REVIEWS'!$A$5:$A$504,B10)=0,"Ask for review",IF(AND(P10="No",M10>=1),"Offer recurring plan","—"))))))) | S10: =IF(B10="","",COUNTIF('REFERRALS'!$B$5:$B$204,B10))
A11: C-007 | B11: Finley Quigley | C11: 555-0110 | D11: finley.quigley@example.com | E11: Residential | F11: Google Search | G11: Call | H11: Active | I11: 46105 | K11: =IF(B11="","",IF(_xlfn.MINIFS('JOBS'!$B$5:$B$1504,'JOBS'!$D$5:$D$1504,B11,'JOBS'!$O$5:$O$1504,"Completed")=0,"",_xlfn.MINIFS('JOBS'!$B$5:$B$1504,'JOBS'!$D$5:$D$1504,B11,'JOBS'!$O$5:$O$1504,"Completed"))) | L11: =IF(B11="","",IF(_xlfn.MAXIFS('JOBS'!$B$5:$B$1504,'JOBS'!$D$5:$D$1504,B11,'JOBS'!$O$5:$O$1504,"Completed")=0,"",_xlfn.MAXIFS('JOBS'!$B$5:$B$1504,'JOBS'!$D$5:$D$1504,B11,'JOBS'!$O$5:$O$1504,"Completed"))) | M11: =IF(B11="","",COUNTIFS('JOBS'!$D$5:$D$1504,B11,'JOBS'!$O$5:$O$1504,"Completed")) | N11: =IF(B11="","",SUMIFS('JOBS'!$L$5:$L$1504,'JOBS'!$D$5:$D$1504,B11,'JOBS'!$O$5:$O$1504,"Completed")) | O11: =IF(B11="","",SUMIFS('JOBS'!$U$5:$U$1504,'JOBS'!$D$5:$D$1504,B11)) | P11: =IF(B11="","",IF(COUNTIFS('RECURRING'!$B$5:$B$154,B11,'RECURRING'!$J$5:$J$154,"Active")>0,"Yes","No")) | Q11: =IF(L11="","",AsOf-L11) | R11: =IF(B11="","",IF(H11="Do not service","—",IF(O11>0.005,"Collect balance",IF(M11=0,"Book first job",IF(AND(P11="No",Q11>=ReactDays),"Reactivate",IF(COUNTIF('REVIEWS'!$A$5:$A$504,B11)=0,"Ask for review",IF(AND(P11="No",M11>=1),"Offer recurring plan","—"))))))) | S11: =IF(B11="","",COUNTIF('REFERRALS'!$B$5:$B$204,B11))
A12: C-008 | B12: Dana Ivers | C12: 555-0111 | D12: dana.ivers@example.com | E12: Residential | F12: Google Business Profile | G12: Text | H12: Active | I12: 46147 | K12: =IF(B12="","",IF(_xlfn.MINIFS('JOBS'!$B$5:$B$1504,'JOBS'!$D$5:$D$1504,B12,'JOBS'!$O$5:$O$1504,"Completed")=0,"",_xlfn.MINIFS('JOBS'!$B$5:$B$1504,'JOBS'!$D$5:$D$1504,B12,'JOBS'!$O$5:$O$1504,"Completed"))) | L12: =IF(B12="","",IF(_xlfn.MAXIFS('JOBS'!$B$5:$B$1504,'JOBS'!$D$5:$D$1504,B12,'JOBS'!$O$5:$O$1504,"Completed")=0,"",_xlfn.MAXIFS('JOBS'!$B$5:$B$1504,'JOBS'!$D$5:$D$1504,B12,'JOBS'!$O$5:$O$1504,"Completed"))) | M12: =IF(B12="","",COUNTIFS('JOBS'!$D$5:$D$1504,B12,'JOBS'!$O$5:$O$1504,"Completed")) | N12: =IF(B12="","",SUMIFS('JOBS'!$L$5:$L$1504,'JOBS'!$D$5:$D$1504,B12,'JOBS'!$O$5:$O$1504,"Completed")) | O12: =IF(B12="","",SUMIFS('JOBS'!$U$5:$U$1504,'JOBS'!$D$5:$D$1504,B12)) | P12: =IF(B12="","",IF(COUNTIFS('RECURRING'!$B$5:$B$154,B12,'RECURRING'!$J$5:$J$154,"Active")>0,"Yes","No")) | Q12: =IF(L12="","",AsOf-L12) | R12: =IF(B12="","",IF(H12="Do not service","—",IF(O12>0.005,"Collect balance",IF(M12=0,"Book first job",IF(AND(P12="No",Q12>=ReactDays),"Reactivate",IF(COUNTIF('REVIEWS'!$A$5:$A$504,B12)=0,"Ask for review",IF(AND(P12="No",M12>=1),"Offer recurring plan","—"))))))) | S12: =IF(B12="","",COUNTIF('REFERRALS'!$B$5:$B$204,B12))
A13: C-009 | B13: Taylor Quigley | C13: 555-0112 | D13: taylor.quigley@example.com | E13: Residential | F13: Flyer / Door Hanger | G13: Text | H13: Active | I13: 46036 | K13: =IF(B13="","",IF(_xlfn.MINIFS('JOBS'!$B$5:$B$1504,'JOBS'!$D$5:$D$1504,B13,'JOBS'!$O$5:$O$1504,"Completed")=0,"",_xlfn.MINIFS('JOBS'!$B$5:$B$1504,'JOBS'!$D$5:$D$1504,B13,'JOBS'!$O$5:$O$1504,"Completed"))) | L13: =IF(B13="","",IF(_xlfn.MAXIFS('JOBS'!$B$5:$B$1504,'JOBS'!$D$5:$D$1504,B13,'JOBS'!$O$5:$O$1504,"Completed")=0,"",_xlfn.MAXIFS('JOBS'!$B$5:$B$1504,'JOBS'!$D$5:$D$1504,B13,'JOBS'!$O$5:$O$1504,"Completed"))) | M13: =IF(B13="","",COUNTIFS('JOBS'!$D$5:$D$1504,B13,'JOBS'!$O$5:$O$1504,"Completed")) | N13: =IF(B13="","",SUMIFS('JOBS'!$L$5:$L$1504,'JOBS'!$D$5:$D$1504,B13,'JOBS'!$O$5:$O$1504,"Completed")) | O13: =IF(B13="","",SUMIFS('JOBS'!$U$5:$U$1504,'JOBS'!$D$5:$D$1504,B13)) | P13: =IF(B13="","",IF(COUNTIFS('RECURRING'!$B$5:$B$154,B13,'RECURRING'!$J$5:$J$154,"Active")>0,"Yes","No")) | Q13: =IF(L13="","",AsOf-L13) | R13: =IF(B13="","",IF(H13="Do not service","—",IF(O13>0.005,"Collect balance",IF(M13=0,"Book first job",IF(AND(P13="No",Q13>=ReactDays),"Reactivate",IF(COUNTIF('REVIEWS'!$A$5:$A$504,B13)=0,"Ask for review",IF(AND(P13="No",M13>=1),"Offer recurring plan","—"))))))) | S13: =IF(B13="","",COUNTIF('REFERRALS'!$B$5:$B$204,B13))
A14: C-010 | B14: Lane Northcott | C14: 555-0113 | D14: lane.northcott@example.com | E14: Residential | F14: Google Business Profile | G14: Email | H14: Active | I14: 46030 | K14: =IF(B14="","",IF(_xlfn.MINIFS('JOBS'!$B$5:$B$1504,'JOBS'!$D$5:$D$1504,B14,'JOBS'!$O$5:$O$1504,"Completed")=0,"",_xlfn.MINIFS('JOBS'!$B$5:$B$1504,'JOBS'!$D$5:$D$1504,B14,'JOBS'!$O$5:$O$1504,"Completed"))) | L14: =IF(B14="","",IF(_xlfn.MAXIFS('JOBS'!$B$5:$B$1504,'JOBS'!$D$5:$D$1504,B14,'JOBS'!$O$5:$O$1504,"Completed")=0,"",_xlfn.MAXIFS('JOBS'!$B$5:$B$1504,'JOBS'!$D$5:$D$1504,B14,'JOBS'!$O$5:$O$1504,"Completed"))) | M14: =IF(B14="","",COUNTIFS('JOBS'!$D$5:$D$1504,B14,'JOBS'!$O$5:$O$1504,"Completed")) | N14: =IF(B14="","",SUMIFS('JOBS'!$L$5:$L$1504,'JOBS'!$D$5:$D$1504,B14,'JOBS'!$O$5:$O$1504,"Completed")) | O14: =IF(B14="","",SUMIFS('JOBS'!$U$5:$U$1504,'JOBS'!$D$5:$D$1504,B14)) | P14: =IF(B14="","",IF(COUNTIFS('RECURRING'!$B$5:$B$154,B14,'RECURRING'!$J$5:$J$154,"Active")>0,"Yes","No")) | Q14: =IF(L14="","",AsOf-L14) | R14: =IF(B14="","",IF(H14="Do not service","—",IF(O14>0.005,"Collect balance",IF(M14=0,"Book first job",IF(AND(P14="No",Q14>=ReactDays),"Reactivate",IF(COUNTIF('REVIEWS'!$A$5:$A$504,B14)=0,"Ask for review",IF(AND(P14="No",M14>=1),"Offer recurring plan","—"))))))) | S14: =IF(B14="","",COUNTIF('REFERRALS'!$B$5:$B$204,B14))
A15: C-011 | B15: Peyton Underhill | C15: 555-0114 | D15: peyton.underhill@example.com | E15: Residential | F15: Referral | G15: Call | H15: Active | I15: 46079 | K15: =IF(B15="","",IF(_xlfn.MINIFS('JOBS'!$B$5:$B$1504,'JOBS'!$D$5:$D$1504,B15,'JOBS'!$O$5:$O$1504,"Completed")=0,"",_xlfn.MINIFS('JOBS'!$B$5:$B$1504,'JOBS'!$D$5:$D$1504,B15,'JOBS'!$O$5:$O$1504,"Completed"))) | L15: =IF(B15="","",IF(_xlfn.MAXIFS('JOBS'!$B$5:$B$1504,'JOBS'!$D$5:$D$1504,B15,'JOBS'!$O$5:$O$1504,"Completed")=0,"",_xlfn.MAXIFS('JOBS'!$B$5:$B$1504,'JOBS'!$D$5:$D$1504,B15,'JOBS'!$O$5:$O$1504,"Completed"))) | M15: =IF(B15="","",COUNTIFS('JOBS'!$D$5:$D$1504,B15,'JOBS'!$O$5:$O$1504,"Completed")) | N15: =IF(B15="","",SUMIFS('JOBS'!$L$5:$L$1504,'JOBS'!$D$5:$D$1504,B15,'JOBS'!$O$5:$O$1504,"Completed")) | O15: =IF(B15="","",SUMIFS('JOBS'!$U$5:$U$1504,'JOBS'!$D$5:$D$1504,B15)) | P15: =IF(B15="","",IF(COUNTIFS('RECURRING'!$B$5:$B$154,B15,'RECURRING'!$J$5:$J$154,"Active")>0,"Yes","No")) | Q15: =IF(L15="","",AsOf-L15) | R15: =IF(B15="","",IF(H15="Do not service","—",IF(O15>0.005,"Collect balance",IF(M15=0,"Book first job",IF(AND(P15="No",Q15>=ReactDays),"Reactivate",IF(COUNTIF('REVIEWS'!$A$5:$A$504,B15)=0,"Ask for review",IF(AND(P15="No",M15>=1),"Offer recurring plan","—"))))))) | S15: =IF(B15="","",COUNTIF('REFERRALS'!$B$5:$B$204,B15))
A16: C-012 | B16: Rowan Merriweather | C16: 555-0115 | D16: rowan.merriweather@example.com | E16: Residential | F16: Nextdoor | G16: Text | H16: Active | I16: 46091 | K16: =IF(B16="","",IF(_xlfn.MINIFS('JOBS'!$B$5:$B$1504,'JOBS'!$D$5:$D$1504,B16,'JOBS'!$O$5:$O$1504,"Completed")=0,"",_xlfn.MINIFS('JOBS'!$B$5:$B$1504,'JOBS'!$D$5:$D$1504,B16,'JOBS'!$O$5:$O$1504,"Completed"))) | L16: =IF(B16="","",IF(_xlfn.MAXIFS('JOBS'!$B$5:$B$1504,'JOBS'!$D$5:$D$1504,B16,'JOBS'!$O$5:$O$1504,"Completed")=0,"",_xlfn.MAXIFS('JOBS'!$B$5:$B$1504,'JOBS'!$D$5:$D$1504,B16,'JOBS'!$O$5:$O$1504,"Completed"))) | M16: =IF(B16="","",COUNTIFS('JOBS'!$D$5:$D$1504,B16,'JOBS'!$O$5:$O$1504,"Completed")) | N16: =IF(B16="","",SUMIFS('JOBS'!$L$5:$L$1504,'JOBS'!$D$5:$D$1504,B16,'JOBS'!$O$5:$O$1504,"Completed")) | O16: =IF(B16="","",SUMIFS('JOBS'!$U$5:$U$1504,'JOBS'!$D$5:$D$1504,B16)) | P16: =IF(B16="","",IF(COUNTIFS('RECURRING'!$B$5:$B$154,B16,'RECURRING'!$J$5:$J$154,"Active")>0,"Yes","No")) | Q16: =IF(L16="","",AsOf-L16) | R16: =IF(B16="","",IF(H16="Do not service","—",IF(O16>0.005,"Collect balance",IF(M16=0,"Book first job",IF(AND(P16="No",Q16>=ReactDays),"Reactivate",IF(COUNTIF('REVIEWS'!$A$5:$A$504,B16)=0,"Ask for review",IF(AND(P16="No",M16>=1),"Offer recurring plan","—"))))))) | S16: =IF(B16="","",COUNTIF('REFERRALS'!$B$5:$B$204,B16))
... A24: C-020 | B24: Wren Porter | C24: 555-0123 | D24: wren.porter@example.com | E24: Residential | F24: Referral | G24: Text | H24: Active | I24: 46050 | K24: =IF(B24="","",IF(_xlfn.MINIFS('JOBS'!$B$5:$B$1504,'JOBS'!$D$5:$D$1504,B24,'JOBS'!$O$5:$O$1504,"Completed")=0,"",_xlfn.MINIFS('JOBS'!$B$5:$B$1504,'JOBS'!$D$5:$D$1504,B24,'JOBS'!$O$5:$O$1504,"Completed"))) | L24: =IF(B24="","",IF(_xlfn.MAXIFS('JOBS'!$B$5:$B$1504,'JOBS'!$D$5:$D$1504,B24,'JOBS'!$O$5:$O$1504,"Completed")=0,"",_xlfn.MAXIFS('JOBS'!$B$5:$B$1504,'JOBS'!$D$5:$D$1504,B24,'JOBS'!$O$5:$O$1504,"Completed"))) | M24: =IF(B24="","",COUNTIFS('JOBS'!$D$5:$D$1504,B24,'JOBS'!$O$5:$O$1504,"Completed")) | N24: =IF(B24="","",SUMIFS('JOBS'!$L$5:$L$1504,'JOBS'!$D$5:$D$1504,B24,'JOBS'!$O$5:$O$1504,"Completed")) | O24: =IF(B24="","",SUMIFS('JOBS'!$U$5:$U$1504,'JOBS'!$D$5:$D$1504,B24)) | P24: =IF(B24="","",IF(COUNTIFS('RECURRING'!$B$5:$B$154,B24,'RECURRING'!$J$5:$J$154,"Active")>0,"Yes","No")) | Q24: =IF(L24="","",AsOf-L24) | R24: =IF(B24="","",IF(H24="Do not service","—",IF(O24>0.005,"Collect balance",IF(M24=0,"Book first job",IF(AND(P24="No",Q24>=ReactDays),"Reactivate",IF(COUNTIF('REVIEWS'!$A$5:$A$504,B24)=0,"Ask for review",IF(AND(P24="No",M24>=1),"Offer recurring plan","—"))))))) | S24: =IF(B24="","",COUNTIF('REFERRALS'!$B$5:$B$204,B24))
A25: C-021 | B25: Wren Delgado | C25: 555-0124 | D25: wren.delgado@example.com | E25: Residential | F25: Nextdoor | G25: Text | H25: Active | I25: 46181 | J25: Moved? Try a reactivation message | K25: =IF(B25="","",IF(_xlfn.MINIFS('JOBS'!$B$5:$B$1504,'JOBS'!$D$5:$D$1504,B25,'JOBS'!$O$5:$O$1504,"Completed")=0,"",_xlfn.MINIFS('JOBS'!$B$5:$B$1504,'JOBS'!$D$5:$D$1504,B25,'JOBS'!$O$5:$O$1504,"Completed"))) | L25: =IF(B25="","",IF(_xlfn.MAXIFS('JOBS'!$B$5:$B$1504,'JOBS'!$D$5:$D$1504,B25,'JOBS'!$O$5:$O$1504,"Completed")=0,"",_xlfn.MAXIFS('JOBS'!$B$5:$B$1504,'JOBS'!$D$5:$D$1504,B25,'JOBS'!$O$5:$O$1504,"Completed"))) | M25: =IF(B25="","",COUNTIFS('JOBS'!$D$5:$D$1504,B25,'JOBS'!$O$5:$O$1504,"Completed")) | N25: =IF(B25="","",SUMIFS('JOBS'!$L$5:$L$1504,'JOBS'!$D$5:$D$1504,B25,'JOBS'!$O$5:$O$1504,"Completed")) | O25: =IF(B25="","",SUMIFS('JOBS'!$U$5:$U$1504,'JOBS'!$D$5:$D$1504,B25)) | P25: =IF(B25="","",IF(COUNTIFS('RECURRING'!$B$5:$B$154,B25,'RECURRING'!$J$5:$J$154,"Active")>0,"Yes","No")) | Q25: =IF(L25="","",AsOf-L25) | R25: =IF(B25="","",IF(H25="Do not service","—",IF(O25>0.005,"Collect balance",IF(M25=0,"Book first job",IF(AND(P25="No",Q25>=ReactDays),"Reactivate",IF(COUNTIF('REVIEWS'!$A$5:$A$504,B25)=0,"Ask for review",IF(AND(P25="No",M25>=1),"Offer recurring plan","—"))))))) | S25: =IF(B25="","",COUNTIF('REFERRALS'!$B$5:$B$204,B25))
A26: C-022 | B26: Quinn Ashworth | C26: 555-0125 | D26: quinn.ashworth@example.com | E26: Residential | F26: Website Form | G26: Text | H26: Active | I26: 46221 | K26: =IF(B26="","",IF(_xlfn.MINIFS('JOBS'!$B$5:$B$1504,'JOBS'!$D$5:$D$1504,B26,'JOBS'!$O$5:$O$1504,"Completed")=0,"",_xlfn.MINIFS('JOBS'!$B$5:$B$1504,'JOBS'!$D$5:$D$1504,B26,'JOBS'!$O$5:$O$1504,"Completed"))) | L26: =IF(B26="","",IF(_xlfn.MAXIFS('JOBS'!$B$5:$B$1504,'JOBS'!$D$5:$D$1504,B26,'JOBS'!$O$5:$O$1504,"Completed")=0,"",_xlfn.MAXIFS('JOBS'!$B$5:$B$1504,'JOBS'!$D$5:$D$1504,B26,'JOBS'!$O$5:$O$1504,"Completed"))) | M26: =IF(B26="","",COUNTIFS('JOBS'!$D$5:$D$1504,B26,'JOBS'!$O$5:$O$1504,"Completed")) | N26: =IF(B26="","",SUMIFS('JOBS'!$L$5:$L$1504,'JOBS'!$D$5:$D$1504,B26,'JOBS'!$O$5:$O$1504,"Completed")) | O26: =IF(B26="","",SUMIFS('JOBS'!$U$5:$U$1504,'JOBS'!$D$5:$D$1504,B26)) | P26: =IF(B26="","",IF(COUNTIFS('RECURRING'!$B$5:$B$154,B26,'RECURRING'!$J$5:$J$154,"Active")>0,"Yes","No")) | Q26: =IF(L26="","",AsOf-L26) | R26: =IF(B26="","",IF(H26="Do not service","—",IF(O26>0.005,"Collect balance",IF(M26=0,"Book first job",IF(AND(P26="No",Q26>=ReactDays),"Reactivate",IF(COUNTIF('REVIEWS'!$A$5:$A$504,B26)=0,"Ask for review",IF(AND(P26="No",M26>=1),"Offer recurring plan","—"))))))) | S26: =IF(B26="","",COUNTIF('REFERRALS'!$B$5:$B$204,B26))
A27: C-023 | B27: Brightside Dental Studio (sample) | C27: 555-0126 | D27: brightside.dental.studio.(sample)@example.com | E27: Commercial | F27: Referral | G27: Email | H27: Active | I27: 46049 | K27: =IF(B27="","",IF(_xlfn.MINIFS('JOBS'!$B$5:$B$1504,'JOBS'!$D$5:$D$1504,B27,'JOBS'!$O$5:$O$1504,"Completed")=0,"",_xlfn.MINIFS('JOBS'!$B$5:$B$1504,'JOBS'!$D$5:$D$1504,B27,'JOBS'!$O$5:$O$1504,"Completed"))) | L27: =IF(B27="","",IF(_xlfn.MAXIFS('JOBS'!$B$5:$B$1504,'JOBS'!$D$5:$D$1504,B27,'JOBS'!$O$5:$O$1504,"Completed")=0,"",_xlfn.MAXIFS('JOBS'!$B$5:$B$1504,'JOBS'!$D$5:$D$1504,B27,'JOBS'!$O$5:$O$1504,"Completed"))) | M27: =IF(B27="","",COUNTIFS('JOBS'!$D$5:$D$1504,B27,'JOBS'!$O$5:$O$1504,"Completed")) | N27: =IF(B27="","",SUMIFS('JOBS'!$L$5:$L$1504,'JOBS'!$D$5:$D$1504,B27,'JOBS'!$O$5:$O$1504,"Completed")) | O27: =IF(B27="","",SUMIFS('JOBS'!$U$5:$U$1504,'JOBS'!$D$5:$D$1504,B27)) | P27: =IF(B27="","",IF(COUNTIFS('RECURRING'!$B$5:$B$154,B27,'RECURRING'!$J$5:$J$154,"Active")>0,"Yes","No")) | Q27: =IF(L27="","",AsOf-L27) | R27: =IF(B27="","",IF(H27="Do not service","—",IF(O27>0.005,"Collect balance",IF(M27=0,"Book first job",IF(AND(P27="No",Q27>=ReactDays),"Reactivate",IF(COUNTIF('REVIEWS'!$A$5:$A$504,B27)=0,"Ask for review",IF(AND(P27="No",M27>=1),"Offer recurring plan","—"))))))) | S27: =IF(B27="","",COUNTIF('REFERRALS'!$B$5:$B$204,B27))
A28: C-024 | B28: Oakview Office Suites (sample) | C28: 555-0127 | D28: oakview.office.suites.(sample)@example.com | E28: Commercial | F28: Referral | G28: Email | H28: Active | I28: 46111 | K28: =IF(B28="","",IF(_xlfn.MINIFS('JOBS'!$B$5:$B$1504,'JOBS'!$D$5:$D$1504,B28,'JOBS'!$O$5:$O$1504,"Completed")=0,"",_xlfn.MINIFS('JOBS'!$B$5:$B$1504,'JOBS'!$D$5:$D$1504,B28,'JOBS'!$O$5:$O$1504,"Completed"))) | L28: =IF(B28="","",IF(_xlfn.MAXIFS('JOBS'!$B$5:$B$1504,'JOBS'!$D$5:$D$1504,B28,'JOBS'!$O$5:$O$1504,"Completed")=0,"",_xlfn.MAXIFS('JOBS'!$B$5:$B$1504,'JOBS'!$D$5:$D$1504,B28,'JOBS'!$O$5:$O$1504,"Completed"))) | M28: =IF(B28="","",COUNTIFS('JOBS'!$D$5:$D$1504,B28,'JOBS'!$O$5:$O$1504,"Completed")) | N28: =IF(B28="","",SUMIFS('JOBS'!$L$5:$L$1504,'JOBS'!$D$5:$D$1504,B28,'JOBS'!$O$5:$O$1504,"Completed")) | O28: =IF(B28="","",SUMIFS('JOBS'!$U$5:$U$1504,'JOBS'!$D$5:$D$1504,B28)) | P28: =IF(B28="","",IF(COUNTIFS('RECURRING'!$B$5:$B$154,B28,'RECURRING'!$J$5:$J$154,"Active")>0,"Yes","No")) | Q28: =IF(L28="","",AsOf-L28) | R28: =IF(B28="","",IF(H28="Do not service","—",IF(O28>0.005,"Collect balance",IF(M28=0,"Book first job",IF(AND(P28="No",Q28>=ReactDays),"Reactivate",IF(COUNTIF('REVIEWS'!$A$5:$A$504,B28)=0,"Ask for review",IF(AND(P28="No",M28>=1),"Offer recurring plan","—"))))))) | S28: =IF(B28="","",COUNTIF('REFERRALS'!$B$5:$B$204,B28))
A29: C-025 | B29: Harbor Yoga Loft (sample) | C29: 555-0128 | D29: harbor.yoga.loft.(sample)@example.com | E29: Commercial | F29: Nextdoor | G29: Email | H29: Active | I29: 46086 | K29: =IF(B29="","",IF(_xlfn.MINIFS('JOBS'!$B$5:$B$1504,'JOBS'!$D$5:$D$1504,B29,'JOBS'!$O$5:$O$1504,"Completed")=0,"",_xlfn.MINIFS('JOBS'!$B$5:$B$1504,'JOBS'!$D$5:$D$1504,B29,'JOBS'!$O$5:$O$1504,"Completed"))) | L29: =IF(B29="","",IF(_xlfn.MAXIFS('JOBS'!$B$5:$B$1504,'JOBS'!$D$5:$D$1504,B29,'JOBS'!$O$5:$O$1504,"Completed")=0,"",_xlfn.MAXIFS('JOBS'!$B$5:$B$1504,'JOBS'!$D$5:$D$1504,B29,'JOBS'!$O$5:$O$1504,"Completed"))) | M29: =IF(B29="","",COUNTIFS('JOBS'!$D$5:$D$1504,B29,'JOBS'!$O$5:$O$1504,"Completed")) | N29: =IF(B29="","",SUMIFS('JOBS'!$L$5:$L$1504,'JOBS'!$D$5:$D$1504,B29,'JOBS'!$O$5:$O$1504,"Completed")) | O29: =IF(B29="","",SUMIFS('JOBS'!$U$5:$U$1504,'JOBS'!$D$5:$D$1504,B29)) | P29: =IF(B29="","",IF(COUNTIFS('RECURRING'!$B$5:$B$154,B29,'RECURRING'!$J$5:$J$154,"Active")>0,"Yes","No")) | Q29: =IF(L29="","",AsOf-L29) | R29: =IF(B29="","",IF(H29="Do not service","—",IF(O29>0.005,"Collect balance",IF(M29=0,"Book first job",IF(AND(P29="No",Q29>=ReactDays),"Reactivate",IF(COUNTIF('REVIEWS'!$A$5:$A$504,B29)=0,"Ask for review",IF(AND(P29="No",M29>=1),"Offer recurring plan","—"))))))) | S29: =IF(B29="","",COUNTIF('REFERRALS'!$B$5:$B$204,B29))
A30: C-026 | B30: Dana Oakes | C30: 555-0129 | D30: dana.oakes@example.com | E30: Short-Term Rental Host | F30: Facebook | G30: Email | H30: Active | I30: 46035 | K30: =IF(B30="","",IF(_xlfn.MINIFS('JOBS'!$B$5:$B$1504,'JOBS'!$D$5:$D$1504,B30,'JOBS'!$O$5:$O$1504,"Completed")=0,"",_xlfn.MINIFS('JOBS'!$B$5:$B$1504,'JOBS'!$D$5:$D$1504,B30,'JOBS'!$O$5:$O$1504,"Completed"))) | L30: =IF(B30="","",IF(_xlfn.MAXIFS('JOBS'!$B$5:$B$1504,'JOBS'!$D$5:$D$1504,B30,'JOBS'!$O$5:$O$1504,"Completed")=0,"",_xlfn.MAXIFS('JOBS'!$B$5:$B$1504,'JOBS'!$D$5:$D$1504,B30,'JOBS'!$O$5:$O$1504,"Completed"))) | M30: =IF(B30="","",COUNTIFS('JOBS'!$D$5:$D$1504,B30,'JOBS'!$O$5:$O$1504,"Completed")) | N30: =IF(B30="","",SUMIFS('JOBS'!$L$5:$L$1504,'JOBS'!$D$5:$D$1504,B30,'JOBS'!$O$5:$O$1504,"Completed")) | O30: =IF(B30="","",SUMIFS('JOBS'!$U$5:$U$1504,'JOBS'!$D$5:$D$1504,B30)) | P30: =IF(B30="","",IF(COUNTIFS('RECURRING'!$B$5:$B$154,B30,'RECURRING'!$J$5:$J$154,"Active")>0,"Yes","No")) | Q30: =IF(L30="","",AsOf-L30) | R30: =IF(B30="","",IF(H30="Do not service","—",IF(O30>0.005,"Collect balance",IF(M30=0,"Book first job",IF(AND(P30="No",Q30>=ReactDays),"Reactivate",IF(COUNTIF('REVIEWS'!$A$5:$A$504,B30)=0,"Ask for review",IF(AND(P30="No",M30>=1),"Offer recurring plan","—"))))))) | S30: =IF(B30="","",COUNTIF('REFERRALS'!$B$5:$B$204,B30))
A31: C-027 | B31: Blake Oakes | C31: 555-0130 | D31: blake.oakes@example.com | E31: Short-Term Rental Host | F31: Google Search | G31: Text | H31: Active | I31: 46038 | K31: =IF(B31="","",IF(_xlfn.MINIFS('JOBS'!$B$5:$B$1504,'JOBS'!$D$5:$D$1504,B31,'JOBS'!$O$5:$O$1504,"Completed")=0,"",_xlfn.MINIFS('JOBS'!$B$5:$B$1504,'JOBS'!$D$5:$D$1504,B31,'JOBS'!$O$5:$O$1504,"Completed"))) | L31: =IF(B31="","",IF(_xlfn.MAXIFS('JOBS'!$B$5:$B$1504,'JOBS'!$D$5:$D$1504,B31,'JOBS'!$O$5:$O$1504,"Completed")=0,"",_xlfn.MAXIFS('JOBS'!$B$5:$B$1504,'JOBS'!$D$5:$D$1504,B31,'JOBS'!$O$5:$O$1504,"Completed"))) | M31: =IF(B31="","",COUNTIFS('JOBS'!$D$5:$D$1504,B31,'JOBS'!$O$5:$O$1504,"Completed")) | N31: =IF(B31="","",SUMIFS('JOBS'!$L$5:$L$1504,'JOBS'!$D$5:$D$1504,B31,'JOBS'!$O$5:$O$1504,"Completed")) | O31: =IF(B31="","",SUMIFS('JOBS'!$U$5:$U$1504,'JOBS'!$D$5:$D$1504,B31)) | P31: =IF(B31="","",IF(COUNTIFS('RECURRING'!$B$5:$B$154,B31,'RECURRING'!$J$5:$J$154,"Active")>0,"Yes","No")) | Q31: =IF(L31="","",AsOf-L31) | R31: =IF(B31="","",IF(H31="Do not service","—",IF(O31>0.005,"Collect balance",IF(M31=0,"Book first job",IF(AND(P31="No",Q31>=ReactDays),"Reactivate",IF(COUNTIF('REVIEWS'!$A$5:$A$504,B31)=0,"Ask for review",IF(AND(P31="No",M31>=1),"Offer recurring plan","—"))))))) | S31: =IF(B31="","",COUNTIF('REFERRALS'!$B$5:$B$204,B31))
A32: C-028 | B32: Emerson Holloway | C32: 555-0131 | D32: emerson.holloway@example.com | E32: Short-Term Rental Host | F32: Google Business Profile | G32: Call | H32: Active | I32: 46036 | K32: =IF(B32="","",IF(_xlfn.MINIFS('JOBS'!$B$5:$B$1504,'JOBS'!$D$5:$D$1504,B32,'JOBS'!$O$5:$O$1504,"Completed")=0,"",_xlfn.MINIFS('JOBS'!$B$5:$B$1504,'JOBS'!$D$5:$D$1504,B32,'JOBS'!$O$5:$O$1504,"Completed"))) | L32: =IF(B32="","",IF(_xlfn.MAXIFS('JOBS'!$B$5:$B$1504,'JOBS'!$D$5:$D$1504,B32,'JOBS'!$O$5:$O$1504,"Completed")=0,"",_xlfn.MAXIFS('JOBS'!$B$5:$B$1504,'JOBS'!$D$5:$D$1504,B32,'JOBS'!$O$5:$O$1504,"Completed"))) | M32: =IF(B32="","",COUNTIFS('JOBS'!$D$5:$D$1504,B32,'JOBS'!$O$5:$O$1504,"Completed")) | N32: =IF(B32="","",SUMIFS('JOBS'!$L$5:$L$1504,'JOBS'!$D$5:$D$1504,B32,'JOBS'!$O$5:$O$1504,"Completed")) | O32: =IF(B32="","",SUMIFS('JOBS'!$U$5:$U$1504,'JOBS'!$D$5:$D$1504,B32)) | P32: =IF(B32="","",IF(COUNTIFS('RECURRING'!$B$5:$B$154,B32,'RECURRING'!$J$5:$J$154,"Active")>0,"Yes","No")) | Q32: =IF(L32="","",AsOf-L32) | R32: =IF(B32="","",IF(H32="Do not service","—",IF(O32>0.005,"Collect balance",IF(M32=0,"Book first job",IF(AND(P32="No",Q32>=ReactDays),"Reactivate",IF(COUNTIF('REVIEWS'!$A$5:$A$504,B32)=0,"Ask for review",IF(AND(P32="No",M32>=1),"Offer recurring plan","—"))))))) | S32: =IF(B32="","",COUNTIF('REFERRALS'!$B$5:$B$204,B32))
A33: C-029 | B33: Parker Lockhart | C33: 555-0132 | D33: parker.lockhart@example.com | E33: Short-Term Rental Host | F33: Google Search | G33: Email | H33: Active | I33: 46046 | K33: =IF(B33="","",IF(_xlfn.MINIFS('JOBS'!$B$5:$B$1504,'JOBS'!$D$5:$D$1504,B33,'JOBS'!$O$5:$O$1504,"Completed")=0,"",_xlfn.MINIFS('JOBS'!$B$5:$B$1504,'JOBS'!$D$5:$D$1504,B33,'JOBS'!$O$5:$O$1504,"Completed"))) | L33: =IF(B33="","",IF(_xlfn.MAXIFS('JOBS'!$B$5:$B$1504,'JOBS'!$D$5:$D$1504,B33,'JOBS'!$O$5:$O$1504,"Completed")=0,"",_xlfn.MAXIFS('JOBS'!$B$5:$B$1504,'JOBS'!$D$5:$D$1504,B33,'JOBS'!$O$5:$O$1504,"Completed"))) | M33: =IF(B33="","",COUNTIFS('JOBS'!$D$5:$D$1504,B33,'JOBS'!$O$5:$O$1504,"Completed")) | N33: =IF(B33="","",SUMIFS('JOBS'!$L$5:$L$1504,'JOBS'!$D$5:$D$1504,B33,'JOBS'!$O$5:$O$1504,"Completed")) | O33: =IF(B33="","",SUMIFS('JOBS'!$U$5:$U$1504,'JOBS'!$D$5:$D$1504,B33)) | P33: =IF(B33="","",IF(COUNTIFS('RECURRING'!$B$5:$B$154,B33,'RECURRING'!$J$5:$J$154,"Active")>0,"Yes","No")) | Q33: =IF(L33="","",AsOf-L33) | R33: =IF(B33="","",IF(H33="Do not service","—",IF(O33>0.005,"Collect balance",IF(M33=0,"Book first job",IF(AND(P33="No",Q33>=ReactDays),"Reactivate",IF(COUNTIF('REVIEWS'!$A$5:$A$504,B33)=0,"Ask for review",IF(AND(P33="No",M33>=1),"Offer recurring plan","—"))))))) | S33: =IF(B33="","",COUNTIF('REFERRALS'!$B$5:$B$204,B33))
A34: C-030 | B34: Crescent Property Group (sample) | C34: 555-0133 | D34: crescent.property.group.(sample)@example.com | E34: Property Manager | F34: Google Business Profile | G34: Email | H34: Active | I34: 46073 | K34: =IF(B34="","",IF(_xlfn.MINIFS('JOBS'!$B$5:$B$1504,'JOBS'!$D$5:$D$1504,B34,'JOBS'!$O$5:$O$1504,"Completed")=0,"",_xlfn.MINIFS('JOBS'!$B$5:$B$1504,'JOBS'!$D$5:$D$1504,B34,'JOBS'!$O$5:$O$1504,"Completed"))) | L34: =IF(B34="","",IF(_xlfn.MAXIFS('JOBS'!$B$5:$B$1504,'JOBS'!$D$5:$D$1504,B34,'JOBS'!$O$5:$O$1504,"Completed")=0,"",_xlfn.MAXIFS('JOBS'!$B$5:$B$1504,'JOBS'!$D$5:$D$1504,B34,'JOBS'!$O$5:$O$1504,"Completed"))) | M34: =IF(B34="","",COUNTIFS('JOBS'!$D$5:$D$1504,B34,'JOBS'!$O$5:$O$1504,"Completed")) | N34: =IF(B34="","",SUMIFS('JOBS'!$L$5:$L$1504,'JOBS'!$D$5:$D$1504,B34,'JOBS'!$O$5:$O$1504,"Completed")) | O34: =IF(B34="","",SUMIFS('JOBS'!$U$5:$U$1504,'JOBS'!$D$5:$D$1504,B34)) | P34: =IF(B34="","",IF(COUNTIFS('RECURRING'!$B$5:$B$154,B34,'RECURRING'!$J$5:$J$154,"Active")>0,"Yes","No")) | Q34: =IF(L34="","",AsOf-L34) | R34: =IF(B34="","",IF(H34="Do not service","—",IF(O34>0.005,"Collect balance",IF(M34=0,"Book first job",IF(AND(P34="No",Q34>=ReactDays),"Reactivate",IF(COUNTIF('REVIEWS'!$A$5:$A$504,B34)=0,"Ask for review",IF(AND(P34="No",M34>=1),"Offer recurring plan","—"))))))) | S34: =IF(B34="","",COUNTIF('REFERRALS'!$B$5:$B$204,B34))
A35: C-031 | K35: =IF(B35="","",IF(_xlfn.MINIFS('JOBS'!$B$5:$B$1504,'JOBS'!$D$5:$D$1504,B35,'JOBS'!$O$5:$O$1504,"Completed")=0,"",_xlfn.MINIFS('JOBS'!$B$5:$B$1504,'JOBS'!$D$5:$D$1504,B35,'JOBS'!$O$5:$O$1504,"Completed"))) | L35: =IF(B35="","",IF(_xlfn.MAXIFS('JOBS'!$B$5:$B$1504,'JOBS'!$D$5:$D$1504,B35,'JOBS'!$O$5:$O$1504,"Completed")=0,"",_xlfn.MAXIFS('JOBS'!$B$5:$B$1504,'JOBS'!$D$5:$D$1504,B35,'JOBS'!$O$5:$O$1504,"Completed"))) | M35: =IF(B35="","",COUNTIFS('JOBS'!$D$5:$D$1504,B35,'JOBS'!$O$5:$O$1504,"Completed")) | N35: =IF(B35="","",SUMIFS('JOBS'!$L$5:$L$1504,'JOBS'!$D$5:$D$1504,B35,'JOBS'!$O$5:$O$1504,"Completed")) | O35: =IF(B35="","",SUMIFS('JOBS'!$U$5:$U$1504,'JOBS'!$D$5:$D$1504,B35)) | P35: =IF(B35="","",IF(COUNTIFS('RECURRING'!$B$5:$B$154,B35,'RECURRING'!$J$5:$J$154,"Active")>0,"Yes","No")) | Q35: =IF(L35="","",AsOf-L35) | R35: =IF(B35="","",IF(H35="Do not service","—",IF(O35>0.005,"Collect balance",IF(M35=0,"Book first job",IF(AND(P35="No",Q35>=ReactDays),"Reactivate",IF(COUNTIF('REVIEWS'!$A$5:$A$504,B35)=0,"Ask for review",IF(AND(P35="No",M35>=1),"Offer recurring plan","—"))))))) | S35: =IF(B35="","",COUNTIF('REFERRALS'!$B$5:$B$204,B35))
A36: C-032 | K36: =IF(B36="","",IF(_xlfn.MINIFS('JOBS'!$B$5:$B$1504,'JOBS'!$D$5:$D$1504,B36,'JOBS'!$O$5:$O$1504,"Completed")=0,"",_xlfn.MINIFS('JOBS'!$B$5:$B$1504,'JOBS'!$D$5:$D$1504,B36,'JOBS'!$O$5:$O$1504,"Completed"))) | L36: =IF(B36="","",IF(_xlfn.MAXIFS('JOBS'!$B$5:$B$1504,'JOBS'!$D$5:$D$1504,B36,'JOBS'!$O$5:$O$1504,"Completed")=0,"",_xlfn.MAXIFS('JOBS'!$B$5:$B$1504,'JOBS'!$D$5:$D$1504,B36,'JOBS'!$O$5:$O$1504,"Completed"))) | M36: =IF(B36="","",COUNTIFS('JOBS'!$D$5:$D$1504,B36,'JOBS'!$O$5:$O$1504,"Completed")) | N36: =IF(B36="","",SUMIFS('JOBS'!$L$5:$L$1504,'JOBS'!$D$5:$D$1504,B36,'JOBS'!$O$5:$O$1504,"Completed")) | O36: =IF(B36="","",SUMIFS('JOBS'!$U$5:$U$1504,'JOBS'!$D$5:$D$1504,B36)) | P36: =IF(B36="","",IF(COUNTIFS('RECURRING'!$B$5:$B$154,B36,'RECURRING'!$J$5:$J$154,"Active")>0,"Yes","No")) | Q36: =IF(L36="","",AsOf-L36) | R36: =IF(B36="","",IF(H36="Do not service","—",IF(O36>0.005,"Collect balance",IF(M36=0,"Book first job",IF(AND(P36="No",Q36>=ReactDays),"Reactivate",IF(COUNTIF('REVIEWS'!$A$5:$A$504,B36)=0,"Ask for review",IF(AND(P36="No",M36>=1),"Offer recurring plan","—"))))))) | S36: =IF(B36="","",COUNTIF('REFERRALS'!$B$5:$B$204,B36))
A37: C-033 | K37: =IF(B37="","",IF(_xlfn.MINIFS('JOBS'!$B$5:$B$1504,'JOBS'!$D$5:$D$1504,B37,'JOBS'!$O$5:$O$1504,"Completed")=0,"",_xlfn.MINIFS('JOBS'!$B$5:$B$1504,'JOBS'!$D$5:$D$1504,B37,'JOBS'!$O$5:$O$1504,"Completed"))) | L37: =IF(B37="","",IF(_xlfn.MAXIFS('JOBS'!$B$5:$B$1504,'JOBS'!$D$5:$D$1504,B37,'JOBS'!$O$5:$O$1504,"Completed")=0,"",_xlfn.MAXIFS('JOBS'!$B$5:$B$1504,'JOBS'!$D$5:$D$1504,B37,'JOBS'!$O$5:$O$1504,"Completed"))) | M37: =IF(B37="","",COUNTIFS('JOBS'!$D$5:$D$1504,B37,'JOBS'!$O$5:$O$1504,"Completed")) | N37: =IF(B37="","",SUMIFS('JOBS'!$L$5:$L$1504,'JOBS'!$D$5:$D$1504,B37,'JOBS'!$O$5:$O$1504,"Completed")) | O37: =IF(B37="","",SUMIFS('JOBS'!$U$5:$U$1504,'JOBS'!$D$5:$D$1504,B37)) | P37: =IF(B37="","",IF(COUNTIFS('RECURRING'!$B$5:$B$154,B37,'RECURRING'!$J$5:$J$154,"Active")>0,"Yes","No")) | Q37: =IF(L37="","",AsOf-L37) | R37: =IF(B37="","",IF(H37="Do not service","—",IF(O37>0.005,"Collect balance",IF(M37=0,"Book first job",IF(AND(P37="No",Q37>=ReactDays),"Reactivate",IF(COUNTIF('REVIEWS'!$A$5:$A$504,B37)=0,"Ask for review",IF(AND(P37="No",M37>=1),"Offer recurring plan","—"))))))) | S37: =IF(B37="","",COUNTIF('REFERRALS'!$B$5:$B$204,B37))
A38: C-034 | K38: =IF(B38="","",IF(_xlfn.MINIFS('JOBS'!$B$5:$B$1504,'JOBS'!$D$5:$D$1504,B38,'JOBS'!$O$5:$O$1504,"Completed")=0,"",_xlfn.MINIFS('JOBS'!$B$5:$B$1504,'JOBS'!$D$5:$D$1504,B38,'JOBS'!$O$5:$O$1504,"Completed"))) | L38: =IF(B38="","",IF(_xlfn.MAXIFS('JOBS'!$B$5:$B$1504,'JOBS'!$D$5:$D$1504,B38,'JOBS'!$O$5:$O$1504,"Completed")=0,"",_xlfn.MAXIFS('JOBS'!$B$5:$B$1504,'JOBS'!$D$5:$D$1504,B38,'JOBS'!$O$5:$O$1504,"Completed"))) | M38: =IF(B38="","",COUNTIFS('JOBS'!$D$5:$D$1504,B38,'JOBS'!$O$5:$O$1504,"Completed")) | N38: =IF(B38="","",SUMIFS('JOBS'!$L$5:$L$1504,'JOBS'!$D$5:$D$1504,B38,'JOBS'!$O$5:$O$1504,"Completed")) | O38: =IF(B38="","",SUMIFS('JOBS'!$U$5:$U$1504,'JOBS'!$D$5:$D$1504,B38)) | P38: =IF(B38="","",IF(COUNTIFS('RECURRING'!$B$5:$B$154,B38,'RECURRING'!$J$5:$J$154,"Active")>0,"Yes","No")) | Q38: =IF(L38="","",AsOf-L38) | R38: =IF(B38="","",IF(H38="Do not service","—",IF(O38>0.005,"Collect balance",IF(M38=0,"Book first job",IF(AND(P38="No",Q38>=ReactDays),"Reactivate",IF(COUNTIF('REVIEWS'!$A$5:$A$504,B38)=0,"Ask for review",IF(AND(P38="No",M38>=1),"Offer recurring plan","—"))))))) | S38: =IF(B38="","",COUNTIF('REFERRALS'!$B$5:$B$204,B38))
A39: C-035 | K39: =IF(B39="","",IF(_xlfn.MINIFS('JOBS'!$B$5:$B$1504,'JOBS'!$D$5:$D$1504,B39,'JOBS'!$O$5:$O$1504,"Completed")=0,"",_xlfn.MINIFS('JOBS'!$B$5:$B$1504,'JOBS'!$D$5:$D$1504,B39,'JOBS'!$O$5:$O$1504,"Completed"))) | L39: =IF(B39="","",IF(_xlfn.MAXIFS('JOBS'!$B$5:$B$1504,'JOBS'!$D$5:$D$1504,B39,'JOBS'!$O$5:$O$1504,"Completed")=0,"",_xlfn.MAXIFS('JOBS'!$B$5:$B$1504,'JOBS'!$D$5:$D$1504,B39,'JOBS'!$O$5:$O$1504,"Completed"))) | M39: =IF(B39="","",COUNTIFS('JOBS'!$D$5:$D$1504,B39,'JOBS'!$O$5:$O$1504,"Completed")) | N39: =IF(B39="","",SUMIFS('JOBS'!$L$5:$L$1504,'JOBS'!$D$5:$D$1504,B39,'JOBS'!$O$5:$O$1504,"Completed")) | O39: =IF(B39="","",SUMIFS('JOBS'!$U$5:$U$1504,'JOBS'!$D$5:$D$1504,B39)) | P39: =IF(B39="","",IF(COUNTIFS('RECURRING'!$B$5:$B$154,B39,'RECURRING'!$J$5:$J$154,"Active")>0,"Yes","No")) | Q39: =IF(L39="","",AsOf-L39) | R39: =IF(B39="","",IF(H39="Do not service","—",IF(O39>0.005,"Collect balance",IF(M39=0,"Book first job",IF(AND(P39="No",Q39>=ReactDays),"Reactivate",IF(COUNTIF('REVIEWS'!$A$5:$A$504,B39)=0,"Ask for review",IF(AND(P39="No",M39>=1),"Offer recurring plan","—"))))))) | S39: =IF(B39="","",COUNTIF('REFERRALS'!$B$5:$B$204,B39))
A40: C-036 | K40: =IF(B40="","",IF(_xlfn.MINIFS('JOBS'!$B$5:$B$1504,'JOBS'!$D$5:$D$1504,B40,'JOBS'!$O$5:$O$1504,"Completed")=0,"",_xlfn.MINIFS('JOBS'!$B$5:$B$1504,'JOBS'!$D$5:$D$1504,B40,'JOBS'!$O$5:$O$1504,"Completed"))) | L40: =IF(B40="","",IF(_xlfn.MAXIFS('JOBS'!$B$5:$B$1504,'JOBS'!$D$5:$D$1504,B40,'JOBS'!$O$5:$O$1504,"Completed")=0,"",_xlfn.MAXIFS('JOBS'!$B$5:$B$1504,'JOBS'!$D$5:$D$1504,B40,'JOBS'!$O$5:$O$1504,"Completed"))) | M40: =IF(B40="","",COUNTIFS('JOBS'!$D$5:$D$1504,B40,'JOBS'!$O$5:$O$1504,"Completed")) | N40: =IF(B40="","",SUMIFS('JOBS'!$L$5:$L$1504,'JOBS'!$D$5:$D$1504,B40,'JOBS'!$O$5:$O$1504,"Completed")) | O40: =IF(B40="","",SUMIFS('JOBS'!$U$5:$U$1504,'JOBS'!$D$5:$D$1504,B40)) | P40: =IF(B40="","",IF(COUNTIFS('RECURRING'!$B$5:$B$154,B40,'RECURRING'!$J$5:$J$154,"Active")>0,"Yes","No")) | Q40: =IF(L40="","",AsOf-L40) | R40: =IF(B40="","",IF(H40="Do not service","—",IF(O40>0.005,"Collect balance",IF(M40=0,"Book first job",IF(AND(P40="No",Q40>=ReactDays),"Reactivate",IF(COUNTIF('REVIEWS'!$A$5:$A$504,B40)=0,"Ask for review",IF(AND(P40="No",M40>=1),"Offer recurring plan","—"))))))) | S40: =IF(B40="","",COUNTIF('REFERRALS'!$B$5:$B$204,B40))
A41: C-037 | K41: =IF(B41="","",IF(_xlfn.MINIFS('JOBS'!$B$5:$B$1504,'JOBS'!$D$5:$D$1504,B41,'JOBS'!$O$5:$O$1504,"Completed")=0,"",_xlfn.MINIFS('JOBS'!$B$5:$B$1504,'JOBS'!$D$5:$D$1504,B41,'JOBS'!$O$5:$O$1504,"Completed"))) | L41: =IF(B41="","",IF(_xlfn.MAXIFS('JOBS'!$B$5:$B$1504,'JOBS'!$D$5:$D$1504,B41,'JOBS'!$O$5:$O$1504,"Completed")=0,"",_xlfn.MAXIFS('JOBS'!$B$5:$B$1504,'JOBS'!$D$5:$D$1504,B41,'JOBS'!$O$5:$O$1504,"Completed"))) | M41: =IF(B41="","",COUNTIFS('JOBS'!$D$5:$D$1504,B41,'JOBS'!$O$5:$O$1504,"Completed")) | N41: =IF(B41="","",SUMIFS('JOBS'!$L$5:$L$1504,'JOBS'!$D$5:$D$1504,B41,'JOBS'!$O$5:$O$1504,"Completed")) | O41: =IF(B41="","",SUMIFS('JOBS'!$U$5:$U$1504,'JOBS'!$D$5:$D$1504,B41)) | P41: =IF(B41="","",IF(COUNTIFS('RECURRING'!$B$5:$B$154,B41,'RECURRING'!$J$5:$J$154,"Active")>0,"Yes","No")) | Q41: =IF(L41="","",AsOf-L41) | R41: =IF(B41="","",IF(H41="Do not service","—",IF(O41>0.005,"Collect balance",IF(M41=0,"Book first job",IF(AND(P41="No",Q41>=ReactDays),"Reactivate",IF(COUNTIF('REVIEWS'!$A$5:$A$504,B41)=0,"Ask for review",IF(AND(P41="No",M41>=1),"Offer recurring plan","—"))))))) | S41: =IF(B41="","",COUNTIF('REFERRALS'!$B$5:$B$204,B41))
A42: C-038 | K42: =IF(B42="","",IF(_xlfn.MINIFS('JOBS'!$B$5:$B$1504,'JOBS'!$D$5:$D$1504,B42,'JOBS'!$O$5:$O$1504,"Completed")=0,"",_xlfn.MINIFS('JOBS'!$B$5:$B$1504,'JOBS'!$D$5:$D$1504,B42,'JOBS'!$O$5:$O$1504,"Completed"))) | L42: =IF(B42="","",IF(_xlfn.MAXIFS('JOBS'!$B$5:$B$1504,'JOBS'!$D$5:$D$1504,B42,'JOBS'!$O$5:$O$1504,"Completed")=0,"",_xlfn.MAXIFS('JOBS'!$B$5:$B$1504,'JOBS'!$D$5:$D$1504,B42,'JOBS'!$O$5:$O$1504,"Completed"))) | M42: =IF(B42="","",COUNTIFS('JOBS'!$D$5:$D$1504,B42,'JOBS'!$O$5:$O$1504,"Completed")) | N42: =IF(B42="","",SUMIFS('JOBS'!$L$5:$L$1504,'JOBS'!$D$5:$D$1504,B42,'JOBS'!$O$5:$O$1504,"Completed")) | O42: =IF(B42="","",SUMIFS('JOBS'!$U$5:$U$1504,'JOBS'!$D$5:$D$1504,B42)) | P42: =IF(B42="","",IF(COUNTIFS('RECURRING'!$B$5:$B$154,B42,'RECURRING'!$J$5:$J$154,"Active")>0,"Yes","No")) | Q42: =IF(L42="","",AsOf-L42) | R42: =IF(B42="","",IF(H42="Do not service","—",IF(O42>0.005,"Collect balance",IF(M42=0,"Book first job",IF(AND(P42="No",Q42>=ReactDays),"Reactivate",IF(COUNTIF('REVIEWS'!$A$5:$A$504,B42)=0,"Ask for review",IF(AND(P42="No",M42>=1),"Offer recurring plan","—"))))))) | S42: =IF(B42="","",COUNTIF('REFERRALS'!$B$5:$B$204,B42))
A43: C-039 | K43: =IF(B43="","",IF(_xlfn.MINIFS('JOBS'!$B$5:$B$1504,'JOBS'!$D$5:$D$1504,B43,'JOBS'!$O$5:$O$1504,"Completed")=0,"",_xlfn.MINIFS('JOBS'!$B$5:$B$1504,'JOBS'!$D$5:$D$1504,B43,'JOBS'!$O$5:$O$1504,"Completed"))) | L43: =IF(B43="","",IF(_xlfn.MAXIFS('JOBS'!$B$5:$B$1504,'JOBS'!$D$5:$D$1504,B43,'JOBS'!$O$5:$O$1504,"Completed")=0,"",_xlfn.MAXIFS('JOBS'!$B$5:$B$1504,'JOBS'!$D$5:$D$1504,B43,'JOBS'!$O$5:$O$1504,"Completed"))) | M43: =IF(B43="","",COUNTIFS('JOBS'!$D$5:$D$1504,B43,'JOBS'!$O$5:$O$1504,"Completed")) | N43: =IF(B43="","",SUMIFS('JOBS'!$L$5:$L$1504,'JOBS'!$D$5:$D$1504,B43,'JOBS'!$O$5:$O$1504,"Completed")) | O43: =IF(B43="","",SUMIFS('JOBS'!$U$5:$U$1504,'JOBS'!$D$5:$D$1504,B43)) | P43: =IF(B43="","",IF(COUNTIFS('RECURRING'!$B$5:$B$154,B43,'RECURRING'!$J$5:$J$154,"Active")>0,"Yes","No")) | Q43: =IF(L43="","",AsOf-L43) | R43: =IF(B43="","",IF(H43="Do not service","—",IF(O43>0.005,"Collect balance",IF(M43=0,"Book first job",IF(AND(P43="No",Q43>=ReactDays),"Reactivate",IF(COUNTIF('REVIEWS'!$A$5:$A$504,B43)=0,"Ask for review",IF(AND(P43="No",M43>=1),"Offer recurring plan","—"))))))) | S43: =IF(B43="","",COUNTIF('REFERRALS'!$B$5:$B$204,B43))
A44: C-040 | K44: =IF(B44="","",IF(_xlfn.MINIFS('JOBS'!$B$5:$B$1504,'JOBS'!$D$5:$D$1504,B44,'JOBS'!$O$5:$O$1504,"Completed")=0,"",_xlfn.MINIFS('JOBS'!$B$5:$B$1504,'JOBS'!$D$5:$D$1504,B44,'JOBS'!$O$5:$O$1504,"Completed"))) | L44: =IF(B44="","",IF(_xlfn.MAXIFS('JOBS'!$B$5:$B$1504,'JOBS'!$D$5:$D$1504,B44,'JOBS'!$O$5:$O$1504,"Completed")=0,"",_xlfn.MAXIFS('JOBS'!$B$5:$B$1504,'JOBS'!$D$5:$D$1504,B44,'JOBS'!$O$5:$O$1504,"Completed"))) | M44: =IF(B44="","",COUNTIFS('JOBS'!$D$5:$D$1504,B44,'JOBS'!$O$5:$O$1504,"Completed")) | N44: =IF(B44="","",SUMIFS('JOBS'!$L$5:$L$1504,'JOBS'!$D$5:$D$1504,B44,'JOBS'!$O$5:$O$1504,"Completed")) | O44: =IF(B44="","",SUMIFS('JOBS'!$U$5:$U$1504,'JOBS'!$D$5:$D$1504,B44)) | P44: =IF(B44="","",IF(COUNTIFS('RECURRING'!$B$5:$B$154,B44,'RECURRING'!$J$5:$J$154,"Active")>0,"Yes","No")) | Q44: =IF(L44="","",AsOf-L44) | R44: =IF(B44="","",IF(H44="Do not service","—",IF(O44>0.005,"Collect balance",IF(M44=0,"Book first job",IF(AND(P44="No",Q44>=ReactDays),"Reactivate",IF(COUNTIF('REVIEWS'!$A$5:$A$504,B44)=0,"Ask for review",IF(AND(P44="No",M44>=1),"Offer recurring plan","—"))))))) | S44: =IF(B44="","",COUNTIF('REFERRALS'!$B$5:$B$204,B44))
A45: C-041 | K45: =IF(B45="","",IF(_xlfn.MINIFS('JOBS'!$B$5:$B$1504,'JOBS'!$D$5:$D$1504,B45,'JOBS'!$O$5:$O$1504,"Completed")=0,"",_xlfn.MINIFS('JOBS'!$B$5:$B$1504,'JOBS'!$D$5:$D$1504,B45,'JOBS'!$O$5:$O$1504,"Completed"))) | L45: =IF(B45="","",IF(_xlfn.MAXIFS('JOBS'!$B$5:$B$1504,'JOBS'!$D$5:$D$1504,B45,'JOBS'!$O$5:$O$1504,"Completed")=0,"",_xlfn.MAXIFS('JOBS'!$B$5:$B$1504,'JOBS'!$D$5:$D$1504,B45,'JOBS'!$O$5:$O$1504,"Completed"))) | M45: =IF(B45="","",COUNTIFS('JOBS'!$D$5:$D$1504,B45,'JOBS'!$O$5:$O$1504,"Completed")) | N45: =IF(B45="","",SUMIFS('JOBS'!$L$5:$L$1504,'JOBS'!$D$5:$D$1504,B45,'JOBS'!$O$5:$O$1504,"Completed")) | O45: =IF(B45="","",SUMIFS('JOBS'!$U$5:$U$1504,'JOBS'!$D$5:$D$1504,B45)) | P45: =IF(B45="","",IF(COUNTIFS('RECURRING'!$B$5:$B$154,B45,'RECURRING'!$J$5:$J$154,"Active")>0,"Yes","No")) | Q45: =IF(L45="","",AsOf-L45) | R45: =IF(B45="","",IF(H45="Do not service","—",IF(O45>0.005,"Collect balance",IF(M45=0,"Book first job",IF(AND(P45="No",Q45>=ReactDays),"Reactivate",IF(COUNTIF('REVIEWS'!$A$5:$A$504,B45)=0,"Ask for review",IF(AND(P45="No",M45>=1),"Offer recurring plan","—"))))))) | S45: =IF(B45="","",COUNTIF('REFERRALS'!$B$5:$B$204,B45))
A46: C-042 | K46: =IF(B46="","",IF(_xlfn.MINIFS('JOBS'!$B$5:$B$1504,'JOBS'!$D$5:$D$1504,B46,'JOBS'!$O$5:$O$1504,"Completed")=0,"",_xlfn.MINIFS('JOBS'!$B$5:$B$1504,'JOBS'!$D$5:$D$1504,B46,'JOBS'!$O$5:$O$1504,"Completed"))) | L46: =IF(B46="","",IF(_xlfn.MAXIFS('JOBS'!$B$5:$B$1504,'JOBS'!$D$5:$D$1504,B46,'JOBS'!$O$5:$O$1504,"Completed")=0,"",_xlfn.MAXIFS('JOBS'!$B$5:$B$1504,'JOBS'!$D$5:$D$1504,B46,'JOBS'!$O$5:$O$1504,"Completed"))) | M46: =IF(B46="","",COUNTIFS('JOBS'!$D$5:$D$1504,B46,'JOBS'!$O$5:$O$1504,"Completed")) | N46: =IF(B46="","",SUMIFS('JOBS'!$L$5:$L$1504,'JOBS'!$D$5:$D$1504,B46,'JOBS'!$O$5:$O$1504,"Completed")) | O46: =IF(B46="","",SUMIFS('JOBS'!$U$5:$U$1504,'JOBS'!$D$5:$D$1504,B46)) | P46: =IF(B46="","",IF(COUNTIFS('RECURRING'!$B$5:$B$154,B46,'RECURRING'!$J$5:$J$154,"Active")>0,"Yes","No")) | Q46: =IF(L46="","",AsOf-L46) | R46: =IF(B46="","",IF(H46="Do not service","—",IF(O46>0.005,"Collect balance",IF(M46=0,"Book first job",IF(AND(P46="No",Q46>=ReactDays),"Reactivate",IF(COUNTIF('REVIEWS'!$A$5:$A$504,B46)=0,"Ask for review",IF(AND(P46="No",M46>=1),"Offer recurring plan","—"))))))) | S46: =IF(B46="","",COUNTIF('REFERRALS'!$B$5:$B$204,B46))
... A404: C-400 | K404: =IF(B404="","",IF(_xlfn.MINIFS('JOBS'!$B$5:$B$1504,'JOBS'!$D$5:$D$1504,B404,'JOBS'!$O$5:$O$1504,"Completed")=0,"",_xlfn.MINIFS('JOBS'!$B$5:$B$1504,'JOBS'!$D$5:$D$1504,B404,'JOBS'!$O$5:$O$1504,"Completed"))) | L404: =IF(B404="","",IF(_xlfn.MAXIFS('JOBS'!$B$5:$B$1504,'JOBS'!$D$5:$D$1504,B404,'JOBS'!$O$5:$O$1504,"Completed")=0,"",_xlfn.MAXIFS('JOBS'!$B$5:$B$1504,'JOBS'!$D$5:$D$1504,B404,'JOBS'!$O$5:$O$1504,"Completed"))) | M404: =IF(B404="","",COUNTIFS('JOBS'!$D$5:$D$1504,B404,'JOBS'!$O$5:$O$1504,"Completed")) | N404: =IF(B404="","",SUMIFS('JOBS'!$L$5:$L$1504,'JOBS'!$D$5:$D$1504,B404,'JOBS'!$O$5:$O$1504,"Completed")) | O404: =IF(B404="","",SUMIFS('JOBS'!$U$5:$U$1504,'JOBS'!$D$5:$D$1504,B404)) | P404: =IF(B404="","",IF(COUNTIFS('RECURRING'!$B$5:$B$154,B404,'RECURRING'!$J$5:$J$154,"Active")>0,"Yes","No")) | Q404: =IF(L404="","",AsOf-L404) | R404: =IF(B404="","",IF(H404="Do not service","—",IF(O404>0.005,"Collect balance",IF(M404=0,"Book first job",IF(AND(P404="No",Q404>=ReactDays),"Reactivate",IF(COUNTIF('REVIEWS'!$A$5:$A$504,B404)=0,"Ask for review",IF(AND(P404="No",M404>=1),"Offer recurring plan","—"))))))) | S404: =IF(B404="","",COUNTIF('REFERRALS'!$B$5:$B$204,B404))

Sheet PROPERTIES
A1: PROPERTIES
A2: One row per property. Square footage, bedrooms and bathrooms power the automatic time estimate in JOBS. Keep access notes here, not in public places.
A3: ← Start Here | B3: Dashboard →
A4: Property ID | B4: Address / Label (unique) | C4: Customer | D4: City / Area | E4: Property Type | F4: Sq Ft | G4: Bedrooms | H4: Bathrooms | I4: Pets | J4: Access / Entry Instructions | K4: Parking | L4: Special Requests / Notes | M4: Completed Jobs ⚙ | N4: Last Clean ⚙ | O4: Avg Price ⚙
A5: P-001 | B5: 497 Aspen Drive, Sampletown | C5: Lane Ivers | D5: Sampletown | E5: House | F5: 2400 | G5: 4 | H5: 2.5 | J5: Key under office management | K5: Visitor lot | L5: Shoes off at entry | M5: =IF(B5="","",COUNTIFS('JOBS'!$E$5:$E$1504,B5,'JOBS'!$O$5:$O$1504,"Completed")) | N5: =IF(B5="","",IF(_xlfn.MAXIFS('JOBS'!$B$5:$B$1504,'JOBS'!$E$5:$E$1504,B5,'JOBS'!$O$5:$O$1504,"Completed")=0,"",_xlfn.MAXIFS('JOBS'!$B$5:$B$1504,'JOBS'!$E$5:$E$1504,B5,'JOBS'!$O$5:$O$1504,"Completed"))) | O5: =IF(B5="","",IFERROR(AVERAGEIFS('JOBS'!$L$5:$L$1504,'JOBS'!$E$5:$E$1504,B5,'JOBS'!$O$5:$O$1504,"Completed"),""))
A6: P-002 | B6: 675 Aspen Drive, Lakeview (fictional) | C6: Logan Porter | D6: Lakeview (fictional) | E6: Condo | F6: 2900 | G6: 4 | H6: 3 | I6: 2 cats | J6: Lockbox code on file | K6: Driveway | L6: Shoes off at entry | M6: =IF(B6="","",COUNTIFS('JOBS'!$E$5:$E$1504,B6,'JOBS'!$O$5:$O$1504,"Completed")) | N6: =IF(B6="","",IF(_xlfn.MAXIFS('JOBS'!$B$5:$B$1504,'JOBS'!$E$5:$E$1504,B6,'JOBS'!$O$5:$O$1504,"Completed")=0,"",_xlfn.MAXIFS('JOBS'!$B$5:$B$1504,'JOBS'!$E$5:$E$1504,B6,'JOBS'!$O$5:$O$1504,"Completed"))) | O6: =IF(B6="","",IFERROR(AVERAGEIFS('JOBS'!$L$5:$L$1504,'JOBS'!$E$5:$E$1504,B6,'JOBS'!$O$5:$O$1504,"Completed"),""))
A7: P-003 | B7: 461 Hawthorn Road, Lakeview (fictional) | C7: Devon Hayes | D7: Lakeview (fictional) | E7: House | F7: 2900 | G7: 4 | H7: 3 | I7: 2 cats | J7: Customer home | K7: Visitor lot | L7: Unscented products only | M7: =IF(B7="","",COUNTIFS('JOBS'!$E$5:$E$1504,B7,'JOBS'!$O$5:$O$1504,"Completed")) | N7: =IF(B7="","",IF(_xlfn.MAXIFS('JOBS'!$B$5:$B$1504,'JOBS'!$E$5:$E$1504,B7,'JOBS'!$O$5:$O$1504,"Completed")=0,"",_xlfn.MAXIFS('JOBS'!$B$5:$B$1504,'JOBS'!$E$5:$E$1504,B7,'JOBS'!$O$5:$O$1504,"Completed"))) | O7: =IF(B7="","",IFERROR(AVERAGEIFS('JOBS'!$L$5:$L$1504,'JOBS'!$E$5:$E$1504,B7,'JOBS'!$O$5:$O$1504,"Completed"),""))
A8: P-004 | B8: 964 Cedar Court, Lakeview (fictional) | C8: Noel Collins | D8: Lakeview (fictional) | E8: Townhome | F8: 3200 | G8: 5 | H8: 3.5 | I8: 2 cats | J8: Garage keypad (code in office file) | K8: Visitor lot | L8: Shoes off at entry | M8: =IF(B8="","",COUNTIFS('JOBS'!$E$5:$E$1504,B8,'JOBS'!$O$5:$O$1504,"Completed")) | N8: =IF(B8="","",IF(_xlfn.MAXIFS('JOBS'!$B$5:$B$1504,'JOBS'!$E$5:$E$1504,B8,'JOBS'!$O$5:$O$1504,"Completed")=0,"",_xlfn.MAXIFS('JOBS'!$B$5:$B$1504,'JOBS'!$E$5:$E$1504,B8,'JOBS'!$O$5:$O$1504,"Completed"))) | O8: =IF(B8="","",IFERROR(AVERAGEIFS('JOBS'!$L$5:$L$1504,'JOBS'!$E$5:$E$1504,B8,'JOBS'!$O$5:$O$1504,"Completed"),""))
A9: P-005 | B9: 876 Magnolia Circle, North Sampletown | C9: Rowan Foxworth | D9: North Sampletown | E9: House | F9: 2900 | G9: 4 | H9: 3 | I9: 2 cats | J9: Lockbox code on file | K9: Driveway | M9: =IF(B9="","",COUNTIFS('JOBS'!$E$5:$E$1504,B9,'JOBS'!$O$5:$O$1504,"Completed")) | N9: =IF(B9="","",IF(_xlfn.MAXIFS('JOBS'!$B$5:$B$1504,'JOBS'!$E$5:$E$1504,B9,'JOBS'!$O$5:$O$1504,"Completed")=0,"",_xlfn.MAXIFS('JOBS'!$B$5:$B$1504,'JOBS'!$E$5:$E$1504,B9,'JOBS'!$O$5:$O$1504,"Completed"))) | O9: =IF(B9="","",IFERROR(AVERAGEIFS('JOBS'!$L$5:$L$1504,'JOBS'!$E$5:$E$1504,B9,'JOBS'!$O$5:$O$1504,"Completed"),""))
A10: P-006 | B10: 84 Hawthorn Road, Lakeview (fictional) | C10: Dana Collins | D10: Lakeview (fictional) | E10: Condo | F10: 2400 | G10: 4 | H10: 2.5 | I10: 2 cats | J10: Garage keypad (code in office file) | K10: Visitor lot | L10: Skip office room | M10: =IF(B10="","",COUNTIFS('JOBS'!$E$5:$E$1504,B10,'JOBS'!$O$5:$O$1504,"Completed")) | N10: =IF(B10="","",IF(_xlfn.MAXIFS('JOBS'!$B$5:$B$1504,'JOBS'!$E$5:$E$1504,B10,'JOBS'!$O$5:$O$1504,"Completed")=0,"",_xlfn.MAXIFS('JOBS'!$B$5:$B$1504,'JOBS'!$E$5:$E$1504,B10,'JOBS'!$O$5:$O$1504,"Completed"))) | O10: =IF(B10="","",IFERROR(AVERAGEIFS('JOBS'!$L$5:$L$1504,'JOBS'!$E$5:$E$1504,B10,'JOBS'!$O$5:$O$1504,"Completed"),""))
A11: P-007 | B11: 21 Maple Avenue, North Sampletown | C11: Finley Quigley | D11: North Sampletown | E11: House | F11: 1300 | G11: 2 | H11: 1.5 | J11: Key under office management | K11: Street | M11: =IF(B11="","",COUNTIFS('JOBS'!$E$5:$E$1504,B11,'JOBS'!$O$5:$O$1504,"Completed")) | N11: =IF(B11="","",IF(_xlfn.MAXIFS('JOBS'!$B$5:$B$1504,'JOBS'!$E$5:$E$1504,B11,'JOBS'!$O$5:$O$1504,"Completed")=0,"",_xlfn.MAXIFS('JOBS'!$B$5:$B$1504,'JOBS'!$E$5:$E$1504,B11,'JOBS'!$O$5:$O$1504,"Completed"))) | O11: =IF(B11="","",IFERROR(AVERAGEIFS('JOBS'!$L$5:$L$1504,'JOBS'!$E$5:$E$1504,B11,'JOBS'!$O$5:$O$1504,"Completed"),""))
A12: P-008 | B12: 129 Elm Terrace, North Sampletown | C12: Dana Ivers | D12: North Sampletown | E12: House | F12: 3600 | G12: 5 | H12: 3.5 | I12: 2 cats | J12: Customer home | K12: Driveway | L12: Skip office room | M12: =IF(B12="","",COUNTIFS('JOBS'!$E$5:$E$1504,B12,'JOBS'!$O$5:$O$1504,"Completed")) | N12: =IF(B12="","",IF(_xlfn.MAXIFS('JOBS'!$B$5:$B$1504,'JOBS'!$E$5:$E$1504,B12,'JOBS'!$O$5:$O$1504,"Completed")=0,"",_xlfn.MAXIFS('JOBS'!$B$5:$B$1504,'JOBS'!$E$5:$E$1504,B12,'JOBS'!$O$5:$O$1504,"Completed"))) | O12: =IF(B12="","",IFERROR(AVERAGEIFS('JOBS'!$L$5:$L$1504,'JOBS'!$E$5:$E$1504,B12,'JOBS'!$O$5:$O$1504,"Completed"),""))
A13: P-009 | B13: 667 Willow Way, Sampletown | C13: Taylor Quigley | D13: Sampletown | E13: House | F13: 1700 | G13: 3 | H13: 2 | I13: 2 cats | J13: Customer home | K13: Street | L13: Shoes off at entry | M13: =IF(B13="","",COUNTIFS('JOBS'!$E$5:$E$1504,B13,'JOBS'!$O$5:$O$1504,"Completed")) | N13: =IF(B13="","",IF(_xlfn.MAXIFS('JOBS'!$B$5:$B$1504,'JOBS'!$E$5:$E$1504,B13,'JOBS'!$O$5:$O$1504,"Completed")=0,"",_xlfn.MAXIFS('JOBS'!$B$5:$B$1504,'JOBS'!$E$5:$E$1504,B13,'JOBS'!$O$5:$O$1504,"Completed"))) | O13: =IF(B13="","",IFERROR(AVERAGEIFS('JOBS'!$L$5:$L$1504,'JOBS'!$E$5:$E$1504,B13,'JOBS'!$O$5:$O$1504,"Completed"),""))
A14: P-010 | B14: 102 Hawthorn Road, Lakeview (fictional) | C14: Lane Northcott | D14: Lakeview (fictional) | E14: Condo | F14: 1800 | G14: 3 | H14: 2 | J14: Customer home | K14: Driveway | M14: =IF(B14="","",COUNTIFS('JOBS'!$E$5:$E$1504,B14,'JOBS'!$O$5:$O$1504,"Completed")) | N14: =IF(B14="","",IF(_xlfn.MAXIFS('JOBS'!$B$5:$B$1504,'JOBS'!$E$5:$E$1504,B14,'JOBS'!$O$5:$O$1504,"Completed")=0,"",_xlfn.MAXIFS('JOBS'!$B$5:$B$1504,'JOBS'!$E$5:$E$1504,B14,'JOBS'!$O$5:$O$1504,"Completed"))) | O14: =IF(B14="","",IFERROR(AVERAGEIFS('JOBS'!$L$5:$L$1504,'JOBS'!$E$5:$E$1504,B14,'JOBS'!$O$5:$O$1504,"Completed"),""))
A15: P-011 | B15: 897 Elm Terrace, Sampletown | C15: Peyton Underhill | D15: Sampletown | E15: Condo | F15: 1500 | G15: 3 | H15: 2 | I15: 1 cat | J15: Customer home | K15: Visitor lot | M15: =IF(B15="","",COUNTIFS('JOBS'!$E$5:$E$1504,B15,'JOBS'!$O$5:$O$1504,"Completed")) | N15: =IF(B15="","",IF(_xlfn.MAXIFS('JOBS'!$B$5:$B$1504,'JOBS'!$E$5:$E$1504,B15,'JOBS'!$O$5:$O$1504,"Completed")=0,"",_xlfn.MAXIFS('JOBS'!$B$5:$B$1504,'JOBS'!$E$5:$E$1504,B15,'JOBS'!$O$5:$O$1504,"Completed"))) | O15: =IF(B15="","",IFERROR(AVERAGEIFS('JOBS'!$L$5:$L$1504,'JOBS'!$E$5:$E$1504,B15,'JOBS'!$O$5:$O$1504,"Completed"),""))
A16: P-012 | B16: 628 Cedar Court, North Sampletown | C16: Rowan Merriweather | D16: North Sampletown | E16: House | F16: 3600 | G16: 5 | H16: 3.5 | I16: 2 cats | J16: Lockbox code on file | K16: Driveway | L16: Skip office room | M16: =IF(B16="","",COUNTIFS('JOBS'!$E$5:$E$1504,B16,'JOBS'!$O$5:$O$1504,"Completed")) | N16: =IF(B16="","",IF(_xlfn.MAXIFS('JOBS'!$B$5:$B$1504,'JOBS'!$E$5:$E$1504,B16,'JOBS'!$O$5:$O$1504,"Completed")=0,"",_xlfn.MAXIFS('JOBS'!$B$5:$B$1504,'JOBS'!$E$5:$E$1504,B16,'JOBS'!$O$5:$O$1504,"Completed"))) | O16: =IF(B16="","",IFERROR(AVERAGEIFS('JOBS'!$L$5:$L$1504,'JOBS'!$E$5:$E$1504,B16,'JOBS'!$O$5:$O$1504,"Completed"),""))
A17: P-013 | B17: 853 Alder Lane, North Sampletown | C17: Harper Hayes | D17: North Sampletown | E17: Condo | F17: 1700 | G17: 3 | H17: 2 | I17: 1 dog | J17: Smart lock — code sent day before | K17: Street | L17: Skip office room | M17: =IF(B17="","",COUNTIFS('JOBS'!$E$5:$E$1504,B17,'JOBS'!$O$5:$O$1504,"Completed")) | N17: =IF(B17="","",IF(_xlfn.MAXIFS('JOBS'!$B$5:$B$1504,'JOBS'!$E$5:$E$1504,B17,'JOBS'!$O$5:$O$1504,"Completed")=0,"",_xlfn.MAXIFS('JOBS'!$B$5:$B$1504,'JOBS'!$E$5:$E$1504,B17,'JOBS'!$O$5:$O$1504,"Completed"))) | O17: =IF(B17="","",IFERROR(AVERAGEIFS('JOBS'!$L$5:$L$1504,'JOBS'!$E$5:$E$1504,B17,'JOBS'!$O$5:$O$1504,"Completed"),""))
A18: P-014 | B18: 80 Sycamore Street, North Sampletown | C18: Emerson Calloway | D18: North Sampletown | E18: House | F18: 1800 | G18: 3 | H18: 2 | J18: Key under office management | K18: Street | M18: =IF(B18="","",COUNTIFS('JOBS'!$E$5:$E$1504,B18,'JOBS'!$O$5:$O$1504,"Completed")) | N18: =IF(B18="","",IF(_xlfn.MAXIFS('JOBS'!$B$5:$B$1504,'JOBS'!$E$5:$E$1504,B18,'JOBS'!$O$5:$O$1504,"Completed")=0,"",_xlfn.MAXIFS('JOBS'!$B$5:$B$1504,'JOBS'!$E$5:$E$1504,B18,'JOBS'!$O$5:$O$1504,"Completed"))) | O18: =IF(B18="","",IFERROR(AVERAGEIFS('JOBS'!$L$5:$L$1504,'JOBS'!$E$5:$E$1504,B18,'JOBS'!$O$5:$O$1504,"Completed"),""))
A19: P-015 | B19: 348 Hazel Court, Lakeview (fictional) | C19: Parker Pembrook | D19: Lakeview (fictional) | E19: Townhome | F19: 1300 | G19: 2 | H19: 1.5 | J19: Customer home | K19: Driveway | L19: Skip office room | M19: =IF(B19="","",COUNTIFS('JOBS'!$E$5:$E$1504,B19,'JOBS'!$O$5:$O$1504,"Completed")) | N19: =IF(B19="","",IF(_xlfn.MAXIFS('JOBS'!$B$5:$B$1504,'JOBS'!$E$5:$E$1504,B19,'JOBS'!$O$5:$O$1504,"Completed")=0,"",_xlfn.MAXIFS('JOBS'!$B$5:$B$1504,'JOBS'!$E$5:$E$1504,B19,'JOBS'!$O$5:$O$1504,"Completed"))) | O19: =IF(B19="","",IFERROR(AVERAGEIFS('JOBS'!$L$5:$L$1504,'JOBS'!$E$5:$E$1504,B19,'JOBS'!$O$5:$O$1504,"Completed"),""))
A20: P-016 | B20: 503 Cedar Court, Lakeview (fictional) | C20: Blake Dunmore | D20: Lakeview (fictional) | E20: House | F20: 1100 | G20: 2 | H20: 1.5 | I20: 1 cat | J20: Garage keypad (code in office file) | K20: Visitor lot | M20: =IF(B20="","",COUNTIFS('JOBS'!$E$5:$E$1504,B20,'JOBS'!$O$5:$O$1504,"Completed")) | N20: =IF(B20="","",IF(_xlfn.MAXIFS('JOBS'!$B$5:$B$1504,'JOBS'!$E$5:$E$1504,B20,'JOBS'!$O$5:$O$1504,"Completed")=0,"",_xlfn.MAXIFS('JOBS'!$B$5:$B$1504,'JOBS'!$E$5:$E$1504,B20,'JOBS'!$O$5:$O$1504,"Completed"))) | O20: =IF(B20="","",IFERROR(AVERAGEIFS('JOBS'!$L$5:$L$1504,'JOBS'!$E$5:$E$1504,B20,'JOBS'!$O$5:$O$1504,"Completed"),""))
A21: P-017 | B21: 370 Cedar Court, Lakeview (fictional) | C21: Kendall Sutton | D21: Lakeview (fictional) | E21: House | F21: 3600 | G21: 5 | H21: 3.5 | J21: Key under office management | K21: Driveway | L21: Unscented products only | M21: =IF(B21="","",COUNTIFS('JOBS'!$E$5:$E$1504,B21,'JOBS'!$O$5:$O$1504,"Completed")) | N21: =IF(B21="","",IF(_xlfn.MAXIFS('JOBS'!$B$5:$B$1504,'JOBS'!$E$5:$E$1504,B21,'JOBS'!$O$5:$O$1504,"Completed")=0,"",_xlfn.MAXIFS('JOBS'!$B$5:$B$1504,'JOBS'!$E$5:$E$1504,B21,'JOBS'!$O$5:$O$1504,"Completed"))) | O21: =IF(B21="","",IFERROR(AVERAGEIFS('JOBS'!$L$5:$L$1504,'JOBS'!$E$5:$E$1504,B21,'JOBS'!$O$5:$O$1504,"Completed"),""))
A22: P-018 | B22: 22 Cedar Court, Sampletown | C22: Drew Bennett | D22: Sampletown | E22: Condo | F22: 2900 | G22: 4 | H22: 3 | I22: 2 cats | J22: Lockbox code on file | K22: Driveway | L22: Shoes off at entry | M22: =IF(B22="","",COUNTIFS('JOBS'!$E$5:$E$1504,B22,'JOBS'!$O$5:$O$1504,"Completed")) | N22: =IF(B22="","",IF(_xlfn.MAXIFS('JOBS'!$B$5:$B$1504,'JOBS'!$E$5:$E$1504,B22,'JOBS'!$O$5:$O$1504,"Completed")=0,"",_xlfn.MAXIFS('JOBS'!$B$5:$B$1504,'JOBS'!$E$5:$E$1504,B22,'JOBS'!$O$5:$O$1504,"Completed"))) | O22: =IF(B22="","",IFERROR(AVERAGEIFS('JOBS'!$L$5:$L$1504,'JOBS'!$E$5:$E$1504,B22,'JOBS'!$O$5:$O$1504,"Completed"),""))
A23: P-019 | B23: 868 Rowan Drive, Sampletown | C23: Skyler Yardley | D23: Sampletown | E23: Condo | F23: 3600 | G23: 5 | H23: 3.5 | I23: 2 cats | J23: Smart lock — code sent day before | K23: Driveway | L23: Skip office room | M23: =IF(B23="","",COUNTIFS('JOBS'!$E$5:$E$1504,B23,'JOBS'!$O$5:$O$1504,"Completed")) | N23: =IF(B23="","",IF(_xlfn.MAXIFS('JOBS'!$B$5:$B$1504,'JOBS'!$E$5:$E$1504,B23,'JOBS'!$O$5:$O$1504,"Completed")=0,"",_xlfn.MAXIFS('JOBS'!$B$5:$B$1504,'JOBS'!$E$5:$E$1504,B23,'JOBS'!$O$5:$O$1504,"Completed"))) | O23: =IF(B23="","",IFERROR(AVERAGEIFS('JOBS'!$L$5:$L$1504,'JOBS'!$E$5:$E$1504,B23,'JOBS'!$O$5:$O$1504,"Completed"),""))
A24: P-020 | B24: 685 Alder Lane, North Sampletown | C24: Wren Porter | D24: North Sampletown | E24: House | F24: 3600 | G24: 5 | H24: 3.5 | I24: 2 cats | J24: Lockbox code on file | K24: Visitor lot | L24: Shoes off at entry | M24: =IF(B24="","",COUNTIFS('JOBS'!$E$5:$E$1504,B24,'JOBS'!$O$5:$O$1504,"Completed")) | N24: =IF(B24="","",IF(_xlfn.MAXIFS('JOBS'!$B$5:$B$1504,'JOBS'!$E$5:$E$1504,B24,'JOBS'!$O$5:$O$1504,"Completed")=0,"",_xlfn.MAXIFS('JOBS'!$B$5:$B$1504,'JOBS'!$E$5:$E$1504,B24,'JOBS'!$O$5:$O$1504,"Completed"))) | O24: =IF(B24="","",IFERROR(AVERAGEIFS('JOBS'!$L$5:$L$1504,'JOBS'!$E$5:$E$1504,B24,'JOBS'!$O$5:$O$1504,"Completed"),""))
A25: P-021 | B25: 520 Linden Place, North Sampletown | C25: Wren Delgado | D25: North Sampletown | E25: House | F25: 2600 | G25: 4 | H25: 3 | I25: 1 dog | J25: Key under office management | K25: Visitor lot | L25: Skip office room | M25: =IF(B25="","",COUNTIFS('JOBS'!$E$5:$E$1504,B25,'JOBS'!$O$5:$O$1504,"Completed")) | N25: =IF(B25="","",IF(_xlfn.MAXIFS('JOBS'!$B$5:$B$1504,'JOBS'!$E$5:$E$1504,B25,'JOBS'!$O$5:$O$1504,"Completed")=0,"",_xlfn.MAXIFS('JOBS'!$B$5:$B$1504,'JOBS'!$E$5:$E$1504,B25,'JOBS'!$O$5:$O$1504,"Completed"))) | O25: =IF(B25="","",IFERROR(AVERAGEIFS('JOBS'!$L$5:$L$1504,'JOBS'!$E$5:$E$1504,B25,'JOBS'!$O$5:$O$1504,"Completed"),""))
A26: P-022 | B26: 952 Poplar Trail, Sampletown | C26: Quinn Ashworth | D26: Sampletown | E26: Condo | F26: 1700 | G26: 3 | H26: 2 | J26: Customer home | K26: Street | L26: Shoes off at entry | M26: =IF(B26="","",COUNTIFS('JOBS'!$E$5:$E$1504,B26,'JOBS'!$O$5:$O$1504,"Completed")) | N26: =IF(B26="","",IF(_xlfn.MAXIFS('JOBS'!$B$5:$B$1504,'JOBS'!$E$5:$E$1504,B26,'JOBS'!$O$5:$O$1504,"Completed")=0,"",_xlfn.MAXIFS('JOBS'!$B$5:$B$1504,'JOBS'!$E$5:$E$1504,B26,'JOBS'!$O$5:$O$1504,"Completed"))) | O26: =IF(B26="","",IFERROR(AVERAGEIFS('JOBS'!$L$5:$L$1504,'JOBS'!$E$5:$E$1504,B26,'JOBS'!$O$5:$O$1504,"Completed"),""))
A27: P-023 | B27: 738 Cedar Court, North Sampletown | C27: Brightside Dental Studio (sample) | D27: North Sampletown | E27: Medical/Dental | F27: 2400 | G27: 0 | H27: 2 | J27: Customer home | K27: Driveway | L27: After-hours only | M27: =IF(B27="","",COUNTIFS('JOBS'!$E$5:$E$1504,B27,'JOBS'!$O$5:$O$1504,"Completed")) | N27: =IF(B27="","",IF(_xlfn.MAXIFS('JOBS'!$B$5:$B$1504,'JOBS'!$E$5:$E$1504,B27,'JOBS'!$O$5:$O$1504,"Completed")=0,"",_xlfn.MAXIFS('JOBS'!$B$5:$B$1504,'JOBS'!$E$5:$E$1504,B27,'JOBS'!$O$5:$O$1504,"Completed"))) | O27: =IF(B27="","",IFERROR(AVERAGEIFS('JOBS'!$L$5:$L$1504,'JOBS'!$E$5:$E$1504,B27,'JOBS'!$O$5:$O$1504,"Completed"),""))
A28: P-024 | B28: 957 Hawthorn Road, North Sampletown | C28: Oakview Office Suites (sample) | D28: North Sampletown | E28: Office | F28: 5200 | G28: 0 | H28: 4 | J28: Key under office management | K28: Garage apron | L28: After-hours only | M28: =IF(B28="","",COUNTIFS('JOBS'!$E$5:$E$1504,B28,'JOBS'!$O$5:$O$1504,"Completed")) | N28: =IF(B28="","",IF(_xlfn.MAXIFS('JOBS'!$B$5:$B$1504,'JOBS'!$E$5:$E$1504,B28,'JOBS'!$O$5:$O$1504,"Completed")=0,"",_xlfn.MAXIFS('JOBS'!$B$5:$B$1504,'JOBS'!$E$5:$E$1504,B28,'JOBS'!$O$5:$O$1504,"Completed"))) | O28: =IF(B28="","",IFERROR(AVERAGEIFS('JOBS'!$L$5:$L$1504,'JOBS'!$E$5:$E$1504,B28,'JOBS'!$O$5:$O$1504,"Completed"),""))
A29: P-025 | B29: 338 Cedar Court, Sampletown | C29: Harbor Yoga Loft (sample) | D29: Sampletown | E29: Office | F29: 1800 | G29: 0 | H29: 2 | J29: Garage keypad (code in office file) | K29: Driveway | L29: After-hours only | M29: =IF(B29="","",COUNTIFS('JOBS'!$E$5:$E$1504,B29,'JOBS'!$O$5:$O$1504,"Completed")) | N29: =IF(B29="","",IF(_xlfn.MAXIFS('JOBS'!$B$5:$B$1504,'JOBS'!$E$5:$E$1504,B29,'JOBS'!$O$5:$O$1504,"Completed")=0,"",_xlfn.MAXIFS('JOBS'!$B$5:$B$1504,'JOBS'!$E$5:$E$1504,B29,'JOBS'!$O$5:$O$1504,"Completed"))) | O29: =IF(B29="","",IFERROR(AVERAGEIFS('JOBS'!$L$5:$L$1504,'JOBS'!$E$5:$E$1504,B29,'JOBS'!$O$5:$O$1504,"Completed"),""))
A30: P-026 | B30: 666 Juniper Street, North Sampletown | C30: Dana Oakes | D30: North Sampletown | E30: Short-Term Rental | F30: 850 | G30: 1 | H30: 1 | J30: Key under office management | K30: Street | L30: Photo each room after reset | M30: =IF(B30="","",COUNTIFS('JOBS'!$E$5:$E$1504,B30,'JOBS'!$O$5:$O$1504,"Completed")) | N30: =IF(B30="","",IF(_xlfn.MAXIFS('JOBS'!$B$5:$B$1504,'JOBS'!$E$5:$E$1504,B30,'JOBS'!$O$5:$O$1504,"Completed")=0,"",_xlfn.MAXIFS('JOBS'!$B$5:$B$1504,'JOBS'!$E$5:$E$1504,B30,'JOBS'!$O$5:$O$1504,"Completed"))) | O30: =IF(B30="","",IFERROR(AVERAGEIFS('JOBS'!$L$5:$L$1504,'JOBS'!$E$5:$E$1504,B30,'JOBS'!$O$5:$O$1504,"Completed"),""))
A31: P-027 | B31: 654 Willow Way, North Sampletown | C31: Blake Oakes | D31: North Sampletown | E31: Short-Term Rental | F31: 850 | G31: 1 | H31: 1 | J31: Lockbox code on file | K31: Visitor lot | L31: Photo each room after reset | M31: =IF(B31="","",COUNTIFS('JOBS'!$E$5:$E$1504,B31,'JOBS'!$O$5:$O$1504,"Completed")) | N31: =IF(B31="","",IF(_xlfn.MAXIFS('JOBS'!$B$5:$B$1504,'JOBS'!$E$5:$E$1504,B31,'JOBS'!$O$5:$O$1504,"Completed")=0,"",_xlfn.MAXIFS('JOBS'!$B$5:$B$1504,'JOBS'!$E$5:$E$1504,B31,'JOBS'!$O$5:$O$1504,"Completed"))) | O31: =IF(B31="","",IFERROR(AVERAGEIFS('JOBS'!$L$5:$L$1504,'JOBS'!$E$5:$E$1504,B31,'JOBS'!$O$5:$O$1504,"Completed"),""))
A32: P-028 | B32: 192 Birch Lane, North Sampletown | C32: Emerson Holloway | D32: North Sampletown | E32: Short-Term Rental | F32: 1200 | G32: 2 | H32: 1 | J32: Smart lock — code sent day before | K32: Driveway | L32: Photo each room after reset | M32: =IF(B32="","",COUNTIFS('JOBS'!$E$5:$E$1504,B32,'JOBS'!$O$5:$O$1504,"Completed")) | N32: =IF(B32="","",IF(_xlfn.MAXIFS('JOBS'!$B$5:$B$1504,'JOBS'!$E$5:$E$1504,B32,'JOBS'!$O$5:$O$1504,"Completed")=0,"",_xlfn.MAXIFS('JOBS'!$B$5:$B$1504,'JOBS'!$E$5:$E$1504,B32,'JOBS'!$O$5:$O$1504,"Completed"))) | O32: =IF(B32="","",IFERROR(AVERAGEIFS('JOBS'!$L$5:$L$1504,'JOBS'!$E$5:$E$1504,B32,'JOBS'!$O$5:$O$1504,"Completed"),""))
A33: P-029 | B33: 412 Linden Place, Sampletown | C33: Parker Lockhart | D33: Sampletown | E33: Short-Term Rental | F33: 1000 | G33: 2 | H33: 1 | J33: Key under office management | K33: Garage apron | L33: Photo each room after reset | M33: =IF(B33="","",COUNTIFS('JOBS'!$E$5:$E$1504,B33,'JOBS'!$O$5:$O$1504,"Completed")) | N33: =IF(B33="","",IF(_xlfn.MAXIFS('JOBS'!$B$5:$B$1504,'JOBS'!$E$5:$E$1504,B33,'JOBS'!$O$5:$O$1504,"Completed")=0,"",_xlfn.MAXIFS('JOBS'!$B$5:$B$1504,'JOBS'!$E$5:$E$1504,B33,'JOBS'!$O$5:$O$1504,"Completed"))) | O33: =IF(B33="","",IFERROR(AVERAGEIFS('JOBS'!$L$5:$L$1504,'JOBS'!$E$5:$E$1504,B33,'JOBS'!$O$5:$O$1504,"Completed"),""))
A34: P-030 | B34: 211 Birch Lane, North Sampletown | C34: Crescent Property Group (sample) | D34: North Sampletown | E34: Apartment | F34: 900 | G34: 2 | H34: 1 | J34: Smart lock — code sent day before | K34: Visitor lot | M34: =IF(B34="","",COUNTIFS('JOBS'!$E$5:$E$1504,B34,'JOBS'!$O$5:$O$1504,"Completed")) | N34: =IF(B34="","",IF(_xlfn.MAXIFS('JOBS'!$B$5:$B$1504,'JOBS'!$E$5:$E$1504,B34,'JOBS'!$O$5:$O$1504,"Completed")=0,"",_xlfn.MAXIFS('JOBS'!$B$5:$B$1504,'JOBS'!$E$5:$E$1504,B34,'JOBS'!$O$5:$O$1504,"Completed"))) | O34: =IF(B34="","",IFERROR(AVERAGEIFS('JOBS'!$L$5:$L$1504,'JOBS'!$E$5:$E$1504,B34,'JOBS'!$O$5:$O$1504,"Completed"),""))
A35: P-031 | B35: 484 Poplar Trail, Lakeview (fictional) | C35: Crescent Property Group (sample) | D35: Lakeview (fictional) | E35: Apartment | F35: 1150 | G35: 2 | H35: 2 | J35: Customer home | K35: Driveway | M35: =IF(B35="","",COUNTIFS('JOBS'!$E$5:$E$1504,B35,'JOBS'!$O$5:$O$1504,"Completed")) | N35: =IF(B35="","",IF(_xlfn.MAXIFS('JOBS'!$B$5:$B$1504,'JOBS'!$E$5:$E$1504,B35,'JOBS'!$O$5:$O$1504,"Completed")=0,"",_xlfn.MAXIFS('JOBS'!$B$5:$B$1504,'JOBS'!$E$5:$E$1504,B35,'JOBS'!$O$5:$O$1504,"Completed"))) | O35: =IF(B35="","",IFERROR(AVERAGEIFS('JOBS'!$L$5:$L$1504,'JOBS'!$E$5:$E$1504,B35,'JOBS'!$O$5:$O$1504,"Completed"),""))
A36: P-032 | B36: 749 Willow Way, Sampletown | C36: Crescent Property Group (sample) | D36: Sampletown | E36: Apartment | F36: 1400 | G36: 3 | H36: 2 | J36: Customer home | K36: Garage apron | M36: =IF(B36="","",COUNTIFS('JOBS'!$E$5:$E$1504,B36,'JOBS'!$O$5:$O$1504,"Completed")) | N36: =IF(B36="","",IF(_xlfn.MAXIFS('JOBS'!$B$5:$B$1504,'JOBS'!$E$5:$E$1504,B36,'JOBS'!$O$5:$O$1504,"Completed")=0,"",_xlfn.MAXIFS('JOBS'!$B$5:$B$1504,'JOBS'!$E$5:$E$1504,B36,'JOBS'!$O$5:$O$1504,"Completed"))) | O36: =IF(B36="","",IFERROR(AVERAGEIFS('JOBS'!$L$5:$L$1504,'JOBS'!$E$5:$E$1504,B36,'JOBS'!$O$5:$O$1504,"Completed"),""))
A37: P-033 | M37: =IF(B37="","",COUNTIFS('JOBS'!$E$5:$E$1504,B37,'JOBS'!$O$5:$O$1504,"Completed")) | N37: =IF(B37="","",IF(_xlfn.MAXIFS('JOBS'!$B$5:$B$1504,'JOBS'!$E$5:$E$1504,B37,'JOBS'!$O$5:$O$1504,"Completed")=0,"",_xlfn.MAXIFS('JOBS'!$B$5:$B$1504,'JOBS'!$E$5:$E$1504,B37,'JOBS'!$O$5:$O$1504,"Completed"))) | O37: =IF(B37="","",IFERROR(AVERAGEIFS('JOBS'!$L$5:$L$1504,'JOBS'!$E$5:$E$1504,B37,'JOBS'!$O$5:$O$1504,"Completed"),""))
A38: P-034 | M38: =IF(B38="","",COUNTIFS('JOBS'!$E$5:$E$1504,B38,'JOBS'!$O$5:$O$1504,"Completed")) | N38: =IF(B38="","",IF(_xlfn.MAXIFS('JOBS'!$B$5:$B$1504,'JOBS'!$E$5:$E$1504,B38,'JOBS'!$O$5:$O$1504,"Completed")=0,"",_xlfn.MAXIFS('JOBS'!$B$5:$B$1504,'JOBS'!$E$5:$E$1504,B38,'JOBS'!$O$5:$O$1504,"Completed"))) | O38: =IF(B38="","",IFERROR(AVERAGEIFS('JOBS'!$L$5:$L$1504,'JOBS'!$E$5:$E$1504,B38,'JOBS'!$O$5:$O$1504,"Completed"),""))
A39: P-035 | M39: =IF(B39="","",COUNTIFS('JOBS'!$E$5:$E$1504,B39,'JOBS'!$O$5:$O$1504,"Completed")) | N39: =IF(B39="","",IF(_xlfn.MAXIFS('JOBS'!$B$5:$B$1504,'JOBS'!$E$5:$E$1504,B39,'JOBS'!$O$5:$O$1504,"Completed")=0,"",_xlfn.MAXIFS('JOBS'!$B$5:$B$1504,'JOBS'!$E$5:$E$1504,B39,'JOBS'!$O$5:$O$1504,"Completed"))) | O39: =IF(B39="","",IFERROR(AVERAGEIFS('JOBS'!$L$5:$L$1504,'JOBS'!$E$5:$E$1504,B39,'JOBS'!$O$5:$O$1504,"Completed"),""))
A40: P-036 | M40: =IF(B40="","",COUNTIFS('JOBS'!$E$5:$E$1504,B40,'JOBS'!$O$5:$O$1504,"Completed")) | N40: =IF(B40="","",IF(_xlfn.MAXIFS('JOBS'!$B$5:$B$1504,'JOBS'!$E$5:$E$1504,B40,'JOBS'!$O$5:$O$1504,"Completed")=0,"",_xlfn.MAXIFS('JOBS'!$B$5:$B$1504,'JOBS'!$E$5:$E$1504,B40,'JOBS'!$O$5:$O$1504,"Completed"))) | O40: =IF(B40="","",IFERROR(AVERAGEIFS('JOBS'!$L$5:$L$1504,'JOBS'!$E$5:$E$1504,B40,'JOBS'!$O$5:$O$1504,"Completed"),""))
A41: P-037 | M41: =IF(B41="","",COUNTIFS('JOBS'!$E$5:$E$1504,B41,'JOBS'!$O$5:$O$1504,"Completed")) | N41: =IF(B41="","",IF(_xlfn.MAXIFS('JOBS'!$B$5:$B$1504,'JOBS'!$E$5:$E$1504,B41,'JOBS'!$O$5:$O$1504,"Completed")=0,"",_xlfn.MAXIFS('JOBS'!$B$5:$B$1504,'JOBS'!$E$5:$E$1504,B41,'JOBS'!$O$5:$O$1504,"Completed"))) | O41: =IF(B41="","",IFERROR(AVERAGEIFS('JOBS'!$L$5:$L$1504,'JOBS'!$E$5:$E$1504,B41,'JOBS'!$O$5:$O$1504,"Completed"),""))
A42: P-038 | M42: =IF(B42="","",COUNTIFS('JOBS'!$E$5:$E$1504,B42,'JOBS'!$O$5:$O$1504,"Completed")) | N42: =IF(B42="","",IF(_xlfn.MAXIFS('JOBS'!$B$5:$B$1504,'JOBS'!$E$5:$E$1504,B42,'JOBS'!$O$5:$O$1504,"Completed")=0,"",_xlfn.MAXIFS('JOBS'!$B$5:$B$1504,'JOBS'!$E$5:$E$1504,B42,'JOBS'!$O$5:$O$1504,"Completed"))) | O42: =IF(B42="","",IFERROR(AVERAGEIFS('JOBS'!$L$5:$L$1504,'JOBS'!$E$5:$E$1504,B42,'JOBS'!$O$5:$O$1504,"Completed"),""))
A43: P-039 | M43: =IF(B43="","",COUNTIFS('JOBS'!$E$5:$E$1504,B43,'JOBS'!$O$5:$O$1504,"Completed")) | N43: =IF(B43="","",IF(_xlfn.MAXIFS('JOBS'!$B$5:$B$1504,'JOBS'!$E$5:$E$1504,B43,'JOBS'!$O$5:$O$1504,"Completed")=0,"",_xlfn.MAXIFS('JOBS'!$B$5:$B$1504,'JOBS'!$E$5:$E$1504,B43,'JOBS'!$O$5:$O$1504,"Completed"))) | O43: =IF(B43="","",IFERROR(AVERAGEIFS('JOBS'!$L$5:$L$1504,'JOBS'!$E$5:$E$1504,B43,'JOBS'!$O$5:$O$1504,"Completed"),""))
A44: P-040 | M44: =IF(B44="","",COUNTIFS('JOBS'!$E$5:$E$1504,B44,'JOBS'!$O$5:$O$1504,"Completed")) | N44: =IF(B44="","",IF(_xlfn.MAXIFS('JOBS'!$B$5:$B$1504,'JOBS'!$E$5:$E$1504,B44,'JOBS'!$O$5:$O$1504,"Completed")=0,"",_xlfn.MAXIFS('JOBS'!$B$5:$B$1504,'JOBS'!$E$5:$E$1504,B44,'JOBS'!$O$5:$O$1504,"Completed"))) | O44: =IF(B44="","",IFERROR(AVERAGEIFS('JOBS'!$L$5:$L$1504,'JOBS'!$E$5:$E$1504,B44,'JOBS'!$O$5:$O$1504,"Completed"),""))
A45: P-041 | M45: =IF(B45="","",COUNTIFS('JOBS'!$E$5:$E$1504,B45,'JOBS'!$O$5:$O$1504,"Completed")) | N45: =IF(B45="","",IF(_xlfn.MAXIFS('JOBS'!$B$5:$B$1504,'JOBS'!$E$5:$E$1504,B45,'JOBS'!$O$5:$O$1504,"Completed")=0,"",_xlfn.MAXIFS('JOBS'!$B$5:$B$1504,'JOBS'!$E$5:$E$1504,B45,'JOBS'!$O$5:$O$1504,"Completed"))) | O45: =IF(B45="","",IFERROR(AVERAGEIFS('JOBS'!$L$5:$L$1504,'JOBS'!$E$5:$E$1504,B45,'JOBS'!$O$5:$O$1504,"Completed"),""))
A46: P-042 | M46: =IF(B46="","",COUNTIFS('JOBS'!$E$5:$E$1504,B46,'JOBS'!$O$5:$O$1504,"Completed")) | N46: =IF(B46="","",IF(_xlfn.MAXIFS('JOBS'!$B$5:$B$1504,'JOBS'!$E$5:$E$1504,B46,'JOBS'!$O$5:$O$1504,"Completed")=0,"",_xlfn.MAXIFS('JOBS'!$B$5:$B$1504,'JOBS'!$E$5:$E$1504,B46,'JOBS'!$O$5:$O$1504,"Completed"))) | O46: =IF(B46="","",IFERROR(AVERAGEIFS('JOBS'!$L$5:$L$1504,'JOBS'!$E$5:$E$1504,B46,'JOBS'!$O$5:$O$1504,"Completed"),""))
A47: P-043 | M47: =IF(B47="","",COUNTIFS('JOBS'!$E$5:$E$1504,B47,'JOBS'!$O$5:$O$1504,"Completed")) | N47: =IF(B47="","",IF(_xlfn.MAXIFS('JOBS'!$B$5:$B$1504,'JOBS'!$E$5:$E$1504,B47,'JOBS'!$O$5:$O$1504,"Completed")=0,"",_xlfn.MAXIFS('JOBS'!$B$5:$B$1504,'JOBS'!$E$5:$E$1504,B47,'JOBS'!$O$5:$O$1504,"Completed"))) | O47: =IF(B47="","",IFERROR(AVERAGEIFS('JOBS'!$L$5:$L$1504,'JOBS'!$E$5:$E$1504,B47,'JOBS'!$O$5:$O$1504,"Completed"),""))
A48: P-044 | M48: =IF(B48="","",COUNTIFS('JOBS'!$E$5:$E$1504,B48,'JOBS'!$O$5:$O$1504,"Completed")) | N48: =IF(B48="","",IF(_xlfn.MAXIFS('JOBS'!$B$5:$B$1504,'JOBS'!$E$5:$E$1504,B48,'JOBS'!$O$5:$O$1504,"Completed")=0,"",_xlfn.MAXIFS('JOBS'!$B$5:$B$1504,'JOBS'!$E$5:$E$1504,B48,'JOBS'!$O$5:$O$1504,"Completed"))) | O48: =IF(B48="","",IFERROR(AVERAGEIFS('JOBS'!$L$5:$L$1504,'JOBS'!$E$5:$E$1504,B48,'JOBS'!$O$5:$O$1504,"Completed"),""))
... A404: P-400 | M404: =IF(B404="","",COUNTIFS('JOBS'!$E$5:$E$1504,B404,'JOBS'!$O$5:$O$1504,"Completed")) | N404: =IF(B404="","",IF(_xlfn.MAXIFS('JOBS'!$B$5:$B$1504,'JOBS'!$E$5:$E$1504,B404,'JOBS'!$O$5:$O$1504,"Completed")=0,"",_xlfn.MAXIFS('JOBS'!$B$5:$B$1504,'JOBS'!$E$5:$E$1504,B404,'JOBS'!$O$5:$O$1504,"Completed"))) | O404: =IF(B404="","",IFERROR(AVERAGEIFS('JOBS'!$L$5:$L$1504,'JOBS'!$E$5:$E$1504,B404,'JOBS'!$O$5:$O$1504,"Completed"),""))

Sheet QUOTE BUILDER
A1: QUOTE BUILDER + PROFIT ENGINE
A2: Enter the job details on the left. The right side shows the price, your costs, gross profit and margin. All assumptions come from PRICING and SETTINGS and can be overridden here. Results are estimates from YOUR assumptions — not market rates.
A3: ← Start Here | B3: Dashboard →
A5: JOB DETAILS | F5: RESULTS (automatic)
A6: Quote date | B6: 46295 | F6: TIME
A7: Customer name | B7: Avery Collins | F7: Estimated labor hours (model, before add-ons) | G7: =IFERROR(ROUND(($B$10/INDEX('PRICING'!$C$7:$C$16,MATCH($B$9,'PRICING'!$A$7:$A$16,0))+$B$11*INDEX('PRICING'!$D$7:$D$16,MATCH($B$9,'PRICING'!$A$7:$A$16,0))/60+$B$12*INDEX('PRICING'!$E$7:$E$16,MATCH($B$9,'PRICING'!$A$7:$A$16,0))/60+INDEX('PRICING'!$F$7:$F$16,MATCH($B$9,'PRICING'!$A$7:$A$16,0))/60)*IFERROR(INDEX('PRICING'!$B$20:$B$24,MATCH($B$13,'PRICING'!$A$20:$A$24,0)),1),2),0)
A8: Property address | B8: 14 Birch Lane, Sampletown | F8: Labor hours used (incl. add-ons) | G8: =IF(N(B16)>0,B16,G7)+SUM(D25:D30)/60
A9: Cleaning type | B9: Deep Clean | F9: Time on site with your crew (hours) | G9: =IFERROR(G8/MAX(1,N(B15)),0)
A10: Square footage | B10: 2200 | F10: PRICE
A11: Bedrooms | B11: 3 | F11: Billing rate used ($ per labor hour) | G11: =IF(N(B17)>0,B17,IFERROR(INDEX('PRICING'!$B$7:$B$16,MATCH($B$9,'PRICING'!$A$7:$A$16,0)),0))
A12: Bathrooms | B12: 2.5 | F12: Base service price | G12: =IF(G7=0,0,MAX(MinJob,ROUND(IF(N(B16)>0,B16,G7)*G11,2)))
A13: Property condition | B13: Average | F13: Frequency discount | G13: =-ROUND(G12*IFERROR(INDEX('PRICING'!$B$28:$B$33,MATCH(B14,'PRICING'!$A$28:$A$33,0)),0),2)
A14: Frequency | B14: One-time | F14: Add-ons | G14: =SUM(C25:C30)
A15: Number of workers | B15: 2 | F15: Manual discount | G15: =-N(B33)
A16: Labor hours override (optional) | F16: PRICE BEFORE TAX | G16: =MAX(0,G12+G13+G14+G15)
A17: Billing rate per labor hour override (optional) | F17: Sales tax | G17: =ROUND(G16*N(B34),2)
A18: Worker pay rate ($/hr) | B18: =PayRate | F18: CUSTOMER TOTAL | G18: =G16+G17
A19: Supplies cost override (optional) | F19: DIRECT COSTS
A20: Round-trip distance (miles) | B20: 12 | F20: Labor cost (hours × pay × (1 + extra labor %)) | G20: =ROUND(G8*N(B18)*(1+Burden),2)
A21: Paid travel time per worker (minutes) | B21: =TravelMin | F21: Paid travel time | G21: =ROUND(N(B21)/60*MAX(1,N(B15))*N(B18)*(1+Burden),2)
A22: Formulas in B18 and B21 pull your SETTINGS defaults — type over them to override for this quote. | F22: Vehicle cost (miles × your rate) | G22: =ROUND(N(B20)*MileRate,2)
A23: ADD-ONS | F23: Supplies | G23: =IF(B19<>"",N(B19),ROUND(G8*SupHr*IFERROR(INDEX('PRICING'!$G$7:$G$16,MATCH($B$9,'PRICING'!$A$7:$A$16,0)),1),2))
A24: Add-on | B24: Quantity | C24: Price | D24: Minutes | F24: Add-on direct costs | G24: =IF(OR(A25="",N(B25)=0),0,B25*IFERROR(INDEX('PRICING'!$D$37:$D$51,MATCH(A25,'PRICING'!$A$37:$A$51,0)),0))+IF(OR(A26="",N(B26)=0),0,B26*IFERROR(INDEX('PRICING'!$D$37:$D$51,MATCH(A26,'PRICING'!$A$37:$A$51,0)),0))+IF(OR(A27="",N(B27)=0),0,B27*IFERROR(INDEX('PRICING'!$D$37:$D$51,MATCH(A27,'PRICING'!$A$37:$A$51,0)),0))+IF(OR(A28="",N(B28)=0),0,B28*IFERROR(INDEX('PRICING'!$D$37:$D$51,MATCH(A28,'PRICING'!$A$37:$A$51,0)),0))+IF(OR(A29="",N(B29)=0),0,B29*IFERROR(INDEX('PRICING'!$D$37:$D$51,MATCH(A29,'PRICING'!$A$37:$A$51,0)),0))+IF(OR(A30="",N(B30)=0),0,B30*IFERROR(INDEX('PRICING'!$D$37:$D$51,MATCH(A30,'PRICING'!$A$37:$A$51,0)),0))
A25: Inside oven | B25: 1 | C25: =IF(OR(A25="",N(B25)=0),0,B25*IFERROR(INDEX('PRICING'!$B$37:$B$51,MATCH(A25,'PRICING'!$A$37:$A$51,0)),0)) | D25: =IF(OR(A25="",N(B25)=0),0,B25*IFERROR(INDEX('PRICING'!$C$37:$C$51,MATCH(A25,'PRICING'!$A$37:$A$51,0)),0)) | F25: Payment processing fee | G25: =IF(B35="Yes",ROUND(G18*FeePct,2),0)
A26: Inside refrigerator | B26: 1 | C26: =IF(OR(A26="",N(B26)=0),0,B26*IFERROR(INDEX('PRICING'!$B$37:$B$51,MATCH(A26,'PRICING'!$A$37:$A$51,0)),0)) | D26: =IF(OR(A26="",N(B26)=0),0,B26*IFERROR(INDEX('PRICING'!$C$37:$C$51,MATCH(A26,'PRICING'!$A$37:$A$51,0)),0)) | F26: TOTAL DIRECT COSTS | G26: =SUM(G20:G25)
A27: Interior windows (per 10) | B27: 1 | C27: =IF(OR(A27="",N(B27)=0),0,B27*IFERROR(INDEX('PRICING'!$B$37:$B$51,MATCH(A27,'PRICING'!$A$37:$A$51,0)),0)) | D27: =IF(OR(A27="",N(B27)=0),0,B27*IFERROR(INDEX('PRICING'!$C$37:$C$51,MATCH(A27,'PRICING'!$A$37:$A$51,0)),0)) | F27: PROFIT
C28: =IF(OR(A28="",N(B28)=0),0,B28*IFERROR(INDEX('PRICING'!$B$37:$B$51,MATCH(A28,'PRICING'!$A$37:$A$51,0)),0)) | D28: =IF(OR(A28="",N(B28)=0),0,B28*IFERROR(INDEX('PRICING'!$C$37:$C$51,MATCH(A28,'PRICING'!$A$37:$A$51,0)),0)) | F28: GROSS PROFIT | G28: =G16-G26
C29: =IF(OR(A29="",N(B29)=0),0,B29*IFERROR(INDEX('PRICING'!$B$37:$B$51,MATCH(A29,'PRICING'!$A$37:$A$51,0)),0)) | D29: =IF(OR(A29="",N(B29)=0),0,B29*IFERROR(INDEX('PRICING'!$C$37:$C$51,MATCH(A29,'PRICING'!$A$37:$A$51,0)),0)) | F29: GROSS MARGIN % | G29: =IF(G16=0,0,G28/G16)
C30: =IF(OR(A30="",N(B30)=0),0,B30*IFERROR(INDEX('PRICING'!$B$37:$B$51,MATCH(A30,'PRICING'!$A$37:$A$51,0)),0)) | D30: =IF(OR(A30="",N(B30)=0),0,B30*IFERROR(INDEX('PRICING'!$C$37:$C$51,MATCH(A30,'PRICING'!$A$37:$A$51,0)),0)) | F30: Revenue per labor hour | G30: =IF(G8=0,0,G16/G8)
F31: Gross profit per labor hour | G31: =IF(G8=0,0,G28/G8)
A32: DISCOUNT & TAX | F32: Break-even price (before tax) | G32: =IFERROR(ROUND((G26-G25)/(1-IF(B35="Yes",FeePct*(1+N(B34)),0)),2),0)
A33: Manual discount ($) | B33: 0 | F33: Price needed for your target margin | G33: =IFERROR(ROUND((G26-G25)/(1-TargetMargin-IF(B35="Yes",FeePct*(1+N(B34)),0)),2),0)
A34: Sales tax % (only if it applies to you) | B34: =TaxDefault | F34: Monthly value if recurring | G34: =IFERROR(G16*INDEX('PRICING'!$D$28:$D$33,MATCH(B14,'PRICING'!$A$28:$A$33,0)),0)
A35: Customer pays by card/online (adds fee to costs)? | B35: Yes | F35: Margin check | G35: =IF(G16=0,"Enter job details",IF(G28<0,"Below break-even — raise price or reduce hours",IF(G29<TargetMargin,"Below your target margin","Meets your target margin")))
F36: Overhead share (labor hours × SETTINGS rate) | G36: =ROUND(G8*OverheadHr,2)
F37: Est. profit after overhead share | G37: =G28-G36
A38: QUOTE SUMMARY — copy into your quote, the LEADS sheet, or AI Workflow 02
A39: =IF(G16=0,"Enter job details above.","Quote for "&IF(B7="","[customer]",B7)&" at "&IF(B8="","[address]",B8)&": "&B9&", "&TEXT(B10,"#,##0")&" sq ft, "&B11&" bd / "&B12&" ba, "&LOWER(B13)&" condition, "&LOWER(B14)&". "&"Crew of "&B15&", about "&TEXT(G9,"0.0")&" hours on site. Add-ons: "&IF(G14=0,"none",TEXT(G14,"$#,##0.00"))&". "&"Price before tax "&TEXT(G16,"$#,##0.00")&IF(G17>0,", tax "&TEXT(G17,"$#,##0.00"),"")&", total "&TEXT(G18,"$#,##0.00")&".")
A43: How to use: price shown is what YOUR assumptions produce. Compare it to what you know about your local market, then decide. Copy the price-before-tax into the LEADS Quote Value column when you send the quote.

Sheet PRICING
A1: PRICING CALCULATOR
A2: Your pricing assumptions. Every number is an EXAMPLE starting point — replace them with your own. These are not market rates or recommendations.
A3: ← Start Here | B3: Dashboard →
A5: 1. CLEANING TYPES — how long each type takes and what you bill per labor hour
A6: Cleaning Type | B6: Billing Rate per Labor Hr ($) | C6: Sq Ft Cleaned per Labor Hr | D6: Minutes per Bedroom | E6: Minutes per Bathroom | F6: Setup Minutes per Job | G6: Supplies Multiplier | H6: Example: 2,000 sq ft, 3 bd / 2 ba (hrs) | I6: Notes
A7: Standard Clean | B7: 50 | C7: 800 | D7: 5 | E7: 15 | F7: 10 | G7: 1 | H7: =IF(A7="","",IFERROR(ROUND((2000/INDEX('PRICING'!$C$7:$C$16,MATCH(A7,'PRICING'!$A$7:$A$16,0))+3*INDEX('PRICING'!$D$7:$D$16,MATCH(A7,'PRICING'!$A$7:$A$16,0))/60+2*INDEX('PRICING'!$E$7:$E$16,MATCH(A7,'PRICING'!$A$7:$A$16,0))/60+INDEX('PRICING'!$F$7:$F$16,MATCH(A7,'PRICING'!$A$7:$A$16,0))/60),2),"")) | I7: Routine maintenance clean
A8: Deep Clean | B8: 55 | C8: 400 | D8: 10 | E8: 30 | F8: 15 | G8: 1.5 | H8: =IF(A8="","",IFERROR(ROUND((2000/INDEX('PRICING'!$C$7:$C$16,MATCH(A8,'PRICING'!$A$7:$A$16,0))+3*INDEX('PRICING'!$D$7:$D$16,MATCH(A8,'PRICING'!$A$7:$A$16,0))/60+2*INDEX('PRICING'!$E$7:$E$16,MATCH(A8,'PRICING'!$A$7:$A$16,0))/60+INDEX('PRICING'!$F$7:$F$16,MATCH(A8,'PRICING'!$A$7:$A$16,0))/60),2),"")) | I8: Detail work: baseboards, buildup, fixtures
A9: Move-In/Move-Out | B9: 55 | C9: 350 | D9: 15 | E9: 40 | F9: 20 | G9: 1.6 | H9: =IF(A9="","",IFERROR(ROUND((2000/INDEX('PRICING'!$C$7:$C$16,MATCH(A9,'PRICING'!$A$7:$A$16,0))+3*INDEX('PRICING'!$D$7:$D$16,MATCH(A9,'PRICING'!$A$7:$A$16,0))/60+2*INDEX('PRICING'!$E$7:$E$16,MATCH(A9,'PRICING'!$A$7:$A$16,0))/60+INDEX('PRICING'!$F$7:$F$16,MATCH(A9,'PRICING'!$A$7:$A$16,0))/60),2),"")) | I9: Empty home, inside cabinets & appliances as add-ons
A10: Airbnb Turnover | B10: 50 | C10: 900 | D10: 10 | E10: 20 | F10: 15 | G10: 1.2 | H10: =IF(A10="","",IFERROR(ROUND((2000/INDEX('PRICING'!$C$7:$C$16,MATCH(A10,'PRICING'!$A$7:$A$16,0))+3*INDEX('PRICING'!$D$7:$D$16,MATCH(A10,'PRICING'!$A$7:$A$16,0))/60+2*INDEX('PRICING'!$E$7:$E$16,MATCH(A10,'PRICING'!$A$7:$A$16,0))/60+INDEX('PRICING'!$F$7:$F$16,MATCH(A10,'PRICING'!$A$7:$A$16,0))/60),2),"")) | I10: Reset + staging; laundry/restock as add-ons
A11: Commercial Clean | B11: 45 | C11: 2500 | D11: 0 | E11: 20 | F11: 15 | G11: 0.8 | H11: =IF(A11="","",IFERROR(ROUND((2000/INDEX('PRICING'!$C$7:$C$16,MATCH(A11,'PRICING'!$A$7:$A$16,0))+3*INDEX('PRICING'!$D$7:$D$16,MATCH(A11,'PRICING'!$A$7:$A$16,0))/60+2*INDEX('PRICING'!$E$7:$E$16,MATCH(A11,'PRICING'!$A$7:$A$16,0))/60+INDEX('PRICING'!$F$7:$F$16,MATCH(A11,'PRICING'!$A$7:$A$16,0))/60),2),"")) | I11: Use 'bathrooms' for restrooms; bedrooms = 0
H12: =IF(A12="","",IFERROR(ROUND((2000/INDEX('PRICING'!$C$7:$C$16,MATCH(A12,'PRICING'!$A$7:$A$16,0))+3*INDEX('PRICING'!$D$7:$D$16,MATCH(A12,'PRICING'!$A$7:$A$16,0))/60+2*INDEX('PRICING'!$E$7:$E$16,MATCH(A12,'PRICING'!$A$7:$A$16,0))/60+INDEX('PRICING'!$F$7:$F$16,MATCH(A12,'PRICING'!$A$7:$A$16,0))/60),2),""))
H13: =IF(A13="","",IFERROR(ROUND((2000/INDEX('PRICING'!$C$7:$C$16,MATCH(A13,'PRICING'!$A$7:$A$16,0))+3*INDEX('PRICING'!$D$7:$D$16,MATCH(A13,'PRICING'!$A$7:$A$16,0))/60+2*INDEX('PRICING'!$E$7:$E$16,MATCH(A13,'PRICING'!$A$7:$A$16,0))/60+INDEX('PRICING'!$F$7:$F$16,MATCH(A13,'PRICING'!$A$7:$A$16,0))/60),2),""))
H14: =IF(A14="","",IFERROR(ROUND((2000/INDEX('PRICING'!$C$7:$C$16,MATCH(A14,'PRICING'!$A$7:$A$16,0))+3*INDEX('PRICING'!$D$7:$D$16,MATCH(A14,'PRICING'!$A$7:$A$16,0))/60+2*INDEX('PRICING'!$E$7:$E$16,MATCH(A14,'PRICING'!$A$7:$A$16,0))/60+INDEX('PRICING'!$F$7:$F$16,MATCH(A14,'PRICING'!$A$7:$A$16,0))/60),2),""))
H15: =IF(A15="","",IFERROR(ROUND((2000/INDEX('PRICING'!$C$7:$C$16,MATCH(A15,'PRICING'!$A$7:$A$16,0))+3*INDEX('PRICING'!$D$7:$D$16,MATCH(A15,'PRICING'!$A$7:$A$16,0))/60+2*INDEX('PRICING'!$E$7:$E$16,MATCH(A15,'PRICING'!$A$7:$A$16,0))/60+INDEX('PRICING'!$F$7:$F$16,MATCH(A15,'PRICING'!$A$7:$A$16,0))/60),2),""))
H16: =IF(A16="","",IFERROR(ROUND((2000/INDEX('PRICING'!$C$7:$C$16,MATCH(A16,'PRICING'!$A$7:$A$16,0))+3*INDEX('PRICING'!$D$7:$D$16,MATCH(A16,'PRICING'!$A$7:$A$16,0))/60+2*INDEX('PRICING'!$E$7:$E$16,MATCH(A16,'PRICING'!$A$7:$A$16,0))/60+INDEX('PRICING'!$F$7:$F$16,MATCH(A16,'PRICING'!$A$7:$A$16,0))/60),2),""))
A17: Add your own service types in the blank rows (e.g., Post-Construction). They appear in every Service dropdown.
A18: 2. PROPERTY CONDITION — multiplies estimated time
A19: Condition | B19: Time Multiplier
A20: Light | B20: 0.9
A21: Average | B21: 1
A22: Heavy | B22: 1.25
A23: Very heavy | B23: 1.5
A26: 3. FREQUENCY — recurring discount and visit spacing
A27: Frequency | B27: Discount % | C27: Days Between Visits | D27: Visits per Month
A28: One-time | B28: 0 | C28: 0 | D28: 0
A29: Weekly | B29: 0.15 | C29: 7 | D29: 4.33
A30: Biweekly | B30: 0.1 | C30: 14 | D30: 2.17
A31: Every 3 weeks | B31: 0.07 | C31: 21 | D31: 1.44
A32: Every 4 weeks | B32: 0.05 | C32: 28 | D32: 1.08
A33: Monthly | B33: 0.05 | C33: 30 | D33: 1
A34: Keep 'One-time' in the first row. 'Monthly' visits are scheduled by calendar month.
A35: 4. ADD-ONS — price, time and direct cost per unit
A36: Add-On | B36: Price per Unit ($) | C36: Minutes per Unit | D36: Direct Cost per Unit ($)
A37: Inside oven | B37: 35 | C37: 30 | D37: 1
A38: Inside refrigerator | B38: 35 | C38: 30 | D38: 1
A39: Interior windows (per 10) | B39: 40 | C39: 45 | D39: 1
A40: Baseboards detail | B40: 30 | C40: 30 | D40: 0.5
A41: Inside cabinets | B41: 40 | C41: 45 | D41: 1
A42: Laundry (per load) | B42: 15 | C42: 10 | D42: 0.75
A43: Bed linen change (per bed) | B43: 10 | C43: 10 | D43: 0
A44: Balcony / patio | B44: 25 | C44: 20 | D44: 0.5
A45: Garage sweep | B45: 30 | C45: 25 | D45: 0.5
A46: Wall spot cleaning | B46: 25 | C46: 20 | D46: 0.5
A47: Restock supplies (STR) | B47: 15 | C47: 10 | D47: 0
A53: 5. RATE CARD — one-time base prices from your assumptions (before add-ons, discounts, tax)
A54: Condition for rate card | B54: Average | C54: Recurring frequency to compare | D54: Biweekly
A55: Sq Ft | B55: Bedrooms | C55: Bathrooms | D55: =A7 | E55: =A8 | F55: =A9 | G55: =A10 | H55: ="Standard at "&D54 | I55: Standard Monthly Value
A56: 800 | B56: 1 | C56: 1 | D56: =IFERROR(MAX(MinJob,ROUND(($A56/INDEX('PRICING'!$C$7:$C$16,MATCH(D$55,'PRICING'!$A$7:$A$16,0))+$B56*INDEX('PRICING'!$D$7:$D$16,MATCH(D$55,'PRICING'!$A$7:$A$16,0))/60+$C56*INDEX('PRICING'!$E$7:$E$16,MATCH(D$55,'PRICING'!$A$7:$A$16,0))/60+INDEX('PRICING'!$F$7:$F$16,MATCH(D$55,'PRICING'!$A$7:$A$16,0))/60)*IFERROR(INDEX('PRICING'!$B$20:$B$24,MATCH($B$54,'PRICING'!$A$20:$A$24,0)),1)*INDEX('PRICING'!$B$7:$B$16,MATCH(D$55,'PRICING'!$A$7:$A$16,0)),0)),"") | E56: =IFERROR(MAX(MinJob,ROUND(($A56/INDEX('PRICING'!$C$7:$C$16,MATCH(E$55,'PRICING'!$A$7:$A$16,0))+$B56*INDEX('PRICING'!$D$7:$D$16,MATCH(E$55,'PRICING'!$A$7:$A$16,0))/60+$C56*INDEX('PRICING'!$E$7:$E$16,MATCH(E$55,'PRICING'!$A$7:$A$16,0))/60+INDEX('PRICING'!$F$7:$F$16,MATCH(E$55,'PRICING'!$A$7:$A$16,0))/60)*IFERROR(INDEX('PRICING'!$B$20:$B$24,MATCH($B$54,'PRICING'!$A$20:$A$24,0)),1)*INDEX('PRICING'!$B$7:$B$16,MATCH(E$55,'PRICING'!$A$7:$A$16,0)),0)),"") | F56: =IFERROR(MAX(MinJob,ROUND(($A56/INDEX('PRICING'!$C$7:$C$16,MATCH(F$55,'PRICING'!$A$7:$A$16,0))+$B56*INDEX('PRICING'!$D$7:$D$16,MATCH(F$55,'PRICING'!$A$7:$A$16,0))/60+$C56*INDEX('PRICING'!$E$7:$E$16,MATCH(F$55,'PRICING'!$A$7:$A$16,0))/60+INDEX('PRICING'!$F$7:$F$16,MATCH(F$55,'PRICING'!$A$7:$A$16,0))/60)*IFERROR(INDEX('PRICING'!$B$20:$B$24,MATCH($B$54,'PRICING'!$A$20:$A$24,0)),1)*INDEX('PRICING'!$B$7:$B$16,MATCH(F$55,'PRICING'!$A$7:$A$16,0)),0)),"") | G56: =IFERROR(MAX(MinJob,ROUND(($A56/INDEX('PRICING'!$C$7:$C$16,MATCH(G$55,'PRICING'!$A$7:$A$16,0))+$B56*INDEX('PRICING'!$D$7:$D$16,MATCH(G$55,'PRICING'!$A$7:$A$16,0))/60+$C56*INDEX('PRICING'!$E$7:$E$16,MATCH(G$55,'PRICING'!$A$7:$A$16,0))/60+INDEX('PRICING'!$F$7:$F$16,MATCH(G$55,'PRICING'!$A$7:$A$16,0))/60)*IFERROR(INDEX('PRICING'!$B$20:$B$24,MATCH($B$54,'PRICING'!$A$20:$A$24,0)),1)*INDEX('PRICING'!$B$7:$B$16,MATCH(G$55,'PRICING'!$A$7:$A$16,0)),0)),"") | H56: =IFERROR(ROUND(D56*(1-INDEX('PRICING'!$B$28:$B$33,MATCH($D$54,'PRICING'!$A$28:$A$33,0))),0),"") | I56: =IFERROR(H56*INDEX('PRICING'!$D$28:$D$33,MATCH($D$54,'PRICING'!$A$28:$A$33,0)),"")
A57: 1000 | B57: 2 | C57: 1 | D57: =IFERROR(MAX(MinJob,ROUND(($A57/INDEX('PRICING'!$C$7:$C$16,MATCH(D$55,'PRICING'!$A$7:$A$16,0))+$B57*INDEX('PRICING'!$D$7:$D$16,MATCH(D$55,'PRICING'!$A$7:$A$16,0))/60+$C57*INDEX('PRICING'!$E$7:$E$16,MATCH(D$55,'PRICING'!$A$7:$A$16,0))/60+INDEX('PRICING'!$F$7:$F$16,MATCH(D$55,'PRICING'!$A$7:$A$16,0))/60)*IFERROR(INDEX('PRICING'!$B$20:$B$24,MATCH($B$54,'PRICING'!$A$20:$A$24,0)),1)*INDEX('PRICING'!$B$7:$B$16,MATCH(D$55,'PRICING'!$A$7:$A$16,0)),0)),"") | E57: =IFERROR(MAX(MinJob,ROUND(($A57/INDEX('PRICING'!$C$7:$C$16,MATCH(E$55,'PRICING'!$A$7:$A$16,0))+$B57*INDEX('PRICING'!$D$7:$D$16,MATCH(E$55,'PRICING'!$A$7:$A$16,0))/60+$C57*INDEX('PRICING'!$E$7:$E$16,MATCH(E$55,'PRICING'!$A$7:$A$16,0))/60+INDEX('PRICING'!$F$7:$F$16,MATCH(E$55,'PRICING'!$A$7:$A$16,0))/60)*IFERROR(INDEX('PRICING'!$B$20:$B$24,MATCH($B$54,'PRICING'!$A$20:$A$24,0)),1)*INDEX('PRICING'!$B$7:$B$16,MATCH(E$55,'PRICING'!$A$7:$A$16,0)),0)),"") | F57: =IFERROR(MAX(MinJob,ROUND(($A57/INDEX('PRICING'!$C$7:$C$16,MATCH(F$55,'PRICING'!$A$7:$A$16,0))+$B57*INDEX('PRICING'!$D$7:$D$16,MATCH(F$55,'PRICING'!$A$7:$A$16,0))/60+$C57*INDEX('PRICING'!$E$7:$E$16,MATCH(F$55,'PRICING'!$A$7:$A$16,0))/60+INDEX('PRICING'!$F$7:$F$16,MATCH(F$55,'PRICING'!$A$7:$A$16,0))/60)*IFERROR(INDEX('PRICING'!$B$20:$B$24,MATCH($B$54,'PRICING'!$A$20:$A$24,0)),1)*INDEX('PRICING'!$B$7:$B$16,MATCH(F$55,'PRICING'!$A$7:$A$16,0)),0)),"") | G57: =IFERROR(MAX(MinJob,ROUND(($A57/INDEX('PRICING'!$C$7:$C$16,MATCH(G$55,'PRICING'!$A$7:$A$16,0))+$B57*INDEX('PRICING'!$D$7:$D$16,MATCH(G$55,'PRICING'!$A$7:$A$16,0))/60+$C57*INDEX('PRICING'!$E$7:$E$16,MATCH(G$55,'PRICING'!$A$7:$A$16,0))/60+INDEX('PRICING'!$F$7:$F$16,MATCH(G$55,'PRICING'!$A$7:$A$16,0))/60)*IFERROR(INDEX('PRICING'!$B$20:$B$24,MATCH($B$54,'PRICING'!$A$20:$A$24,0)),1)*INDEX('PRICING'!$B$7:$B$16,MATCH(G$55,'PRICING'!$A$7:$A$16,0)),0)),"") | H57: =IFERROR(ROUND(D57*(1-INDEX('PRICING'!$B$28:$B$33,MATCH($D$54,'PRICING'!$A$28:$A$33,0))),0),"") | I57: =IFERROR(H57*INDEX('PRICING'!$D$28:$D$33,MATCH($D$54,'PRICING'!$A$28:$A$33,0)),"")
A58: 1500 | B58: 3 | C58: 2 | D58: =IFERROR(MAX(MinJob,ROUND(($A58/INDEX('PRICING'!$C$7:$C$16,MATCH(D$55,'PRICING'!$A$7:$A$16,0))+$B58*INDEX('PRICING'!$D$7:$D$16,MATCH(D$55,'PRICING'!$A$7:$A$16,0))/60+$C58*INDEX('PRICING'!$E$7:$E$16,MATCH(D$55,'PRICING'!$A$7:$A$16,0))/60+INDEX('PRICING'!$F$7:$F$16,MATCH(D$55,'PRICING'!$A$7:$A$16,0))/60)*IFERROR(INDEX('PRICING'!$B$20:$B$24,MATCH($B$54,'PRICING'!$A$20:$A$24,0)),1)*INDEX('PRICING'!$B$7:$B$16,MATCH(D$55,'PRICING'!$A$7:$A$16,0)),0)),"") | E58: =IFERROR(MAX(MinJob,ROUND(($A58/INDEX('PRICING'!$C$7:$C$16,MATCH(E$55,'PRICING'!$A$7:$A$16,0))+$B58*INDEX('PRICING'!$D$7:$D$16,MATCH(E$55,'PRICING'!$A$7:$A$16,0))/60+$C58*INDEX('PRICING'!$E$7:$E$16,MATCH(E$55,'PRICING'!$A$7:$A$16,0))/60+INDEX('PRICING'!$F$7:$F$16,MATCH(E$55,'PRICING'!$A$7:$A$16,0))/60)*IFERROR(INDEX('PRICING'!$B$20:$B$24,MATCH($B$54,'PRICING'!$A$20:$A$24,0)),1)*INDEX('PRICING'!$B$7:$B$16,MATCH(E$55,'PRICING'!$A$7:$A$16,0)),0)),"") | F58: =IFERROR(MAX(MinJob,ROUND(($A58/INDEX('PRICING'!$C$7:$C$16,MATCH(F$55,'PRICING'!$A$7:$A$16,0))+$B58*INDEX('PRICING'!$D$7:$D$16,MATCH(F$55,'PRICING'!$A$7:$A$16,0))/60+$C58*INDEX('PRICING'!$E$7:$E$16,MATCH(F$55,'PRICING'!$A$7:$A$16,0))/60+INDEX('PRICING'!$F$7:$F$16,MATCH(F$55,'PRICING'!$A$7:$A$16,0))/60)*IFERROR(INDEX('PRICING'!$B$20:$B$24,MATCH($B$54,'PRICING'!$A$20:$A$24,0)),1)*INDEX('PRICING'!$B$7:$B$16,MATCH(F$55,'PRICING'!$A$7:$A$16,0)),0)),"") | G58: =IFERROR(MAX(MinJob,ROUND(($A58/INDEX('PRICING'!$C$7:$C$16,MATCH(G$55,'PRICING'!$A$7:$A$16,0))+$B58*INDEX('PRICING'!$D$7:$D$16,MATCH(G$55,'PRICING'!$A$7:$A$16,0))/60+$C58*INDEX('PRICING'!$E$7:$E$16,MATCH(G$55,'PRICING'!$A$7:$A$16,0))/60+INDEX('PRICING'!$F$7:$F$16,MATCH(G$55,'PRICING'!$A$7:$A$16,0))/60)*IFERROR(INDEX('PRICING'!$B$20:$B$24,MATCH($B$54,'PRICING'!$A$20:$A$24,0)),1)*INDEX('PRICING'!$B$7:$B$16,MATCH(G$55,'PRICING'!$A$7:$A$16,0)),0)),"") | H58: =IFERROR(ROUND(D58*(1-INDEX('PRICING'!$B$28:$B$33,MATCH($D$54,'PRICING'!$A$28:$A$33,0))),0),"") | I58: =IFERROR(H58*INDEX('PRICING'!$D$28:$D$33,MATCH($D$54,'PRICING'!$A$28:$A$33,0)),"")
A59: 2000 | B59: 3 | C59: 2 | D59: =IFERROR(MAX(MinJob,ROUND(($A59/INDEX('PRICING'!$C$7:$C$16,MATCH(D$55,'PRICING'!$A$7:$A$16,0))+$B59*INDEX('PRICING'!$D$7:$D$16,MATCH(D$55,'PRICING'!$A$7:$A$16,0))/60+$C59*INDEX('PRICING'!$E$7:$E$16,MATCH(D$55,'PRICING'!$A$7:$A$16,0))/60+INDEX('PRICING'!$F$7:$F$16,MATCH(D$55,'PRICING'!$A$7:$A$16,0))/60)*IFERROR(INDEX('PRICING'!$B$20:$B$24,MATCH($B$54,'PRICING'!$A$20:$A$24,0)),1)*INDEX('PRICING'!$B$7:$B$16,MATCH(D$55,'PRICING'!$A$7:$A$16,0)),0)),"") | E59: =IFERROR(MAX(MinJob,ROUND(($A59/INDEX('PRICING'!$C$7:$C$16,MATCH(E$55,'PRICING'!$A$7:$A$16,0))+$B59*INDEX('PRICING'!$D$7:$D$16,MATCH(E$55,'PRICING'!$A$7:$A$16,0))/60+$C59*INDEX('PRICING'!$E$7:$E$16,MATCH(E$55,'PRICING'!$A$7:$A$16,0))/60+INDEX('PRICING'!$F$7:$F$16,MATCH(E$55,'PRICING'!$A$7:$A$16,0))/60)*IFERROR(INDEX('PRICING'!$B$20:$B$24,MATCH($B$54,'PRICING'!$A$20:$A$24,0)),1)*INDEX('PRICING'!$B$7:$B$16,MATCH(E$55,'PRICING'!$A$7:$A$16,0)),0)),"") | F59: =IFERROR(MAX(MinJob,ROUND(($A59/INDEX('PRICING'!$C$7:$C$16,MATCH(F$55,'PRICING'!$A$7:$A$16,0))+$B59*INDEX('PRICING'!$D$7:$D$16,MATCH(F$55,'PRICING'!$A$7:$A$16,0))/60+$C59*INDEX('PRICING'!$E$7:$E$16,MATCH(F$55,'PRICING'!$A$7:$A$16,0))/60+INDEX('PRICING'!$F$7:$F$16,MATCH(F$55,'PRICING'!$A$7:$A$16,0))/60)*IFERROR(INDEX('PRICING'!$B$20:$B$24,MATCH($B$54,'PRICING'!$A$20:$A$24,0)),1)*INDEX('PRICING'!$B$7:$B$16,MATCH(F$55,'PRICING'!$A$7:$A$16,0)),0)),"") | G59: =IFERROR(MAX(MinJob,ROUND(($A59/INDEX('PRICING'!$C$7:$C$16,MATCH(G$55,'PRICING'!$A$7:$A$16,0))+$B59*INDEX('PRICING'!$D$7:$D$16,MATCH(G$55,'PRICING'!$A$7:$A$16,0))/60+$C59*INDEX('PRICING'!$E$7:$E$16,MATCH(G$55,'PRICING'!$A$7:$A$16,0))/60+INDEX('PRICING'!$F$7:$F$16,MATCH(G$55,'PRICING'!$A$7:$A$16,0))/60)*IFERROR(INDEX('PRICING'!$B$20:$B$24,MATCH($B$54,'PRICING'!$A$20:$A$24,0)),1)*INDEX('PRICING'!$B$7:$B$16,MATCH(G$55,'PRICING'!$A$7:$A$16,0)),0)),"") | H59: =IFERROR(ROUND(D59*(1-INDEX('PRICING'!$B$28:$B$33,MATCH($D$54,'PRICING'!$A$28:$A$33,0))),0),"") | I59: =IFERROR(H59*INDEX('PRICING'!$D$28:$D$33,MATCH($D$54,'PRICING'!$A$28:$A$33,0)),"")
A60: 2500 | B60: 4 | C60: 3 | D60: =IFERROR(MAX(MinJob,ROUND(($A60/INDEX('PRICING'!$C$7:$C$16,MATCH(D$55,'PRICING'!$A$7:$A$16,0))+$B60*INDEX('PRICING'!$D$7:$D$16,MATCH(D$55,'PRICING'!$A$7:$A$16,0))/60+$C60*INDEX('PRICING'!$E$7:$E$16,MATCH(D$55,'PRICING'!$A$7:$A$16,0))/60+INDEX('PRICING'!$F$7:$F$16,MATCH(D$55,'PRICING'!$A$7:$A$16,0))/60)*IFERROR(INDEX('PRICING'!$B$20:$B$24,MATCH($B$54,'PRICING'!$A$20:$A$24,0)),1)*INDEX('PRICING'!$B$7:$B$16,MATCH(D$55,'PRICING'!$A$7:$A$16,0)),0)),"") | E60: =IFERROR(MAX(MinJob,ROUND(($A60/INDEX('PRICING'!$C$7:$C$16,MATCH(E$55,'PRICING'!$A$7:$A$16,0))+$B60*INDEX('PRICING'!$D$7:$D$16,MATCH(E$55,'PRICING'!$A$7:$A$16,0))/60+$C60*INDEX('PRICING'!$E$7:$E$16,MATCH(E$55,'PRICING'!$A$7:$A$16,0))/60+INDEX('PRICING'!$F$7:$F$16,MATCH(E$55,'PRICING'!$A$7:$A$16,0))/60)*IFERROR(INDEX('PRICING'!$B$20:$B$24,MATCH($B$54,'PRICING'!$A$20:$A$24,0)),1)*INDEX('PRICING'!$B$7:$B$16,MATCH(E$55,'PRICING'!$A$7:$A$16,0)),0)),"") | F60: =IFERROR(MAX(MinJob,ROUND(($A60/INDEX('PRICING'!$C$7:$C$16,MATCH(F$55,'PRICING'!$A$7:$A$16,0))+$B60*INDEX('PRICING'!$D$7:$D$16,MATCH(F$55,'PRICING'!$A$7:$A$16,0))/60+$C60*INDEX('PRICING'!$E$7:$E$16,MATCH(F$55,'PRICING'!$A$7:$A$16,0))/60+INDEX('PRICING'!$F$7:$F$16,MATCH(F$55,'PRICING'!$A$7:$A$16,0))/60)*IFERROR(INDEX('PRICING'!$B$20:$B$24,MATCH($B$54,'PRICING'!$A$20:$A$24,0)),1)*INDEX('PRICING'!$B$7:$B$16,MATCH(F$55,'PRICING'!$A$7:$A$16,0)),0)),"") | G60: =IFERROR(MAX(MinJob,ROUND(($A60/INDEX('PRICING'!$C$7:$C$16,MATCH(G$55,'PRICING'!$A$7:$A$16,0))+$B60*INDEX('PRICING'!$D$7:$D$16,MATCH(G$55,'PRICING'!$A$7:$A$16,0))/60+$C60*INDEX('PRICING'!$E$7:$E$16,MATCH(G$55,'PRICING'!$A$7:$A$16,0))/60+INDEX('PRICING'!$F$7:$F$16,MATCH(G$55,'PRICING'!$A$7:$A$16,0))/60)*IFERROR(INDEX('PRICING'!$B$20:$B$24,MATCH($B$54,'PRICING'!$A$20:$A$24,0)),1)*INDEX('PRICING'!$B$7:$B$16,MATCH(G$55,'PRICING'!$A$7:$A$16,0)),0)),"") | H60: =IFERROR(ROUND(D60*(1-INDEX('PRICING'!$B$28:$B$33,MATCH($D$54,'PRICING'!$A$28:$A$33,0))),0),"") | I60: =IFERROR(H60*INDEX('PRICING'!$D$28:$D$33,MATCH($D$54,'PRICING'!$A$28:$A$33,0)),"")
A61: 3000 | B61: 4 | C61: 3 | D61: =IFERROR(MAX(MinJob,ROUND(($A61/INDEX('PRICING'!$C$7:$C$16,MATCH(D$55,'PRICING'!$A$7:$A$16,0))+$B61*INDEX('PRICING'!$D$7:$D$16,MATCH(D$55,'PRICING'!$A$7:$A$16,0))/60+$C61*INDEX('PRICING'!$E$7:$E$16,MATCH(D$55,'PRICING'!$A$7:$A$16,0))/60+INDEX('PRICING'!$F$7:$F$16,MATCH(D$55,'PRICING'!$A$7:$A$16,0))/60)*IFERROR(INDEX('PRICING'!$B$20:$B$24,MATCH($B$54,'PRICING'!$A$20:$A$24,0)),1)*INDEX('PRICING'!$B$7:$B$16,MATCH(D$55,'PRICING'!$A$7:$A$16,0)),0)),"") | E61: =IFERROR(MAX(MinJob,ROUND(($A61/INDEX('PRICING'!$C$7:$C$16,MATCH(E$55,'PRICING'!$A$7:$A$16,0))+$B61*INDEX('PRICING'!$D$7:$D$16,MATCH(E$55,'PRICING'!$A$7:$A$16,0))/60+$C61*INDEX('PRICING'!$E$7:$E$16,MATCH(E$55,'PRICING'!$A$7:$A$16,0))/60+INDEX('PRICING'!$F$7:$F$16,MATCH(E$55,'PRICING'!$A$7:$A$16,0))/60)*IFERROR(INDEX('PRICING'!$B$20:$B$24,MATCH($B$54,'PRICING'!$A$20:$A$24,0)),1)*INDEX('PRICING'!$B$7:$B$16,MATCH(E$55,'PRICING'!$A$7:$A$16,0)),0)),"") | F61: =IFERROR(MAX(MinJob,ROUND(($A61/INDEX('PRICING'!$C$7:$C$16,MATCH(F$55,'PRICING'!$A$7:$A$16,0))+$B61*INDEX('PRICING'!$D$7:$D$16,MATCH(F$55,'PRICING'!$A$7:$A$16,0))/60+$C61*INDEX('PRICING'!$E$7:$E$16,MATCH(F$55,'PRICING'!$A$7:$A$16,0))/60+INDEX('PRICING'!$F$7:$F$16,MATCH(F$55,'PRICING'!$A$7:$A$16,0))/60)*IFERROR(INDEX('PRICING'!$B$20:$B$24,MATCH($B$54,'PRICING'!$A$20:$A$24,0)),1)*INDEX('PRICING'!$B$7:$B$16,MATCH(F$55,'PRICING'!$A$7:$A$16,0)),0)),"") | G61: =IFERROR(MAX(MinJob,ROUND(($A61/INDEX('PRICING'!$C$7:$C$16,MATCH(G$55,'PRICING'!$A$7:$A$16,0))+$B61*INDEX('PRICING'!$D$7:$D$16,MATCH(G$55,'PRICING'!$A$7:$A$16,0))/60+$C61*INDEX('PRICING'!$E$7:$E$16,MATCH(G$55,'PRICING'!$A$7:$A$16,0))/60+INDEX('PRICING'!$F$7:$F$16,MATCH(G$55,'PRICING'!$A$7:$A$16,0))/60)*IFERROR(INDEX('PRICING'!$B$20:$B$24,MATCH($B$54,'PRICING'!$A$20:$A$24,0)),1)*INDEX('PRICING'!$B$7:$B$16,MATCH(G$55,'PRICING'!$A$7:$A$16,0)),0)),"") | H61: =IFERROR(ROUND(D61*(1-INDEX('PRICING'!$B$28:$B$33,MATCH($D$54,'PRICING'!$A$28:$A$33,0))),0),"") | I61: =IFERROR(H61*INDEX('PRICING'!$D$28:$D$33,MATCH($D$54,'PRICING'!$A$28:$A$33,0)),"")
A62: 3500 | B62: 5 | C62: 4 | D62: =IFERROR(MAX(MinJob,ROUND(($A62/INDEX('PRICING'!$C$7:$C$16,MATCH(D$55,'PRICING'!$A$7:$A$16,0))+$B62*INDEX('PRICING'!$D$7:$D$16,MATCH(D$55,'PRICING'!$A$7:$A$16,0))/60+$C62*INDEX('PRICING'!$E$7:$E$16,MATCH(D$55,'PRICING'!$A$7:$A$16,0))/60+INDEX('PRICING'!$F$7:$F$16,MATCH(D$55,'PRICING'!$A$7:$A$16,0))/60)*IFERROR(INDEX('PRICING'!$B$20:$B$24,MATCH($B$54,'PRICING'!$A$20:$A$24,0)),1)*INDEX('PRICING'!$B$7:$B$16,MATCH(D$55,'PRICING'!$A$7:$A$16,0)),0)),"") | E62: =IFERROR(MAX(MinJob,ROUND(($A62/INDEX('PRICING'!$C$7:$C$16,MATCH(E$55,'PRICING'!$A$7:$A$16,0))+$B62*INDEX('PRICING'!$D$7:$D$16,MATCH(E$55,'PRICING'!$A$7:$A$16,0))/60+$C62*INDEX('PRICING'!$E$7:$E$16,MATCH(E$55,'PRICING'!$A$7:$A$16,0))/60+INDEX('PRICING'!$F$7:$F$16,MATCH(E$55,'PRICING'!$A$7:$A$16,0))/60)*IFERROR(INDEX('PRICING'!$B$20:$B$24,MATCH($B$54,'PRICING'!$A$20:$A$24,0)),1)*INDEX('PRICING'!$B$7:$B$16,MATCH(E$55,'PRICING'!$A$7:$A$16,0)),0)),"") | F62: =IFERROR(MAX(MinJob,ROUND(($A62/INDEX('PRICING'!$C$7:$C$16,MATCH(F$55,'PRICING'!$A$7:$A$16,0))+$B62*INDEX('PRICING'!$D$7:$D$16,MATCH(F$55,'PRICING'!$A$7:$A$16,0))/60+$C62*INDEX('PRICING'!$E$7:$E$16,MATCH(F$55,'PRICING'!$A$7:$A$16,0))/60+INDEX('PRICING'!$F$7:$F$16,MATCH(F$55,'PRICING'!$A$7:$A$16,0))/60)*IFERROR(INDEX('PRICING'!$B$20:$B$24,MATCH($B$54,'PRICING'!$A$20:$A$24,0)),1)*INDEX('PRICING'!$B$7:$B$16,MATCH(F$55,'PRICING'!$A$7:$A$16,0)),0)),"") | G62: =IFERROR(MAX(MinJob,ROUND(($A62/INDEX('PRICING'!$C$7:$C$16,MATCH(G$55,'PRICING'!$A$7:$A$16,0))+$B62*INDEX('PRICING'!$D$7:$D$16,MATCH(G$55,'PRICING'!$A$7:$A$16,0))/60+$C62*INDEX('PRICING'!$E$7:$E$16,MATCH(G$55,'PRICING'!$A$7:$A$16,0))/60+INDEX('PRICING'!$F$7:$F$16,MATCH(G$55,'PRICING'!$A$7:$A$16,0))/60)*IFERROR(INDEX('PRICING'!$B$20:$B$24,MATCH($B$54,'PRICING'!$A$20:$A$24,0)),1)*INDEX('PRICING'!$B$7:$B$16,MATCH(G$55,'PRICING'!$A$7:$A$16,0)),0)),"") | H62: =IFERROR(ROUND(D62*(1-INDEX('PRICING'!$B$28:$B$33,MATCH($D$54,'PRICING'!$A$28:$A$33,0))),0),"") | I62: =IFERROR(H62*INDEX('PRICING'!$D$28:$D$33,MATCH($D$54,'PRICING'!$A$28:$A$33,0)),"")
A63: 4000 | B63: 5 | C63: 4 | D63: =IFERROR(MAX(MinJob,ROUND(($A63/INDEX('PRICING'!$C$7:$C$16,MATCH(D$55,'PRICING'!$A$7:$A$16,0))+$B63*INDEX('PRICING'!$D$7:$D$16,MATCH(D$55,'PRICING'!$A$7:$A$16,0))/60+$C63*INDEX('PRICING'!$E$7:$E$16,MATCH(D$55,'PRICING'!$A$7:$A$16,0))/60+INDEX('PRICING'!$F$7:$F$16,MATCH(D$55,'PRICING'!$A$7:$A$16,0))/60)*IFERROR(INDEX('PRICING'!$B$20:$B$24,MATCH($B$54,'PRICING'!$A$20:$A$24,0)),1)*INDEX('PRICING'!$B$7:$B$16,MATCH(D$55,'PRICING'!$A$7:$A$16,0)),0)),"") | E63: =IFERROR(MAX(MinJob,ROUND(($A63/INDEX('PRICING'!$C$7:$C$16,MATCH(E$55,'PRICING'!$A$7:$A$16,0))+$B63*INDEX('PRICING'!$D$7:$D$16,MATCH(E$55,'PRICING'!$A$7:$A$16,0))/60+$C63*INDEX('PRICING'!$E$7:$E$16,MATCH(E$55,'PRICING'!$A$7:$A$16,0))/60+INDEX('PRICING'!$F$7:$F$16,MATCH(E$55,'PRICING'!$A$7:$A$16,0))/60)*IFERROR(INDEX('PRICING'!$B$20:$B$24,MATCH($B$54,'PRICING'!$A$20:$A$24,0)),1)*INDEX('PRICING'!$B$7:$B$16,MATCH(E$55,'PRICING'!$A$7:$A$16,0)),0)),"") | F63: =IFERROR(MAX(MinJob,ROUND(($A63/INDEX('PRICING'!$C$7:$C$16,MATCH(F$55,'PRICING'!$A$7:$A$16,0))+$B63*INDEX('PRICING'!$D$7:$D$16,MATCH(F$55,'PRICING'!$A$7:$A$16,0))/60+$C63*INDEX('PRICING'!$E$7:$E$16,MATCH(F$55,'PRICING'!$A$7:$A$16,0))/60+INDEX('PRICING'!$F$7:$F$16,MATCH(F$55,'PRICING'!$A$7:$A$16,0))/60)*IFERROR(INDEX('PRICING'!$B$20:$B$24,MATCH($B$54,'PRICING'!$A$20:$A$24,0)),1)*INDEX('PRICING'!$B$7:$B$16,MATCH(F$55,'PRICING'!$A$7:$A$16,0)),0)),"") | G63: =IFERROR(MAX(MinJob,ROUND(($A63/INDEX('PRICING'!$C$7:$C$16,MATCH(G$55,'PRICING'!$A$7:$A$16,0))+$B63*INDEX('PRICING'!$D$7:$D$16,MATCH(G$55,'PRICING'!$A$7:$A$16,0))/60+$C63*INDEX('PRICING'!$E$7:$E$16,MATCH(G$55,'PRICING'!$A$7:$A$16,0))/60+INDEX('PRICING'!$F$7:$F$16,MATCH(G$55,'PRICING'!$A$7:$A$16,0))/60)*IFERROR(INDEX('PRICING'!$B$20:$B$24,MATCH($B$54,'PRICING'!$A$20:$A$24,0)),1)*INDEX('PRICING'!$B$7:$B$16,MATCH(G$55,'PRICING'!$A$7:$A$16,0)),0)),"") | H63: =IFERROR(ROUND(D63*(1-INDEX('PRICING'!$B$28:$B$33,MATCH($D$54,'PRICING'!$A$28:$A$33,0))),0),"") | I63: =IFERROR(H63*INDEX('PRICING'!$D$28:$D$33,MATCH($D$54,'PRICING'!$A$28:$A$33,0)),"")
A64: Rate card uses: time = (sq ft ÷ sq ft per hr + bedrooms × min + bathrooms × min + setup) × condition; price = MAX(minimum job price, time × billing rate). Edit rows 56–63 to match the homes you usually quote.

Sheet JOBS
A1: JOBS
A2: Every job, one row. Fill the white columns; payment status, costs and estimated profit are automatic. Link recurring visits with a Plan ID. Log payments in REVENUE and trips in MILEAGE.
A3: ← Start Here | B3: Dashboard →
A4: Job ID | B4: Date | C4: Start Time | D4: Customer | E4: Property | F4: Service | G4: Recurring Plan ID | H4: Assigned Worker (lead) | I4: Crew Size | J4: Est. Labor Hrs (optional) | K4: Actual Labor Hrs | L4: Price (before tax) | M4: Tax % | N4: Supplies $ (blank = auto) | O4: Status | P4: Notes | Q4: Auto Est. Hrs ⚙ | R4: Labor Hrs Used ⚙ | S4: Invoice Total ⚙ | T4: Paid ⚙ | U4: Balance Due ⚙ | V4: Payment Status ⚙ | W4: Pay Rate Used ⚙ | X4: Labor Cost ⚙ | Y4: Supplies Cost ⚙ | Z4: Miles (from MILEAGE) ⚙ | AA4: Vehicle Cost ⚙ | AB4: Payment Fees ⚙ | AC4: Gross Profit (est.) ⚙ | AD4: Gross Margin ⚙ | AE4: Revenue / Labor Hr ⚙ | AF4: Hours Over (+) / Under (−) ⚙ | AG4: QC Score ⚙ | AH4: Month ⚙ | AI4: Customer Type ⚙ | AJ4: Sort Time ⚙ | AK4: Schedule Key ⚙ | AL4: Unpaid Order ⚙
A5: J-0001 | B5: 46031 | C5: 0.33333333 | D5: Dana Collins | E5: 84 Hawthorn Road, Lakeview (fictional) | F5: Deep Clean | H5: Maria Lopez | I5: 2 | K5: 9.2 | L5: 450 | M5: 0 | O5: Completed | P5: Initial deep clean | Q5: =IF(OR(F5="",E5=""),"",IFERROR(IF(INDEX('PROPERTIES'!$F$5:$F$404,MATCH(E5,'PROPERTIES'!$B$5:$B$404,0))=0,"",ROUND((INDEX('PROPERTIES'!$F$5:$F$404,MATCH(E5,'PROPERTIES'!$B$5:$B$404,0))/INDEX('PRICING'!$C$7:$C$16,MATCH(F5,'PRICING'!$A$7:$A$16,0))+INDEX('PROPERTIES'!$G$5:$G$404,MATCH(E5,'PROPERTIES'!$B$5:$B$404,0))*INDEX('PRICING'!$D$7:$D$16,MATCH(F5,'PRICING'!$A$7:$A$16,0))/60+INDEX('PROPERTIES'!$H$5:$H$404,MATCH(E5,'PROPERTIES'!$B$5:$B$404,0))*INDEX('PRICING'!$E$7:$E$16,MATCH(F5,'PRICING'!$A$7:$A$16,0))/60+INDEX('PRICING'!$F$7:$F$16,MATCH(F5,'PRICING'!$A$7:$A$16,0))/60),2)),"")) | R5: =IF(B5="","",IF(N(K5)>0,K5,IF(N(J5)>0,J5,N(Q5)))) | S5: =IF(L5="","",ROUND(L5*(1+N(M5)),2)) | T5: =IF(B5="","",SUMIFS('REVENUE'!$C$5:$C$1504,'REVENUE'!$B$5:$B$1504,A5)) | U5: =IF(B5="","",IF(O5="Completed",MAX(0,N(S5)-T5),"")) | V5: =IF(B5="","",IF(O5<>"Completed",IF(T5>0,"Deposit","—"),IF(U5<=0.005,"Paid",IF(T5>0,"Partial","Unpaid")))) | W5: =IF(B5="","",IFERROR(1/(1/INDEX('STAFF & TASKS'!$C$5:$C$24,MATCH(H5,'STAFF & TASKS'!$A$5:$A$24,0))),PayRate)) | X5: =IF(B5="","",IF(OR(O5="Cancelled",O5="No-Show"),"",ROUND(R5*W5*(1+Burden),2))) | Y5: =IF(B5="","",IF(OR(O5="Cancelled",O5="No-Show"),"",IF(N5<>"",N5,ROUND(R5*SupHr*IFERROR(INDEX('PRICING'!$G$7:$G$16,MATCH(F5,'PRICING'!$A$7:$A$16,0)),1),2)))) | Z5: =IF(B5="","",SUMIFS('MILEAGE'!$J$5:$J$1504,'MILEAGE'!$B$5:$B$1504,A5)) | AA5: =IF(B5="","",ROUND(Z5*MileRate,2)) | AB5: =IF(B5="","",SUMIFS('REVENUE'!$J$5:$J$1504,'REVENUE'!$B$5:$B$1504,A5)) | AC5: =IF(L5="","",IF(OR(O5="Cancelled",O5="No-Show"),"",L5-N(X5)-N(Y5)-AA5-AB5)) | AD5: =IF(OR(AC5="",N(L5)=0),"",AC5/L5) | AE5: =IF(OR(AC5="",N(R5)=0),"",L5/R5) | AF5: =IF(OR(N(K5)=0,N(J5)+N(Q5)=0),"",K5-IF(N(J5)>0,J5,Q5)) | AG5: =IF(B5="","",IFERROR(AVERAGEIFS('QUALITY CONTROL'!$M$5:$M$304,'QUALITY CONTROL'!$B$5:$B$304,A5),"")) | AH5: =IF(B5="","",DATE(YEAR(B5),MONTH(B5),1)) | AI5: =IF(D5="","",IFERROR(INDEX('CUSTOMERS'!$E$5:$E$404,MATCH(D5,'CUSTOMERS'!$B$5:$B$404,0)),"")) | AJ5: =IF(B5="","",N(C5)) | AK5: =IF(OR(B5="",O5="Cancelled",O5="Rescheduled"),"",B5&"|"&(COUNTIFS('JOBS'!$B$5:$B$1504,B5,'JOBS'!$AJ$5:$AJ$1504,"<"&AJ5,'JOBS'!$O$5:$O$1504,"<>Cancelled",'JOBS'!$O$5:$O$1504,"<>Rescheduled")+COUNTIFS($B$5:B5,B5,$AJ$5:AJ5,AJ5,$O$5:O5,"<>Cancelled",$O$5:O5,"<>Rescheduled"))) | AL5: =IF(N(U5)<=0.005,"",COUNTIFS('JOBS'!$U$5:$U$1504,">0.005",'JOBS'!$B$5:$B$1504,"<"&B5)+COUNTIFS($U$5:U5,">0.005",$B$5:B5,B5))
